Workbook

Sheet INDEX
B3: TIME SERIES MODELING IN QUANTITATIVE FINANCE
B4: PART 1 OF 2 — Foundations & Excel Intuition | Part 2: Python Implementation
B5: ────────────────────────────────────────────────────────────────────────────────
B6: SERIES OVERVIEW
B7: This is a two-part project. Part 1 (this workbook) explains foundational concepts using a simulated illustrative return series and live Excel formulas. Part 2 (Python Jupyter notebook) applies every concept to real S&P 500 data, adds PACF and AIC/BIC model selection, and fits GARCH(1,1) via Maximum Likelihood. Start here; continue in Python.
B8: TAB | C8: CONCEPT | D8: WHAT YOU WILL UNDERSTAND | E8: NOTES
B9: 1 - RETURNS | C9: What are Financial Returns? | D9: Why we use log-returns, not prices; additivity across time | E9: '=LN(today/yesterday)*100 [built live in Excel]
B10: 2 - STYLIZED FACTS | C10: How Returns Actually Behave | D10: Fat tails, near-zero autocorrelation, volatility clustering | E10: Histogram, return chart, squared-returns chart
B11: 3 - STATIONARITY | C11: Why Prices Can't Be Modeled Directly | D11: What stationarity means and why returns satisfy it, prices don't | E11: Random walk vs. stationary process side-by-side
B12: 4 - AUTOCORRELATION | C12: Does the Past Predict the Future? | D12: ACF computed manually; raw returns vs. squared returns | E12: CORREL function, hand-built ACF bar chart
B13: 5 - ARIMA | C13: Modeling the Mean | D13: What AR, MA, and I each do in plain English; why ARIMA finds φ̂ ≈ −0.17 and R² ≈ 3% on a simulated illustrative series — ARIMA hands off to GARCH | E13: AR(1), MA(1), ARIMA(1,0,1) simulated & fitted to a simulated illustrative return series; fitted vs. actual charts
B14: 6 - GARCH MOTIVATION | C14: Volatility Modeling & Risk Measurement | D14: GARCH(1,1) captures variance clustering; daily VaR 95%/99% & Expected Shortfall derived from GARCH σ; Kupiec backtest confirms calibration; 3× vol range in the simulated series | E14: GARCH(1,1) recursion formula; VaR/ES time-series model; Kupiec backtest table; 5 embedded charts

Sheet 1.RETURNS
A2: SECTION 1 — WHAT ARE FINANCIAL RETURNS? [Prices below are a simulated illustrative series; base price = Dec 30, 2022; returns run Jan 3 – Dec 19, 2023]
A3: Date | B3: Price ($) | C3: Simple Return | D3: Log-Return | E3: Diff
A4: 30-Dec-2022 | B4: 4500 | C4: n/a | D4: n/a | F4: WHY DO WE USE RETURNS, NOT PRICES? | I4: ADDITIVITY PROOF — Read alongside the explanation box
A5: 03-Jan-2023 | B5: 4526.56 | C5: =B5/B4-1 -> 0.0059022222 | D5: =LN(B5/B4) -> 0.0058848723 | E5: =D5-C5 -> -1.7349878e-05 | I5: Day 1 log-return | J5: =LN(B5/B4)*100 -> 0.58848723
A6: 04-Jan-2023 | B6: 4521.08 | C6: =B6/B5-1 -> -0.0012106324 | D6: =LN(B6/B5) -> -0.0012113658 | E6: =D6-C6 -> -7.3340734e-07 | F6: A stock price on its own tells you almost nothing without context. | I6: Day 2 log-return | J6: =LN(B6/B5)*100 -> -0.12113658
A7: 05-Jan-2023 | B7: 4551.34 | C7: =B7/B6-1 -> 0.006693091 | D7: =LN(B7/B6) -> 0.0066707917 | E7: =D7-C7 -> -2.2299288e-05 | F7: A price of $4,500 is high for one stock and cheap for another. | I7: 2-day log-return (direct) | J7: =LN(B6/B4)*100 -> 0.46735066
A8: 06-Jan-2023 | B8: 4625.05 | C8: =B8/B7-1 -> 0.01619523 | D8: =LN(B8/B7) -> 0.016065487 | E8: =D8-C8 -> -0.0001297438 | F8: Returns — percentage changes from one day to the next — are | I8: Sum of day 1 + day 2 | J8: =J5+J6 -> 0.46735066
A9: 09-Jan-2023 | B9: 4613.71 | C9: =B9/B8-1 -> -0.0024518654 | D9: =LN(B9/B8) -> -0.0024548761 | E9: =D9-C9 -> -3.0107442e-06 | F9: comparable across time, across assets, and across markets. | I9: Are they equal? | J9: =IF(ABS(J7-J8)<0.0001,"YES — they are equal!","Check formulas") -> YES — they are equal! | L9: ← Should be YES
A10: 10-Jan-2023 | B10: 4604.44 | C10: =B10/B9-1 -> -0.002009229 | D10: =LN(B10/B9) -> -0.0020112502 | E10: =D10-C10 -> -2.0212085e-06
A11: 11-Jan-2023 | B11: 4675.59 | C11: =B11/B10-1 -> 0.015452476 | D11: =LN(B11/B10) -> 0.015334303 | E11: =D11-C11 -> -0.00011817368 | F11: WHY LOG-RETURNS SPECIFICALLY? | I11: SIMPLE RETURNS — Additivity Does NOT Hold
A12: 12-Jan-2023 | B12: 4717.27 | C12: =B12/B11-1 -> 0.008914383 | D12: =LN(B12/B11) -> 0.0088748844 | E12: =D12-C12 -> -3.9498549e-05 | I12: Day 1 simple return | J12: =(B5/B4-1)*100 -> 0.59022222
A13: 13-Jan-2023 | B13: 4694.58 | C13: =B13/B12-1 -> -0.0048099854 | D13: =LN(B13/B12) -> -0.0048215906 | E13: =D13-C13 -> -1.1605209e-05 | F13: The log-return is defined as: r_t = LN(P_t / P_{t-1}) × 100 | I13: Day 2 simple return | J13: =(B6/B5-1)*100 -> -0.12106324
A14: 16-Jan-2023 | B14: 4720.53 | C14: =B14/B13-1 -> 0.005527651 | D14: =LN(B14/B13) -> 0.0055124296 | E14: =D14-C14 -> -1.5221396e-05 | I14: 2-day simple return (direct) | J14: =(B6/B4-1)*100 -> 0.46844444
A15: 17-Jan-2023 | B15: 4700.32 | C15: =B15/B14-1 -> -0.0042812989 | D15: =LN(B15/B14) -> -0.0042904899 | E15: =D15-C15 -> -9.1910026e-06 | F15: Three reasons we prefer it over simple returns: | I15: Sum of day 1 + day 2 | J15: =J12+J13 -> 0.46915899
A16: 18-Jan-2023 | B16: 4680.56 | C16: =B16/B15-1 -> -0.0042039691 | D16: =LN(B16/B15) -> -0.0042128306 | E16: =D16-C16 -> -8.8615225e-06 | I16: Are they equal? | J16: =IF(ABS(J14-J15)<0.0001,"YES — they are equal!","NO — simple returns do NOT add!") -> NO — simple returns do NOT add! | L16: ← Should be NO
A17: 19-Jan-2023 | B17: 4692.73 | C17: =B17/B16-1 -> 0.0026001162 | D17: =LN(B17/B16) -> 0.0025967418 | E17: =D17-C17 -> -3.3744541e-06 | F17: 1. ADDITIVITY: Log-returns add up across time.
A18: 20-Jan-2023 | B18: 4603.62 | C18: =B18/B17-1 -> -0.018988947 | D18: =LN(B18/B17) -> -0.019171552 | E18: =D18-C18 -> -0.0001826054 | F18: A 5-day return = sum of 5 daily log-returns. Simple returns do not add.
A19: 23-Jan-2023 | B19: 4510.34 | C19: =B19/B18-1 -> -0.020262315 | D19: =LN(B19/B18) -> -0.020470412 | E19: =D19-C19 -> -0.00020809652
A20: 24-Jan-2023 | B20: 4481.22 | C20: =B20/B19-1 -> -0.006456276 | D20: =LN(B20/B19) -> -0.0064772079 | E20: =D20-C20 -> -2.0931893e-05 | F20: 2. SYMMETRY: A +10% log-return followed by -10% gets you back to the beginning.
A21: 25-Jan-2023 | B21: 4437.53 | C21: =B21/B20-1 -> -0.0097495771 | D21: =LN(B21/B20) -> -0.0097974154 | E21: =D21-C21 -> -4.7838317e-05 | F21: With simple returns, +10% then -10% loses you money (×1.10 × 0.90 = 0.99).
A22: 26-Jan-2023 | B22: 4453.62 | C22: =B22/B21-1 -> 0.003625891 | D22: =LN(B22/B21) -> 0.0036193333 | E22: =D22-C22 -> -6.5576958e-06
A23: 27-Jan-2023 | B23: 4414.81 | C23: =B23/B22-1 -> -0.0087142594 | D23: =LN(B23/B22) -> -0.0087524506 | E23: =D23-C23 -> -3.8191192e-05 | F23: 3. APPROXIMATION: For small daily moves (under ~2%), log ≈ simple return.
A24: 30-Jan-2023 | B24: 4352.34 | C24: =B24/B23-1 -> -0.014150099 | D24: =LN(B24/B23) -> -0.014251167 | E24: =D24-C24 -> -0.0001010672 | F24: So we get all the math benefits at almost no practical cost.
A25: 31-Jan-2023 | B25: 4425.34 | C25: =B25/B24-1 -> 0.016772587 | D25: =LN(B25/B24) -> 0.01663348 | E25: =D25-C25 -> -0.00013910654
A26: 01-Feb-2023 | B26: 4415.05 | C26: =B26/B25-1 -> -0.0023252451 | D26: =LN(B26/B25) -> -0.0023279526 | E26: =D26-C26 -> -2.7075803e-06 | F26: SEE THE DATA TABLE TO THE LEFT →
A27: 02-Feb-2023 | B27: 4419.19 | C27: =B27/B26-1 -> 0.00093770172 | D27: =LN(B27/B26) -> 0.00093726236 | E27: =D27-C27 -> -4.3936762e-07 | F27: Look at how Column D (log-return) and Column E (simple return) compare.
A28: 03-Feb-2023 | B28: 4359.34 | C28: =B28/B27-1 -> -0.013543206 | D28: =LN(B28/B27) -> -0.013635752 | E28: =D28-C28 -> -9.254574e-05 | F28: On normal days they are nearly identical. This confirms the approximation.
A29: 06-Feb-2023 | B29: 4335.03 | C29: =B29/B28-1 -> -0.0055765322 | D29: =LN(B29/B28) -> -0.0055921391 | E29: =D29-C29 -> -1.5606904e-05
A30: 07-Feb-2023 | B30: 4341.04 | C30: =B30/B29-1 -> 0.0013863803 | D30: =LN(B30/B29) -> 0.0013854201 | E30: =D30-C30 -> -9.601378e-07 | F30: LIVE PROOF: Additivity of Log-Returns (see rows 7-10 in data)
A31: 08-Feb-2023 | B31: 4293.48 | C31: =B31/B30-1 -> -0.0109559 | D31: =LN(B31/B30) -> -0.011016358 | E31: =D31-C31 -> -6.0457858e-05 | F31: Cell D9 = LN(C9/C8)*100 ← 1-day log-return
A32: 09-Feb-2023 | B32: 4312.13 | C32: =B32/B31-1 -> 0.0043437957 | D32: =LN(B32/B31) -> 0.0043343887 | E32: =D32-C32 -> -9.4070489e-06 | F32: Cell D10 = LN(C10/C9)*100 ← next 1-day log-return
A33: 10-Feb-2023 | B33: 4286.49 | C33: =B33/B32-1 -> -0.0059460174 | D33: =LN(B33/B32) -> -0.0059637653 | E33: =D33-C33 -> -1.7747949e-05 | F33: Cell D11 = LN(C10/C8)*100 ← 2-day log-return
A34: 13-Feb-2023 | B34: 4274.65 | C34: =B34/B33-1 -> -0.0027621667 | D34: =LN(B34/B33) -> -0.0027659885 | E34: =D34-C34 -> -3.8218218e-06 | F34: Notice: D9 + D10 = D11 (exactly, to many decimal places)
A35: 14-Feb-2023 | B35: 4251.31 | C35: =B35/B34-1 -> -0.0054600961 | D35: =LN(B35/B34) -> -0.005475057 | E35: =D35-C35 -> -1.4960808e-05 | F35: This is the additivity property. Simple returns do NOT have this.
A36: 15-Feb-2023 | B36: 4330.29 | C36: =B36/B35-1 -> 0.018577803 | D36: =LN(B36/B35) -> 0.018407344 | E36: =D36-C36 -> -0.00017045945
A37: 16-Feb-2023 | B37: 4330.67 | C37: =B37/B36-1 -> 8.7753938e-05 | D37: =LN(B37/B36) -> 8.7750088e-05 | E37: =D37-C37 -> -3.8501516e-09
A38: 17-Feb-2023 | B38: 4290.34 | C38: =B38/B37-1 -> -0.0093126468 | D38: =LN(B38/B37) -> -0.0093562806 | E38: =D38-C38 -> -4.3633804e-05
A39: 20-Feb-2023 | B39: 4329.48 | C39: =B39/B38-1 -> 0.0091228201 | D39: =LN(B39/B38) -> 0.0090814585 | E39: =D39-C39 -> -4.1361558e-05
A40: 21-Feb-2023 | B40: 4272.75 | C40: =B40/B39-1 -> -0.01310319 | D40: =LN(B40/B39) -> -0.013189794 | E40: =D40-C40 -> -8.6604156e-05
A41: 22-Feb-2023 | B41: 4283.83 | C41: =B41/B40-1 -> 0.0025931777 | D41: =LN(B41/B40) -> 0.0025898212 | E41: =D41-C41 -> -3.3564839e-06
A42: 23-Feb-2023 | B42: 4204.02 | C42: =B42/B41-1 -> -0.018630525 | D42: =LN(B42/B41) -> -0.018806259 | E42: =D42-C42 -> -0.00017573433
A43: 24-Feb-2023 | B43: 4139.05 | C43: =B43/B42-1 -> -0.015454256 | D43: =LN(B43/B42) -> -0.015574917 | E43: =D43-C43 -> -0.00012066178
A44: 27-Feb-2023 | B44: 4149.36 | C44: =B44/B43-1 -> 0.0024909097 | D44: =LN(B44/B43) -> 0.0024878126 | E44: =D44-C44 -> -3.0971736e-06
A45: 28-Feb-2023 | B45: 4180.82 | C45: =B45/B44-1 -> 0.0075818921 | D45: =LN(B45/B44) -> 0.0075532941 | E45: =D45-C45 -> -2.8598084e-05
A46: 01-Mar-2023 | B46: 4189.67 | C46: =B46/B45-1 -> 0.0021168096 | D46: =LN(B46/B45) -> 0.0021145723 | E46: =D46-C46 -> -2.2372848e-06
A47: 02-Mar-2023 | B47: 4186.12 | C47: =B47/B46-1 -> -0.0008473221 | D47: =LN(B47/B46) -> -0.00084768128 | E47: =D47-C47 -> -3.5918028e-07
... A255: 19-Dec-2023 | B255: 4252.49 | C255: =B255/B254-1 -> -0.01255985 | D255: =LN(B255/B254) -> -0.012639392 | E255: =D255-C255 -> -7.9541642e-05

Sheet 2.STYLIZED FACTS
A2: SECTION 2 — STYLIZED FACTS: HOW FINANCIAL RETURNS ACTUALLY BEHAVE
B3: Date | C3: Log-Return (%) | D3: Squared Return | E3: Abs Return | I3: HISTOGRAM BINS | O3: SCATTER DATA
B4: 30-Dec-2022 | D4: =C4^2 -> 0 | E4: =ABS(C4) -> 0 | G4: WHAT ARE STYLIZED FACTS? | I4: Bin Low | J4: Bin High | K4: Return Range | L4: Actual Count | M4: Normal Expected | O4: r(t-1) | P4: r(t)
B5: 03-Jan-2023 | C5: ='1.RETURNS'!D5 -> 0.0058848723 | D5: =C5^2 -> 3.4631723e-05 | E5: =ABS(C5) -> 0.0058848723 | I5: -0.05 | J5: -0.045 | K5: -4.75% | L5: =COUNTIF($C$5:$C$255,"<"&J5) -> 0 | M5: =COUNT($C$5:$C$255)*_xlfn.NORM.DIST(J5,AVERAGE($C$5:$C$255),STDEV($C$5:$C$255),TRUE) -> 0.0060340321
B6: 04-Jan-2023 | C6: ='1.RETURNS'!D6 -> -0.0012113658 | D6: =C6^2 -> 1.467407e-06 | E6: =ABS(C6) -> 0.0012113658 | G6: Across nearly every financial market and time period, return series | I6: -0.045 | J6: -0.04 | K6: -4.25% | L6: =COUNTIFS($C$5:$C$255,">="&I6,$C$5:$C$255,"<"&J6) -> 1 | M6: =COUNT($C$5:$C$255)*(_xlfn.NORM.DIST(J6,AVERAGE($C$5:$C$255),STDEV($C$5:$C$255),TRUE)-_xlfn.NORM.DIST(I6,AVERAGE($C$5:$C$255),STDEV($C$5:$C$255),TRUE)) -> 0.032267217 | O6: =C5 -> 0.0058848723 | P6: =C6 -> -0.0012113658
B7: 05-Jan-2023 | C7: ='1.RETURNS'!D7 -> 0.0066707917 | D7: =C7^2 -> 4.4499462e-05 | E7: =ABS(C7) -> 0.0066707917 | G7: share the same surprising statistical properties. These are not | I7: -0.04 | J7: -0.035 | K7: -3.75% | L7: =COUNTIFS($C$5:$C$255,">="&I7,$C$5:$C$255,"<"&J7) -> 1 | M7: =COUNT($C$5:$C$255)*(_xlfn.NORM.DIST(J7,AVERAGE($C$5:$C$255),STDEV($C$5:$C$255),TRUE)-_xlfn.NORM.DIST(I7,AVERAGE($C$5:$C$255),STDEV($C$5:$C$255),TRUE)) -> 0.1617883 | O7: =C6 -> -0.0012113658 | P7: =C7 -> 0.0066707917
B8: 06-Jan-2023 | C8: ='1.RETURNS'!D8 -> 0.016065487 | D8: =C8^2 -> 0.00025809986 | E8: =ABS(C8) -> 0.016065487 | G8: theoretical predictions — they are empirical regularities observed | I8: -0.035 | J8: -0.03 | K8: -3.25% | L8: =COUNTIFS($C$5:$C$255,">="&I8,$C$5:$C$255,"<"&J8) -> 1 | M8: =COUNT($C$5:$C$255)*(_xlfn.NORM.DIST(J8,AVERAGE($C$5:$C$255),STDEV($C$5:$C$255),TRUE)-_xlfn.NORM.DIST(I8,AVERAGE($C$5:$C$255),STDEV($C$5:$C$255),TRUE)) -> 0.66223845 | O8: =C7 -> 0.0066707917 | P8: =C8 -> 0.016065487
B9: 09-Jan-2023 | C9: ='1.RETURNS'!D9 -> -0.0024548761 | D9: =C9^2 -> 6.0264168e-06 | E9: =ABS(C9) -> 0.0024548761 | G9: in real data and documented by researchers for decades. | I9: -0.03 | J9: -0.025 | K9: -2.75% | L9: =COUNTIFS($C$5:$C$255,">="&I9,$C$5:$C$255,"<"&J9) -> 1 | M9: =COUNT($C$5:$C$255)*(_xlfn.NORM.DIST(J9,AVERAGE($C$5:$C$255),STDEV($C$5:$C$255),TRUE)-_xlfn.NORM.DIST(I9,AVERAGE($C$5:$C$255),STDEV($C$5:$C$255),TRUE)) -> 2.2131015 | O9: =C8 -> 0.016065487 | P9: =C9 -> -0.0024548761
B10: 10-Jan-2023 | C10: ='1.RETURNS'!D10 -> -0.0020112502 | D10: =C10^2 -> 4.0451275e-06 | E10: =ABS(C10) -> 0.0020112502 | I10: -0.025 | J10: -0.02 | K10: -2.25% | L10: =COUNTIFS($C$5:$C$255,">="&I10,$C$5:$C$255,"<"&J10) -> 4 | M10: =COUNT($C$5:$C$255)*(_xlfn.NORM.DIST(J10,AVERAGE($C$5:$C$255),STDEV($C$5:$C$255),TRUE)-_xlfn.NORM.DIST(I10,AVERAGE($C$5:$C$255),STDEV($C$5:$C$255),TRUE)) -> 6.0386762 | O10: =C9 -> -0.0024548761 | P10: =C10 -> -0.0020112502
B11: 11-Jan-2023 | C11: ='1.RETURNS'!D11 -> 0.015334303 | D11: =C11^2 -> 0.00023514084 | E11: =ABS(C11) -> 0.015334303 | G11: THE 4 KEY STYLIZED FACTS WE COVER HERE: | I11: -0.02 | J11: -0.015 | K11: -1.75% | L11: =COUNTIFS($C$5:$C$255,">="&I11,$C$5:$C$255,"<"&J11) -> 11 | M11: =COUNT($C$5:$C$255)*(_xlfn.NORM.DIST(J11,AVERAGE($C$5:$C$255),STDEV($C$5:$C$255),TRUE)-_xlfn.NORM.DIST(I11,AVERAGE($C$5:$C$255),STDEV($C$5:$C$255),TRUE)) -> 13.454415 | O11: =C10 -> -0.0020112502 | P11: =C11 -> 0.015334303
B12: 12-Jan-2023 | C12: ='1.RETURNS'!D12 -> 0.0088748844 | D12: =C12^2 -> 7.8763574e-05 | E12: =ABS(C12) -> 0.0088748844 | I12: -0.015 | J12: -0.01 | K12: -1.25% | L12: =COUNTIFS($C$5:$C$255,">="&I12,$C$5:$C$255,"<"&J12) -> 21 | M12: =COUNT($C$5:$C$255)*(_xlfn.NORM.DIST(J12,AVERAGE($C$5:$C$255),STDEV($C$5:$C$255),TRUE)-_xlfn.NORM.DIST(I12,AVERAGE($C$5:$C$255),STDEV($C$5:$C$255),TRUE)) -> 24.479046 | O12: =C11 -> 0.015334303 | P12: =C12 -> 0.0088748844
B13: 13-Jan-2023 | C13: ='1.RETURNS'!D13 -> -0.0048215906 | D13: =C13^2 -> 2.3247736e-05 | E13: =ABS(C13) -> 0.0048215906 | G13: FACT 1 — RETURNS LOOK LIKE RANDOM NOISE | I13: -0.01 | J13: -0.005 | K13: -0.75% | L13: =COUNTIFS($C$5:$C$255,">="&I13,$C$5:$C$255,"<"&J13) -> 41 | M13: =COUNT($C$5:$C$255)*(_xlfn.NORM.DIST(J13,AVERAGE($C$5:$C$255),STDEV($C$5:$C$255),TRUE)-_xlfn.NORM.DIST(I13,AVERAGE($C$5:$C$255),STDEV($C$5:$C$255),TRUE)) -> 36.370484 | O13: =C12 -> 0.0088748844 | P13: =C13 -> -0.0048215906
B14: 16-Jan-2023 | C14: ='1.RETURNS'!D14 -> 0.0055124296 | D14: =C14^2 -> 3.0386881e-05 | E14: =ABS(C14) -> 0.0055124296 | G14: Plot Column D (log-returns) over time. It oscillates around zero | I14: -0.005 | J14: 0 | K14: -0.25% | L14: =COUNTIFS($C$5:$C$255,">="&I14,$C$5:$C$255,"<"&J14) -> 41 | M14: =COUNT($C$5:$C$255)*(_xlfn.NORM.DIST(J14,AVERAGE($C$5:$C$255),STDEV($C$5:$C$255),TRUE)-_xlfn.NORM.DIST(I14,AVERAGE($C$5:$C$255),STDEV($C$5:$C$255),TRUE)) -> 44.130709 | O14: =C13 -> -0.0048215906 | P14: =C14 -> 0.0055124296
B15: 17-Jan-2023 | C15: ='1.RETURNS'!D15 -> -0.0042904899 | D15: =C15^2 -> 1.8408304e-05 | E15: =ABS(C15) -> 0.0042904899 | G15: with no clear trend. There is no direction to predict. This is | I15: 0 | J15: 0.005 | K15: 0.25% | L15: =COUNTIFS($C$5:$C$255,">="&I15,$C$5:$C$255,"<"&J15) -> 53 | M15: =COUNT($C$5:$C$255)*(_xlfn.NORM.DIST(J15,AVERAGE($C$5:$C$255),STDEV($C$5:$C$255),TRUE)-_xlfn.NORM.DIST(I15,AVERAGE($C$5:$C$255),STDEV($C$5:$C$255),TRUE)) -> 43.729655 | O15: =C14 -> 0.0055124296 | P15: =C15 -> -0.0042904899
B16: 18-Jan-2023 | C16: ='1.RETURNS'!D16 -> -0.0042128306 | D16: =C16^2 -> 1.7747942e-05 | E16: =ABS(C16) -> 0.0042128306 | G16: consistent with the efficient market idea: prices already reflect | I16: 0.005 | J16: 0.01 | K16: 0.75% | L16: =COUNTIFS($C$5:$C$255,">="&I16,$C$5:$C$255,"<"&J16) -> 38 | M16: =COUNT($C$5:$C$255)*(_xlfn.NORM.DIST(J16,AVERAGE($C$5:$C$255),STDEV($C$5:$C$255),TRUE)-_xlfn.NORM.DIST(I16,AVERAGE($C$5:$C$255),STDEV($C$5:$C$255),TRUE)) -> 35.387853 | O16: =C15 -> -0.0042904899 | P16: =C16 -> -0.0042128306
B17: 19-Jan-2023 | C17: ='1.RETURNS'!D17 -> 0.0025967418 | D17: =C17^2 -> 6.7430678e-06 | E17: =ABS(C17) -> 0.0025967418 | G17: available information. | I17: 0.01 | J17: 0.015 | K17: 1.25% | L17: =COUNTIFS($C$5:$C$255,">="&I17,$C$5:$C$255,"<"&J17) -> 19 | M17: =COUNT($C$5:$C$255)*(_xlfn.NORM.DIST(J17,AVERAGE($C$5:$C$255),STDEV($C$5:$C$255),TRUE)-_xlfn.NORM.DIST(I17,AVERAGE($C$5:$C$255),STDEV($C$5:$C$255),TRUE)) -> 23.38669 | O17: =C16 -> -0.0042128306 | P17: =C17 -> 0.0025967418
B18: 20-Jan-2023 | C18: ='1.RETURNS'!D18 -> -0.019171552 | D18: =C18^2 -> 0.00036754841 | E18: =ABS(C18) -> 0.019171552 | I18: 0.015 | J18: 0.02 | K18: 1.75% | L18: =COUNTIFS($C$5:$C$255,">="&I18,$C$5:$C$255,"<"&J18) -> 12 | M18: =COUNT($C$5:$C$255)*(_xlfn.NORM.DIST(J18,AVERAGE($C$5:$C$255),STDEV($C$5:$C$255),TRUE)-_xlfn.NORM.DIST(I18,AVERAGE($C$5:$C$255),STDEV($C$5:$C$255),TRUE)) -> 12.621379 | O18: =C17 -> 0.0025967418 | P18: =C18 -> -0.019171552
B19: 23-Jan-2023 | C19: ='1.RETURNS'!D19 -> -0.020470412 | D19: =C19^2 -> 0.00041903776 | E19: =ABS(C19) -> 0.020470412 | G19: FACT 2 — FAT TAILS (Leptokurtosis) | I19: 0.02 | J19: 0.025 | K19: 2.25% | L19: =COUNTIFS($C$5:$C$255,">="&I19,$C$5:$C$255,"<"&J19) -> 4 | M19: =COUNT($C$5:$C$255)*(_xlfn.NORM.DIST(J19,AVERAGE($C$5:$C$255),STDEV($C$5:$C$255),TRUE)-_xlfn.NORM.DIST(I19,AVERAGE($C$5:$C$255),STDEV($C$5:$C$255),TRUE)) -> 5.5622379 | O19: =C18 -> -0.019171552 | P19: =C19 -> -0.020470412
B20: 24-Jan-2023 | C20: ='1.RETURNS'!D20 -> -0.0064772079 | D20: =C20^2 -> 4.1954222e-05 | E20: =ABS(C20) -> 0.0064772079 | G20: Plot a histogram of Column D. Compare it to a normal bell curve. | I20: 0.025 | J20: 0.03 | K20: 2.75% | L20: =COUNTIFS($C$5:$C$255,">="&I20,$C$5:$C$255,"<"&J20) -> 2 | M20: =COUNT($C$5:$C$255)*(_xlfn.NORM.DIST(J20,AVERAGE($C$5:$C$255),STDEV($C$5:$C$255),TRUE)-_xlfn.NORM.DIST(I20,AVERAGE($C$5:$C$255),STDEV($C$5:$C$255),TRUE)) -> 2.001578 | O20: =C19 -> -0.020470412 | P20: =C20 -> -0.0064772079
B21: 25-Jan-2023 | C21: ='1.RETURNS'!D21 -> -0.0097974154 | D21: =C21^2 -> 9.5989349e-05 | E21: =ABS(C21) -> 0.0097974154 | G21: The return distribution has a taller, sharper peak and FATTER tails. | I21: 0.03 | J21: 0.035 | K21: 3.25% | L21: =COUNTIFS($C$5:$C$255,">="&I21,$C$5:$C$255,"<"&J21) -> 0 | M21: =COUNT($C$5:$C$255)*(_xlfn.NORM.DIST(J21,AVERAGE($C$5:$C$255),STDEV($C$5:$C$255),TRUE)-_xlfn.NORM.DIST(I21,AVERAGE($C$5:$C$255),STDEV($C$5:$C$255),TRUE)) -> 0.5880931 | O21: =C20 -> -0.0064772079 | P21: =C21 -> -0.0097974154
B22: 26-Jan-2023 | C22: ='1.RETURNS'!D22 -> 0.0036193333 | D22: =C22^2 -> 1.3099573e-05 | E22: =ABS(C22) -> 0.0036193333 | G22: Extreme moves (-3%, -4%, -5%) happen far more often than a normal | I22: 0.035 | J22: 0.04 | K22: 3.75% | L22: =COUNTIFS($C$5:$C$255,">="&I22,$C$5:$C$255,"<"&J22) -> 0 | M22: =COUNT($C$5:$C$255)*(_xlfn.NORM.DIST(J22,AVERAGE($C$5:$C$255),STDEV($C$5:$C$255),TRUE)-_xlfn.NORM.DIST(I22,AVERAGE($C$5:$C$255),STDEV($C$5:$C$255),TRUE)) -> 0.14107045 | O22: =C21 -> -0.0097974154 | P22: =C22 -> 0.0036193333
B23: 27-Jan-2023 | C23: ='1.RETURNS'!D23 -> -0.0087524506 | D23: =C23^2 -> 7.6605392e-05 | E23: =ABS(C23) -> 0.0087524506 | G23: distribution would predict. This is the #1 reason risk models that | I23: 0.04 | J23: 0.045 | K23: 4.25% | L23: =COUNTIFS($C$5:$C$255,">="&I23,$C$5:$C$255,"<"&J23) -> 1 | M23: =COUNT($C$5:$C$255)*(_xlfn.NORM.DIST(J23,AVERAGE($C$5:$C$255),STDEV($C$5:$C$255),TRUE)-_xlfn.NORM.DIST(I23,AVERAGE($C$5:$C$255),STDEV($C$5:$C$255),TRUE)) -> 0.027625115 | O23: =C22 -> 0.0036193333 | P23: =C23 -> -0.0087524506
B24: 30-Jan-2023 | C24: ='1.RETURNS'!D24 -> -0.014251167 | D24: =C24^2 -> 0.00020309575 | E24: =ABS(C24) -> 0.014251167 | G24: assume normality underestimate actual tail losses. | I24: 0.045 | J24: 0.05 | K24: 4.75% | L24: =COUNTIF($C$5:$C$255,">="&I24) -> 0 | M24: =COUNT($C$5:$C$255)*(1-_xlfn.NORM.DIST(I24,AVERAGE($C$5:$C$255),STDEV($C$5:$C$255),TRUE)) -> 0.0050589716 | O24: =C23 -> -0.0087524506 | P24: =C24 -> -0.014251167
B25: 31-Jan-2023 | C25: ='1.RETURNS'!D25 -> 0.01663348 | D25: =C25^2 -> 0.00027667266 | E25: =ABS(C25) -> 0.01663348 | O25: =C24 -> -0.014251167 | P25: =C25 -> 0.01663348
B26: 01-Feb-2023 | C26: ='1.RETURNS'!D26 -> -0.0023279526 | D26: =C26^2 -> 5.4193635e-06 | E26: =ABS(C26) -> 0.0023279526 | G26: FACT 3 — SMALL AUTOCORRELATION IN RAW RETURNS | O26: =C25 -> 0.01663348 | P26: =C26 -> -0.0023279526
B27: 02-Feb-2023 | C27: ='1.RETURNS'!D27 -> 0.00093726236 | D27: =C27^2 -> 8.7846073e-07 | E27: =ABS(C27) -> 0.00093726236 | G27: Today's return gives very little information about tomorrow's return. | O27: =C26 -> -0.0023279526 | P27: =C27 -> 0.00093726236
B28: 03-Feb-2023 | C28: ='1.RETURNS'!D28 -> -0.013635752 | D28: =C28^2 -> 0.00018593372 | E28: =ABS(C28) -> 0.013635752 | G28: We will measure this precisely in Section 4 (Autocorrelation). | O28: =C27 -> 0.00093726236 | P28: =C28 -> -0.013635752
B29: 06-Feb-2023 | C29: ='1.RETURNS'!D29 -> -0.0055921391 | D29: =C29^2 -> 3.127202e-05 | E29: =ABS(C29) -> 0.0055921391 | G29: For now: this is why ARIMA will find almost nothing to model. | O29: =C28 -> -0.013635752 | P29: =C29 -> -0.0055921391
B30: 07-Feb-2023 | C30: ='1.RETURNS'!D30 -> 0.0013854201 | D30: =C30^2 -> 1.9193889e-06 | E30: =ABS(C30) -> 0.0013854201 | O30: =C29 -> -0.0055921391 | P30: =C30 -> 0.0013854201
B31: 08-Feb-2023 | C31: ='1.RETURNS'!D31 -> -0.011016358 | D31: =C31^2 -> 0.00012136014 | E31: =ABS(C31) -> 0.011016358 | G31: FACT 4 — VOLATILITY CLUSTERING (the most important one) | O31: =C30 -> 0.0013854201 | P31: =C31 -> -0.011016358
B32: 09-Feb-2023 | C32: ='1.RETURNS'!D32 -> 0.0043343887 | D32: =C32^2 -> 1.8786925e-05 | E32: =ABS(C32) -> 0.0043343887 | G32: Look at Column E (squared returns). Squaring removes the sign | O32: =C31 -> -0.011016358 | P32: =C32 -> 0.0043343887
B33: 10-Feb-2023 | C33: ='1.RETURNS'!D33 -> -0.0059637653 | D33: =C33^2 -> 3.5566497e-05 | E33: =ABS(C33) -> 0.0059637653 | G33: and leaves only the magnitude. Now you can see clusters of large | O33: =C32 -> 0.0043343887 | P33: =C33 -> -0.0059637653
B34: 13-Feb-2023 | C34: ='1.RETURNS'!D34 -> -0.0027659885 | D34: =C34^2 -> 7.6506926e-06 | E34: =ABS(C34) -> 0.0027659885 | G34: values followed by more large values — calm follows calm, | O34: =C33 -> -0.0059637653 | P34: =C34 -> -0.0027659885
B35: 14-Feb-2023 | C35: ='1.RETURNS'!D35 -> -0.005475057 | D35: =C35^2 -> 2.9976249e-05 | E35: =ABS(C35) -> 0.005475057 | G35: turbulence follows turbulence. This is NOT random. This is the | O35: =C34 -> -0.0027659885 | P35: =C35 -> -0.005475057
B36: 15-Feb-2023 | C36: ='1.RETURNS'!D36 -> 0.018407344 | D36: =C36^2 -> 0.0003388303 | E36: =ABS(C36) -> 0.018407344 | G36: structure GARCH is built to capture. | O36: =C35 -> -0.005475057 | P36: =C36 -> 0.018407344
B37: 16-Feb-2023 | C37: ='1.RETURNS'!D37 -> 8.7750088e-05 | D37: =C37^2 -> 7.7000779e-09 | E37: =ABS(C37) -> 8.7750088e-05 | O37: =C36 -> 0.018407344 | P37: =C37 -> 8.7750088e-05
B38: 17-Feb-2023 | C38: ='1.RETURNS'!D38 -> -0.0093562806 | D38: =C38^2 -> 8.7539986e-05 | E38: =ABS(C38) -> 0.0093562806 | G38: WHY DOES CLUSTERING MATTER FOR RISK? | O38: =C37 -> 8.7750088e-05 | P38: =C38 -> -0.0093562806
B39: 20-Feb-2023 | C39: ='1.RETURNS'!D39 -> 0.0090814585 | D39: =C39^2 -> 8.2472889e-05 | E39: =ABS(C39) -> 0.0090814585 | G39: Because if volatility is predictable, so is risk. | O39: =C38 -> -0.0093562806 | P39: =C39 -> 0.0090814585
B40: 21-Feb-2023 | C40: ='1.RETURNS'!D40 -> -0.013189794 | D40: =C40^2 -> 0.00017397068 | E40: =ABS(C40) -> 0.013189794 | G40: A GARCH model uses this clustering to forecast tomorrow's | O40: =C39 -> 0.0090814585 | P40: =C40 -> -0.013189794
B41: 22-Feb-2023 | C41: ='1.RETURNS'!D41 -> 0.0025898212 | D41: =C41^2 -> 6.7071739e-06 | E41: =ABS(C41) -> 0.0025898212 | G41: expected volatility — and therefore tomorrow's risk. | O41: =C40 -> -0.013189794 | P41: =C41 -> 0.0025898212
B42: 23-Feb-2023 | C42: ='1.RETURNS'!D42 -> -0.018806259 | D42: =C42^2 -> 0.00035367537 | E42: =ABS(C42) -> 0.018806259 | O42: =C41 -> 0.0025898212 | P42: =C42 -> -0.018806259
B43: 24-Feb-2023 | C43: ='1.RETURNS'!D43 -> -0.015574917 | D43: =C43^2 -> 0.00024257805 | E43: =ABS(C43) -> 0.015574917 | O43: =C42 -> -0.018806259 | P43: =C43 -> -0.015574917
B44: 27-Feb-2023 | C44: ='1.RETURNS'!D44 -> 0.0024878126 | D44: =C44^2 -> 6.1892114e-06 | E44: =ABS(C44) -> 0.0024878126 | G44: SUMMARY STATISTICS — Compare these to what a Normal distribution predicts | O44: =C43 -> -0.015574917 | P44: =C44 -> 0.0024878126
B45: 28-Feb-2023 | C45: ='1.RETURNS'!D45 -> 0.0075532941 | D45: =C45^2 -> 5.7052251e-05 | E45: =ABS(C45) -> 0.0075532941 | G45: Mean (%) | H45: =AVERAGE(C4:C255) -> -0.00022538926 | I45: Should be close to zero | O45: =C44 -> 0.0024878126 | P45: =C45 -> 0.0075532941
B46: 01-Mar-2023 | C46: ='1.RETURNS'!D46 -> 0.0021145723 | D46: =C46^2 -> 4.4714162e-06 | E46: =ABS(C46) -> 0.0021145723 | G46: Std Dev (%) | H46: =STDEV(C4:C255) -> 0.011015289 | I46: Daily vol (not annualized) | O46: =C45 -> 0.0075532941 | P46: =C46 -> 0.0021145723
B47: 02-Mar-2023 | C47: ='1.RETURNS'!D47 -> -0.00084768128 | D47: =C47^2 -> 7.1856356e-07 | E47: =ABS(C47) -> 0.00084768128 | G47: Skewness | H47: =SKEW(C4:C255) -> -0.22741115 | I47: Negative = left-skewed (losses dominate) | O47: =C46 -> 0.0021145723 | P47: =C47 -> -0.00084768128
B48: 03-Mar-2023 | C48: ='1.RETURNS'!D48 -> -0.0027581407 | D48: =C48^2 -> 7.6073402e-06 | E48: =ABS(C48) -> 0.0027581407 | G48: Kurtosis | H48: =KURT(C4:C255)+3 -> 4.607175 | I48: Normal = 3. Higher = fatter tails | O48: =C47 -> -0.00084768128 | P48: =C48 -> -0.0027581407
B49: 06-Mar-2023 | C49: ='1.RETURNS'!D49 -> -0.014851304 | D49: =C49^2 -> 0.00022056123 | E49: =ABS(C49) -> 0.014851304 | G49: Excess Kurtosis | H49: =KURT(C4:C255) -> 1.607175 | I49: Normal = 0. Positive = FAT TAILS | O49: =C48 -> -0.0027581407 | P49: =C49 -> -0.014851304
B50: 07-Mar-2023 | C50: ='1.RETURNS'!D50 -> -0.0076831274 | D50: =C50^2 -> 5.9030447e-05 | E50: =ABS(C50) -> 0.0076831274 | G50: Normal has Kurtosis of... | H50: 3 | I50: ← Fixed benchmark | O50: =C49 -> -0.014851304 | P50: =C50 -> -0.0076831274
B51: 08-Mar-2023 | C51: ='1.RETURNS'!D51 -> -0.0043656826 | D51: =C51^2 -> 1.9059185e-05 | E51: =ABS(C51) -> 0.0043656826 | O51: =C50 -> -0.0076831274 | P51: =C51 -> -0.0043656826
B52: 09-Mar-2023 | C52: ='1.RETURNS'!D52 -> 0.010511056 | D52: =C52^2 -> 0.00011048229 | E52: =ABS(C52) -> 0.010511056 | O52: =C51 -> -0.0043656826 | P52: =C52 -> 0.010511056
B53: 10-Mar-2023 | C53: ='1.RETURNS'!D53 -> 0.0038205554 | D53: =C53^2 -> 1.4596644e-05 | E53: =ABS(C53) -> 0.0038205554 | O53: =C52 -> 0.010511056 | P53: =C53 -> 0.0038205554
B54: 13-Mar-2023 | C54: ='1.RETURNS'!D54 -> -0.016681933 | D54: =C54^2 -> 0.0002782869 | E54: =ABS(C54) -> 0.016681933 | O54: =C53 -> 0.0038205554 | P54: =C54 -> -0.016681933
B55: 14-Mar-2023 | C55: ='1.RETURNS'!D55 -> 0.0040394349 | D55: =C55^2 -> 1.6317034e-05 | E55: =ABS(C55) -> 0.0040394349 | O55: =C54 -> -0.016681933 | P55: =C55 -> 0.0040394349
B56: 15-Mar-2023 | C56: ='1.RETURNS'!D56 -> -0.0034328482 | D56: =C56^2 -> 1.1784447e-05 | E56: =ABS(C56) -> 0.0034328482 | O56: =C55 -> 0.0040394349 | P56: =C56 -> -0.0034328482
B57: 16-Mar-2023 | C57: ='1.RETURNS'!D57 -> -0.0063454124 | D57: =C57^2 -> 4.0264258e-05 | E57: =ABS(C57) -> 0.0063454124 | O57: =C56 -> -0.0034328482 | P57: =C57 -> -0.0063454124
B58: 17-Mar-2023 | C58: ='1.RETURNS'!D58 -> 0.006744671 | D58: =C58^2 -> 4.5490587e-05 | E58: =ABS(C58) -> 0.006744671 | O58: =C57 -> -0.0063454124 | P58: =C58 -> 0.006744671
B59: 20-Mar-2023 | C59: ='1.RETURNS'!D59 -> 0.010476356 | D59: =C59^2 -> 0.00010975404 | E59: =ABS(C59) -> 0.010476356 | O59: =C58 -> 0.006744671 | P59: =C59 -> 0.010476356
B60: 21-Mar-2023 | C60: ='1.RETURNS'!D60 -> 0.010563192 | D60: =C60^2 -> 0.00011158103 | E60: =ABS(C60) -> 0.010563192 | O60: =C59 -> 0.010476356 | P60: =C60 -> 0.010563192
B61: 22-Mar-2023 | C61: ='1.RETURNS'!D61 -> -0.0086289841 | D61: =C61^2 -> 7.4459366e-05 | E61: =ABS(C61) -> 0.0086289841 | O61: =C60 -> 0.010563192 | P61: =C61 -> -0.0086289841
B62: 23-Mar-2023 | C62: ='1.RETURNS'!D62 -> -0.0028929543 | D62: =C62^2 -> 8.3691843e-06 | E62: =ABS(C62) -> 0.0028929543 | O62: =C61 -> -0.0086289841 | P62: =C62 -> -0.0028929543
... B255: 19-Dec-2023 | C255: ='1.RETURNS'!D255 -> -0.012639392 | D255: =C255^2 -> 0.00015975423 | E255: =ABS(C255) -> 0.012639392 | O255: =C254 -> 0.0049861947 | P255: =C255 -> -0.012639392

Sheet 3.STATIONARITY
B2: SECTION 3 — STATIONARITY: WHY PRICES CAN'T BE MODELED DIRECTLY
B3: Obs # | C3: Random Shock (ε) | D3: Random Walk (cumsum) | E3: 1st Diff of Walk | F3: Simulated Return (%) | G3: Simulated Cum. Level (Idx=100)
B4: 1 | C4: =_xlfn.NORM.S.INV(RAND()) -> -0.38383894 | D4: =C4 -> -0.38383894 | E4: n/a | F4: n/a | G4: 100 | H4: WHAT IS STATIONARITY?
B5: 2 | C5: =_xlfn.NORM.S.INV(RAND()) -> -0.58489192 | D5: =D4+C5 -> -0.96873086 | E5: =D5-D4 -> -0.58489192 | F5: ='1.RETURNS'!D5 -> 0.0058848723 | G5: =G4*EXP(F5) -> 100.59022
B6: 3 | C6: =_xlfn.NORM.S.INV(RAND()) -> -1.2132108 | D6: =D5+C6 -> -2.1819417 | E6: =D6-D5 -> -1.2132108 | F6: ='1.RETURNS'!D6 -> -0.0012113658 | G6: =G5*EXP(F6) -> 100.46844 | H6: A time series is stationary if its statistical properties — mean,
B7: 4 | C7: =_xlfn.NORM.S.INV(RAND()) -> -1.4998538 | D7: =D6+C7 -> -3.6817955 | E7: =D7-D6 -> -1.4998538 | F7: ='1.RETURNS'!D7 -> 0.0066707917 | G7: =G6*EXP(F7) -> 101.14089 | H7: variance, and autocorrelation structure — do not change over time.
B8: 5 | C8: =_xlfn.NORM.S.INV(RAND()) -> 1.0809506 | D8: =D7+C8 -> -2.6008449 | E8: =D8-D7 -> 1.0809506 | F8: ='1.RETURNS'!D8 -> 0.016065487 | G8: =G7*EXP(F8) -> 102.77889 | T8: The Core Problem: Why You Can't Model Stock Prices Directly
B9: 6 | C9: =_xlfn.NORM.S.INV(RAND()) -> -1.3642157 | D9: =D8+C9 -> -3.9650606 | E9: =D9-D8 -> -1.3642157 | F9: ='1.RETURNS'!D9 -> -0.0024548761 | G9: =G8*EXP(F9) -> 102.52689 | H9: Think of it this way:
B10: 7 | C10: =_xlfn.NORM.S.INV(RAND()) -> 0.28407338 | D10: =D9+C10 -> -3.6809872 | E10: =D10-D9 -> 0.28407338 | F10: ='1.RETURNS'!D10 -> -0.0020112502 | G10: =G9*EXP(F10) -> 102.32089 | H10: A stationary series bounces around a fixed center. | T10: Most time series models (ARIMA, regression, VAR) have one fundamental requirement: the data must be stationary — meaning its mean, variance, and autocorrelation structure don't change over time.
B11: 8 | C11: =_xlfn.NORM.S.INV(RAND()) -> 0.71414913 | D11: =D10+C11 -> -2.9668381 | E11: =D11-D10 -> 0.71414913 | F11: ='1.RETURNS'!D11 -> 0.015334303 | G11: =G10*EXP(F11) -> 103.902 | H11: A non-stationary series drifts — it wanders off and never
B12: 9 | C12: =_xlfn.NORM.S.INV(RAND()) -> 0.52647562 | D12: =D11+C12 -> -2.4403625 | E12: =D12-D11 -> 0.52647562 | F12: ='1.RETURNS'!D12 -> 0.0088748844 | G12: =G11*EXP(F12) -> 104.82822 | H12: comes back to any particular level. | T12: Stock prices violate this. They drift — permanently. There's no level they "return to."
B13: 10 | C13: =_xlfn.NORM.S.INV(RAND()) -> 0.38866945 | D13: =D12+C13 -> -2.051693 | E13: =D13-D12 -> 0.38866945 | F13: ='1.RETURNS'!D13 -> -0.0048215906 | G13: =G12*EXP(F13) -> 104.324
B14: 11 | C14: =_xlfn.NORM.S.INV(RAND()) -> 0.44948214 | D14: =D13+C14 -> -1.6022109 | E14: =D14-D13 -> 0.44948214 | F14: ='1.RETURNS'!D14 -> 0.0055124296 | G14: =G13*EXP(F14) -> 104.90067 | H14: WHY DOES IT MATTER?
B15: 12 | C15: =_xlfn.NORM.S.INV(RAND()) -> 3.2237578 | D15: =D14+C15 -> 1.6215469 | E15: =D15-D14 -> 3.2237578 | F15: ='1.RETURNS'!D15 -> -0.0042904899 | G15: =G14*EXP(F15) -> 104.45156
B16: 13 | C16: =_xlfn.NORM.S.INV(RAND()) -> -0.40261467 | D16: =D15+C16 -> 1.2189322 | E16: =D16-D15 -> -0.40261467 | F16: ='1.RETURNS'!D16 -> -0.0042128306 | G16: =G15*EXP(F16) -> 104.01244 | H16: Almost every classical time series model (ARIMA, regression, | T16: What the 4 Data Columns Show
B17: 14 | C17: =_xlfn.NORM.S.INV(RAND()) -> 1.5137007 | D17: =D16+C17 -> 2.732633 | E17: =D17-D16 -> 1.5137007 | F17: ='1.RETURNS'!D17 -> 0.0025967418 | G17: =G16*EXP(F17) -> 104.28289 | H17: VAR) assumes the data is stationary. Using non-stationary data
B18: 15 | C18: =_xlfn.NORM.S.INV(RAND()) -> 0.10159187 | D18: =D17+C18 -> 2.8342248 | E18: =D18-D17 -> 0.10159187 | F18: ='1.RETURNS'!D18 -> -0.019171552 | G18: =G17*EXP(F18) -> 102.30267 | H18: produces 'spurious regressions' — strong-looking correlations | T18: Column | U18: Series | V18: Stationary? | W18: The Point
B19: 16 | C19: =_xlfn.NORM.S.INV(RAND()) -> 1.0141607 | D19: =D18+C19 -> 3.8483856 | E19: =D19-D18 -> 1.0141607 | F19: ='1.RETURNS'!D19 -> -0.020470412 | G19: =G18*EXP(F19) -> 100.22978 | H19: that are purely accidental, not real. | T19: C | U19: Random Shocks (ε) | V19: ✅ Yes | W19: White noise — mean always ≈ 0, std dev always ≈ 1. This is what "well-behaved" data looks like
B20: 17 | C20: =_xlfn.NORM.S.INV(RAND()) -> -0.35889534 | D20: =D19+C20 -> 3.4894902 | E20: =D20-D19 -> -0.35889534 | F20: ='1.RETURNS'!D20 -> -0.0064772079 | G20: =G19*EXP(F20) -> 99.582667 | T20: D | U20: Random Walk | V20: ❌ No | W20: Cumulative sum of shocks. Each step adds to wherever you ended up — it wanders and never comes back
B21: 18 | C21: =_xlfn.NORM.S.INV(RAND()) -> -1.3247293 | D21: =D20+C21 -> 2.1647609 | E21: =D21-D20 -> -1.3247293 | F21: ='1.RETURNS'!D21 -> -0.0097974154 | G21: =G20*EXP(F21) -> 98.611778 | H21: THE RANDOM WALK — THE CLASSIC NON-STATIONARY PROCESS: | T21: E | U21: 1st Diff of Walk | V21: ✅ Yes | W21: Subtracting adjacent Walk values recovers Column C exactly. Differencing cures non-stationarity
B22: 19 | C22: =_xlfn.NORM.S.INV(RAND()) -> 0.10131075 | D22: =D21+C22 -> 2.2660716 | E22: =D22-D21 -> 0.10131075 | F22: ='1.RETURNS'!D22 -> 0.0036193333 | G22: =G21*EXP(F22) -> 98.969333 | T22: F | U22: Simulated Log-Returns | V22: ✅ Yes | W22: Simulated return series — looks statistically identical to Column C. Returns behave like white noise
B23: 20 | C23: =_xlfn.NORM.S.INV(RAND()) -> 1.4929794 | D23: =D22+C23 -> 3.7590511 | E23: =D23-D22 -> 1.4929794 | F23: ='1.RETURNS'!D23 -> -0.0087524506 | G23: =G22*EXP(F23) -> 98.106889 | H23: X_t = X_{t-1} + ε_t (ε_t ~ Normal(0,1)) | T23: G | U23: Simulated Cum. Price Level | V23: ❌ No | W23: Compounding those returns back into a price index — it drifts, just like the random walk in Column D
B24: 21 | C24: =_xlfn.NORM.S.INV(RAND()) -> 0.94881534 | D24: =D23+C24 -> 4.7078664 | E24: =D24-D23 -> 0.94881534 | F24: ='1.RETURNS'!D24 -> -0.014251167 | G24: =G23*EXP(F24) -> 96.718667
B25: 22 | C25: =_xlfn.NORM.S.INV(RAND()) -> -1.7144441 | D25: =D24+C25 -> 2.9934223 | E25: =D25-D24 -> -1.7144441 | F25: ='1.RETURNS'!D25 -> 0.01663348 | G25: =G24*EXP(F25) -> 98.340889 | H25: Each step adds an independent random shock to wherever we were.
B26: 23 | C26: =_xlfn.NORM.S.INV(RAND()) -> -0.34760169 | D26: =D25+C26 -> 2.6458206 | E26: =D26-D25 -> -0.34760169 | F26: ='1.RETURNS'!D26 -> -0.0023279526 | G26: =G25*EXP(F26) -> 98.112222 | H26: The series has no fixed center — it wanders forever. | T26: The 3 Charts Tell the Story Visually
B27: 24 | C27: =_xlfn.NORM.S.INV(RAND()) -> 0.55172045 | D27: =D26+C27 -> 3.1975411 | E27: =D27-D26 -> 0.55172045 | F27: ='1.RETURNS'!D27 -> 0.00093726236 | G27: =G26*EXP(F27) -> 98.204222 | H27: Stock PRICES behave like this. That is why we cannot model prices
B28: 25 | C28: =_xlfn.NORM.S.INV(RAND()) -> -0.30209539 | D28: =D27+C28 -> 2.8954457 | E28: =D28-D27 -> -0.30209539 | F28: ='1.RETURNS'!D28 -> -0.013635752 | G28: =G27*EXP(F28) -> 96.874222 | H28: directly with ARIMA. | T28: Chart 1 — Random Walk (red, top): The line drifts aimlessly — sometimes up, sometimes down, never returning to zero. Hit F9 and it reshapes entirely. No model can predict where it ends up because it has no "center."
B29: 26 | C29: =_xlfn.NORM.S.INV(RAND()) -> -0.071663493 | D29: =D28+C29 -> 2.8237822 | E29: =D29-D28 -> -0.071663493 | F29: ='1.RETURNS'!D29 -> -0.0055921391 | G29: =G28*EXP(F29) -> 96.334
B30: 27 | C30: =_xlfn.NORM.S.INV(RAND()) -> 0.26513136 | D30: =D29+C30 -> 3.0889136 | E30: =D30-D29 -> 0.26513136 | F30: ='1.RETURNS'!D30 -> 0.0013854201 | G30: =G29*EXP(F30) -> 96.467556 | H30: THE FIX — DIFFERENCING: | T30: Chart 2 — Shocks vs. Simulated Returns (blue + green, middle): Both series do the same thing — noisy oscillation around zero. A simulated random process and these simulated returns are statistically indistinguishable. This is the practical implication: returns, not prices, are the right input to your model.
B31: 28 | C31: =_xlfn.NORM.S.INV(RAND()) -> 1.2584753 | D31: =D30+C31 -> 4.3473888 | E31: =D31-D30 -> 1.2584753 | F31: ='1.RETURNS'!D31 -> -0.011016358 | G31: =G30*EXP(F31) -> 95.410667
B32: 29 | C32: =_xlfn.NORM.S.INV(RAND()) -> -1.1470604 | D32: =D31+C32 -> 3.2003284 | E32: =D32-D31 -> -1.1470604 | F32: ='1.RETURNS'!D32 -> 0.0043343887 | G32: =G31*EXP(F32) -> 95.825111 | H32: Take the first difference: ΔX_t = X_t - X_{t-1} = ε_t | T32: Chart 3 — S&P Price Level vs. Returns (red + blue, bottom): The "aha" chart. Same underlying data, split into two forms. The price level (red) drifts — classic non-stationary. The log-returns (blue) bounce near zero — stationary. This is exactly why quant finance works with ln(P_t / P_{t-1}) instead of P_t.
B33: 30 | C33: =_xlfn.NORM.S.INV(RAND()) -> 0.54228608 | D33: =D32+C33 -> 3.7426145 | E33: =D33-D32 -> 0.54228608 | F33: ='1.RETURNS'!D33 -> -0.0059637653 | G33: =G32*EXP(F33) -> 95.255333 | H33: Now you just have the shocks — a stationary white-noise series.
B34: 31 | C34: =_xlfn.NORM.S.INV(RAND()) -> -0.013510658 | D34: =D33+C34 -> 3.7291039 | E34: =D34-D33 -> -0.013510658 | F34: ='1.RETURNS'!D34 -> -0.0027659885 | G34: =G33*EXP(F34) -> 94.992222 | H34: Log-returns ARE this first difference of log-prices.
B35: 32 | C35: =_xlfn.NORM.S.INV(RAND()) -> -0.65176059 | D35: =D34+C35 -> 3.0773433 | E35: =D35-D34 -> -0.65176059 | F35: ='1.RETURNS'!D35 -> -0.005475057 | G35: =G34*EXP(F35) -> 94.473556 | H35: LN(P_t) - LN(P_{t-1}) = LN(P_t / P_{t-1}) = r_t
B36: 33 | C36: =_xlfn.NORM.S.INV(RAND()) -> 1.500549 | D36: =D35+C36 -> 4.5778923 | E36: =D36-D35 -> 1.500549 | F36: ='1.RETURNS'!D36 -> 0.018407344 | G36: =G35*EXP(F36) -> 96.228667 | T36: Takeaway
B37: 34 | C37: =_xlfn.NORM.S.INV(RAND()) -> -0.21145343 | D37: =D36+C37 -> 4.3664388 | E37: =D37-D36 -> -0.21145343 | F37: ='1.RETURNS'!D37 -> 8.7750088e-05 | G37: =G36*EXP(F37) -> 96.237111 | H37: LOOK AT THE DATA TABLE →
B38: 35 | C38: =_xlfn.NORM.S.INV(RAND()) -> 0.32506591 | D38: =D37+C38 -> 4.6915047 | E38: =D38-D37 -> 0.32506591 | F38: ='1.RETURNS'!D38 -> -0.0093562806 | G38: =G37*EXP(F38) -> 95.340889 | H38: Column C = Random shocks (stationary). Always noisy, mean near 0. | T38: Prices are non-stationary random walks. Log-returns are their first difference — stationary white noise. Always model returns, never prices.
B39: 36 | C39: =_xlfn.NORM.S.INV(RAND()) -> -0.32629491 | D39: =D38+C39 -> 4.3652098 | E39: =D39-D38 -> -0.32629491 | F39: ='1.RETURNS'!D39 -> 0.0090814585 | G39: =G38*EXP(F39) -> 96.210667 | H39: Column D = Random walk (cumulative sum). Drifts up or down forever.
B40: 37 | C40: =_xlfn.NORM.S.INV(RAND()) -> 1.1571455 | D40: =D39+C40 -> 5.5223554 | E40: =D40-D39 -> 1.1571455 | F40: ='1.RETURNS'!D40 -> -0.013189794 | G40: =G39*EXP(F40) -> 94.95 | H40: Column E = First diff of the random walk = Column C (exactly). | T40: Press F9 to regenerate the shocks — the random walk reshapes completely every time, but the returns always look the same. That is stationarity.
B41: 38 | C41: =_xlfn.NORM.S.INV(RAND()) -> -0.53375215 | D41: =D40+C41 -> 4.9886032 | E41: =D41-D40 -> -0.53375215 | F41: ='1.RETURNS'!D41 -> 0.0025898212 | G41: =G40*EXP(F41) -> 95.196222 | H41: Column F = simulated log-returns (also stationary, like Column C).
B42: 39 | C42: =_xlfn.NORM.S.INV(RAND()) -> -0.050942812 | D42: =D41+C42 -> 4.9376604 | E42: =D42-D41 -> -0.050942812 | F42: ='1.RETURNS'!D42 -> -0.018806259 | G42: =G41*EXP(F42) -> 93.422667
B43: 40 | C43: =_xlfn.NORM.S.INV(RAND()) -> 0.17960901 | D43: =D42+C43 -> 5.1172694 | E43: =D43-D42 -> 0.17960901 | F43: ='1.RETURNS'!D43 -> -0.015574917 | G43: =G42*EXP(F43) -> 91.978889 | H43: TIP: Press F9 to regenerate all random shocks and watch
B44: 41 | C44: =_xlfn.NORM.S.INV(RAND()) -> 0.27876826 | D44: =D43+C44 -> 5.3960377 | E44: =D44-D43 -> 0.27876826 | F44: ='1.RETURNS'!D44 -> 0.0024878126 | G44: =G43*EXP(F44) -> 92.208 | H44: Column D reshape into a brand-new random walk path.
B45: 42 | C45: =_xlfn.NORM.S.INV(RAND()) -> -0.51416893 | D45: =D44+C45 -> 4.8818687 | E45: =D45-D44 -> -0.51416893 | F45: ='1.RETURNS'!D45 -> 0.0075532941 | G45: =G44*EXP(F45) -> 92.907111 | H45: The shocks (Column C) always look statistically similar.
B46: 43 | C46: =_xlfn.NORM.S.INV(RAND()) -> -1.1490575 | D46: =D45+C46 -> 3.7328113 | E46: =D46-D45 -> -1.1490575 | F46: ='1.RETURNS'!D46 -> 0.0021145723 | G46: =G45*EXP(F46) -> 93.103778
B47: 44 | C47: =_xlfn.NORM.S.INV(RAND()) -> 0.4842362 | D47: =D46+C47 -> 4.2170475 | E47: =D47-D46 -> 0.4842362 | F47: ='1.RETURNS'!D47 -> -0.00084768128 | G47: =G46*EXP(F47) -> 93.024889 | H47: CHARTS (TO THE RIGHT) →
B48: 45 | C48: =_xlfn.NORM.S.INV(RAND()) -> -2.4972954 | D48: =D47+C48 -> 1.7197521 | E48: =D48-D47 -> -2.4972954 | F48: ='1.RETURNS'!D48 -> -0.0027581407 | G48: =G47*EXP(F48) -> 92.768667 | H48: Two line charts sit to the right of this data table:
B49: 46 | C49: =_xlfn.NORM.S.INV(RAND()) -> 0.68013959 | D49: =D48+C49 -> 2.3998917 | E49: =D49-D48 -> 0.68013959 | F49: ='1.RETURNS'!D49 -> -0.014851304 | G49: =G48*EXP(F49) -> 91.401111 | H49: Top: Random Walk — drifts far from zero. (non-stationary)
B50: 47 | C50: =_xlfn.NORM.S.INV(RAND()) -> 2.1198543 | D50: =D49+C50 -> 4.519746 | E50: =D50-D49 -> 2.1198543 | F50: ='1.RETURNS'!D50 -> -0.0076831274 | G50: =G49*EXP(F50) -> 90.701556 | H50: Bottom: Random Shocks — always bounces near zero. (stationary)
B51: 48 | C51: =_xlfn.NORM.S.INV(RAND()) -> 0.87426592 | D51: =D50+C51 -> 5.3940119 | E51: =D51-D50 -> 0.87426592 | F51: ='1.RETURNS'!D51 -> -0.0043656826 | G51: =G50*EXP(F51) -> 90.306444 | H51: Both charts refresh automatically when you press F9.
B52: 49 | C52: =_xlfn.NORM.S.INV(RAND()) -> 1.4225272 | D52: =D51+C52 -> 6.816539 | E52: =D52-D51 -> 1.4225272 | F52: ='1.RETURNS'!D52 -> 0.010511056 | G52: =G51*EXP(F52) -> 91.260667
B53: 50 | C53: =_xlfn.NORM.S.INV(RAND()) -> 1.3273628 | D53: =D52+C53 -> 8.1439018 | E53: =D53-D52 -> 1.3273628 | F53: ='1.RETURNS'!D53 -> 0.0038205554 | G53: =G52*EXP(F53) -> 91.61
B54: 51 | C54: =_xlfn.NORM.S.INV(RAND()) -> -0.48857718 | D54: =D53+C54 -> 7.6553246 | E54: =D54-D53 -> -0.48857718 | F54: ='1.RETURNS'!D54 -> -0.016681933 | G54: =G53*EXP(F54) -> 90.094444
B55: 52 | C55: =_xlfn.NORM.S.INV(RAND()) -> -1.0582207 | D55: =D54+C55 -> 6.5971039 | E55: =D55-D54 -> -1.0582207 | F55: ='1.RETURNS'!D55 -> 0.0040394349 | G55: =G54*EXP(F55) -> 90.459111
B56: 53 | C56: =_xlfn.NORM.S.INV(RAND()) -> -0.83889209 | D56: =D55+C56 -> 5.7582118 | E56: =D56-D55 -> -0.83889209 | F56: ='1.RETURNS'!D56 -> -0.0034328482 | G56: =G55*EXP(F56) -> 90.149111
B57: 54 | C57: =_xlfn.NORM.S.INV(RAND()) -> -0.51936511 | D57: =D56+C57 -> 5.2388467 | E57: =D57-D56 -> -0.51936511 | F57: ='1.RETURNS'!D57 -> -0.0063454124 | G57: =G56*EXP(F57) -> 89.578889
B58: 55 | C58: =_xlfn.NORM.S.INV(RAND()) -> 1.178132 | D58: =D57+C58 -> 6.4169788 | E58: =D58-D57 -> 1.178132 | F58: ='1.RETURNS'!D58 -> 0.006744671 | G58: =G57*EXP(F58) -> 90.185111
B59: 56 | C59: =_xlfn.NORM.S.INV(RAND()) -> -2.2120431 | D59: =D58+C59 -> 4.2049357 | E59: =D59-D58 -> -2.2120431 | F59: ='1.RETURNS'!D59 -> 0.010476356 | G59: =G58*EXP(F59) -> 91.134889
B60: 57 | C60: =_xlfn.NORM.S.INV(RAND()) -> -0.24975769 | D60: =D59+C60 -> 3.955178 | E60: =D60-D59 -> -0.24975769 | F60: ='1.RETURNS'!D60 -> 0.010563192 | G60: =G59*EXP(F60) -> 92.102667
B61: 58 | C61: =_xlfn.NORM.S.INV(RAND()) -> -0.44300513 | D61: =D60+C61 -> 3.5121729 | E61: =D61-D60 -> -0.44300513 | F61: ='1.RETURNS'!D61 -> -0.0086289841 | G61: =G60*EXP(F61) -> 91.311333
B62: 59 | C62: =_xlfn.NORM.S.INV(RAND()) -> -0.29043657 | D62: =D61+C62 -> 3.2217363 | E62: =D62-D61 -> -0.29043657 | F62: ='1.RETURNS'!D62 -> -0.0028929543 | G62: =G61*EXP(F62) -> 91.047556
B63: 60 | C63: =_xlfn.NORM.S.INV(RAND()) -> -0.20647504 | D63: =D62+C63 -> 3.0152613 | E63: =D63-D62 -> -0.20647504 | F63: ='1.RETURNS'!D63 -> 0.0035960395 | G63: =G62*EXP(F63) -> 91.375556
B65: SUMMARY STATISTICS | H65: INTERPRETATION:
B66: Metric | C66: Random Shock (ε) | D66: Random Walk | E66: 1st Difference | F66: Sim. Return | G66: Sim. Level | H66: Stationary: mean & std dev stay consistent over time.
B67: Mean | C67: =AVERAGE(C4:C63) -> 0.050254355 | D67: =AVERAGE(D4:D63) -> 2.8870776 | E67: =AVERAGE(E5:E63) -> 0.057611868 | F67: =AVERAGE(F5:F63) -> -0.0015286812 | G67: =AVERAGE(G5:G63) -> 96.298911 | H67: • Shocks (C): mean ≈ 0, std dev ≈ 1.0 → STATIONARY ✓
B68: Std Dev | C68: =STDEV(C4:C63) -> 1.0510147 | D68: =STDEV(D4:D63) -> 2.9109882 | E68: =STDEV(E5:E63) -> 1.0584769 | F68: =STDEV(F5:F63) -> 0.0093300487 | G68: =STDEV(G5:G63) -> 4.6918807 | H68: • Walk (D): std dev >> 1, mean drifts → NON-STATIONARY ✗
H69: • 1st Diff (E) ≡ Shocks (C) exactly → differencing works ✓
H70: • Simulated Returns (F): mean ≈ 0, tiny std dev → STATIONARY ✓
H71: • Simulated Level (G): mean drifts from 100, std dev ≈ 5 → NON-STATIONARY ✗

Sheet 4.AUTOCORRELATION
B2: SECTION 4 — AUTOCORRELATION: DOES THE PAST PREDICT THE FUTURE?
B3: Obs | C3: Log-Return (%) | D3: Squared Return | E3: Lag-1 Return | F3: Lag-1 Squared
B4: 1 | C4: ='1.RETURNS'!D5*100 -> 0.58848723 | D4: =C4^2 -> 0.34631723 | E4: n/a | F4: n/a | H4: WHAT IS AUTOCORRELATION?
B5: 2 | C5: ='1.RETURNS'!D6*100 -> -0.12113658 | D5: =C5^2 -> 0.01467407 | E5: =C4 -> 0.58848723 | F5: =D4 -> 0.34631723
B6: 3 | C6: ='1.RETURNS'!D7*100 -> 0.66707917 | D6: =C6^2 -> 0.44499462 | E6: =C5 -> -0.12113658 | F6: =D5 -> 0.01467407 | H6: Autocorrelation measures how much today's value is correlated with
B7: 4 | C7: ='1.RETURNS'!D8*100 -> 1.6065487 | D7: =C7^2 -> 2.5809986 | E7: =C6 -> 0.66707917 | F7: =D6 -> 0.44499462 | H7: its own past values. It answers:
B8: 5 | C8: ='1.RETURNS'!D9*100 -> -0.24548761 | D8: =C8^2 -> 0.060264168 | E8: =C7 -> 1.6065487 | F8: =D7 -> 2.5809986 | H8: 'If today's return is large, is tomorrow's also likely large?'
B9: 6 | C9: ='1.RETURNS'!D10*100 -> -0.20112502 | D9: =C9^2 -> 0.040451275 | E9: =C8 -> -0.24548761 | F9: =D8 -> 0.060264168
B10: 7 | C10: ='1.RETURNS'!D11*100 -> 1.5334303 | D10: =C10^2 -> 2.3514084 | E10: =C9 -> -0.20112502 | F10: =D9 -> 0.040451275 | H10: We call this the ACF — Autocorrelation Function.
B11: 8 | C11: ='1.RETURNS'!D12*100 -> 0.88748844 | D11: =C11^2 -> 0.78763574 | E11: =C10 -> 1.5334303 | F11: =D10 -> 2.3514084 | H11: ACF at lag 1 = correlation of r_t with r_{t-1}
B12: 9 | C12: ='1.RETURNS'!D13*100 -> -0.48215906 | D12: =C12^2 -> 0.23247736 | E12: =C11 -> 0.88748844 | F12: =D11 -> 0.78763574 | H12: ACF at lag 2 = correlation of r_t with r_{t-2} ...and so on.
B13: 10 | C13: ='1.RETURNS'!D14*100 -> 0.55124296 | D13: =C13^2 -> 0.30386881 | E13: =C12 -> -0.48215906 | F13: =D12 -> 0.23247736
B14: 11 | C14: ='1.RETURNS'!D15*100 -> -0.42904899 | D14: =C14^2 -> 0.18408304 | E14: =C13 -> 0.55124296 | F14: =D13 -> 0.30386881 | H14: HOW TO COMPUTE IT IN EXCEL:
B15: 12 | C15: ='1.RETURNS'!D16*100 -> -0.42128306 | D15: =C15^2 -> 0.17747942 | E15: =C14 -> -0.42904899 | F15: =D14 -> 0.18408304
B16: 13 | C16: ='1.RETURNS'!D17*100 -> 0.25967418 | D16: =C16^2 -> 0.067430678 | E16: =C15 -> -0.42128306 | F16: =D15 -> 0.17747942 | H16: =CORREL(C5:C253, C4:C252) <- ACF at lag 1 (shift by 1 row)
B17: 14 | C17: ='1.RETURNS'!D18*100 -> -1.9171552 | D17: =C17^2 -> 3.6754841 | E17: =C16 -> 0.25967418 | F17: =D16 -> 0.067430678 | H17: =CORREL(C6:C253, C4:C251) <- ACF at lag 2 (shift by 2 rows)
B18: 15 | C18: ='1.RETURNS'!D19*100 -> -2.0470412 | D18: =C18^2 -> 4.1903776 | E18: =C17 -> -1.9171552 | F18: =D17 -> 3.6754841
B19: 16 | C19: ='1.RETURNS'!D20*100 -> -0.64772079 | D19: =C19^2 -> 0.41954222 | E19: =C18 -> -2.0470412 | F19: =D18 -> 4.1903776 | H19: This is exactly what the ACF TABLE below does.
B20: 17 | C20: ='1.RETURNS'!D21*100 -> -0.97974154 | D20: =C20^2 -> 0.95989349 | E20: =C19 -> -0.64772079 | F20: =D19 -> 0.41954222
B21: 18 | C21: ='1.RETURNS'!D22*100 -> 0.36193333 | D21: =C21^2 -> 0.13099573 | E21: =C20 -> -0.97974154 | F21: =D20 -> 0.95989349 | H21: THE KEY RESULT — TWO ACF TABLES TO COMPARE:
B22: 19 | C22: ='1.RETURNS'!D23*100 -> -0.87524506 | D22: =C22^2 -> 0.76605392 | E22: =C21 -> 0.36193333 | F22: =D21 -> 0.13099573
B23: 20 | C23: ='1.RETURNS'!D24*100 -> -1.4251167 | D23: =C23^2 -> 2.0309575 | E23: =C22 -> -0.87524506 | F23: =D22 -> 0.76605392 | H23: Table 1 = ACF of raw log-returns
B24: 21 | C24: ='1.RETURNS'!D25*100 -> 1.663348 | D24: =C24^2 -> 2.7667266 | E24: =C23 -> -1.4251167 | F24: =D23 -> 2.0309575 | H24: → Lag-1 = −0.168: statistically nonzero but R²≈3% — tiny predictive power.
B25: 22 | C25: ='1.RETURNS'!D26*100 -> -0.23279526 | D25: =C25^2 -> 0.054193635 | E25: =C24 -> 1.663348 | F25: =D24 -> 2.7667266 | H25: → Even so, knowing today's return barely helps predict tomorrow's.
B26: 23 | C26: ='1.RETURNS'!D27*100 -> 0.093726236 | D26: =C26^2 -> 0.0087846073 | E26: =C25 -> -0.23279526 | F26: =D25 -> 0.054193635 | H26: → This is consistent with market efficiency.
B27: 24 | C27: ='1.RETURNS'!D28*100 -> -1.3635752 | D27: =C27^2 -> 1.8593372 | E27: =C26 -> 0.093726236 | F27: =D26 -> 0.0087846073 | H27: → This also means ARIMA will find very little to model.
B28: 25 | C28: ='1.RETURNS'!D29*100 -> -0.55921391 | D28: =C28^2 -> 0.3127202 | E28: =C27 -> -1.3635752 | F28: =D27 -> 1.8593372 | H28: Note: lag-1 at −0.168 exceeds the 0.1 threshold in column E, so it shows 'Not near zero' — accurate. The key point is that R²≈3% makes it economically negligible.
B29: 26 | C29: ='1.RETURNS'!D30*100 -> 0.13854201 | D29: =C29^2 -> 0.019193889 | E29: =C28 -> -0.55921391 | F29: =D28 -> 0.3127202 | H29: Table 2 = ACF of SQUARED returns
B30: 27 | C30: ='1.RETURNS'!D31*100 -> -1.1016358 | D30: =C30^2 -> 1.2136014 | E30: =C29 -> 0.13854201 | F30: =D29 -> 0.019193889 | H30: → Correlations are clearly positive and decay slowly!
B31: 28 | C31: ='1.RETURNS'!D32*100 -> 0.43343887 | D31: =C31^2 -> 0.18786925 | E31: =C30 -> -1.1016358 | F31: =D30 -> 1.2136014 | H31: → The SIZE of today's move predicts the size of tomorrow's move.
B32: 29 | C32: ='1.RETURNS'!D33*100 -> -0.59637653 | D32: =C32^2 -> 0.35566497 | E32: =C31 -> 0.43343887 | F32: =D31 -> 0.18786925 | H32: → This is volatility clustering — structure in the variance.
B33: 30 | C33: ='1.RETURNS'!D34*100 -> -0.27659885 | D33: =C33^2 -> 0.076506926 | E33: =C32 -> -0.59637653 | F33: =D32 -> 0.35566497 | H33: → This is exactly what GARCH is designed to capture.
B34: 31 | C34: ='1.RETURNS'!D35*100 -> -0.5475057 | D34: =C34^2 -> 0.29976249 | E34: =C33 -> -0.27659885 | F34: =D33 -> 0.076506926
B35: 32 | C35: ='1.RETURNS'!D36*100 -> 1.8407344 | D35: =C35^2 -> 3.388303 | E35: =C34 -> -0.5475057 | F35: =D34 -> 0.29976249 | H35: INTERPRETATION:
B36: 33 | C36: ='1.RETURNS'!D37*100 -> 0.0087750088 | D36: =C36^2 -> 7.7000779e-05 | E36: =C35 -> 1.8407344 | F36: =D35 -> 3.388303 | H36: Returns are unpredictable in direction but
B37: 34 | C37: ='1.RETURNS'!D38*100 -> -0.93562806 | D37: =C37^2 -> 0.87539986 | E37: =C36 -> 0.0087750088 | F37: =D36 -> 7.7000779e-05 | H37: predictable in magnitude.
B38: 35 | C38: ='1.RETURNS'!D39*100 -> 0.90814585 | D38: =C38^2 -> 0.82472889 | E38: =C37 -> -0.93562806 | F38: =D37 -> 0.87539986 | H38: That gap between the two tables is the entire
B39: 36 | C39: ='1.RETURNS'!D40*100 -> -1.3189794 | D39: =C39^2 -> 1.7397068 | E39: =C38 -> 0.90814585 | F39: =D38 -> 0.82472889 | H39: intellectual justification for GARCH modeling.
B40: 37 | C40: ='1.RETURNS'!D41*100 -> 0.25898212 | D40: =C40^2 -> 0.067071739 | E40: =C39 -> -1.3189794 | F40: =D39 -> 1.7397068
B41: 38 | C41: ='1.RETURNS'!D42*100 -> -1.8806259 | D41: =C41^2 -> 3.5367537 | E41: =C40 -> 0.25898212 | F41: =D40 -> 0.067071739
B42: 39 | C42: ='1.RETURNS'!D43*100 -> -1.5574917 | D42: =C42^2 -> 2.4257805 | E42: =C41 -> -1.8806259 | F42: =D41 -> 3.5367537
B43: 40 | C43: ='1.RETURNS'!D44*100 -> 0.24878126 | D43: =C43^2 -> 0.061892114 | E43: =C42 -> -1.5574917 | F43: =D42 -> 2.4257805
B44: 41 | C44: ='1.RETURNS'!D45*100 -> 0.75532941 | D44: =C44^2 -> 0.57052251 | E44: =C43 -> 0.24878126 | F44: =D43 -> 0.061892114
B45: 42 | C45: ='1.RETURNS'!D46*100 -> 0.21145723 | D45: =C45^2 -> 0.044714162 | E45: =C44 -> 0.75532941 | F45: =D44 -> 0.57052251
B46: 43 | C46: ='1.RETURNS'!D47*100 -> -0.084768128 | D46: =C46^2 -> 0.0071856356 | E46: =C45 -> 0.21145723 | F46: =D45 -> 0.044714162
B47: 44 | C47: ='1.RETURNS'!D48*100 -> -0.27581407 | D47: =C47^2 -> 0.076073402 | E47: =C46 -> -0.084768128 | F47: =D46 -> 0.0071856356
B48: 45 | C48: ='1.RETURNS'!D49*100 -> -1.4851304 | D48: =C48^2 -> 2.2056123 | E48: =C47 -> -0.27581407 | F48: =D47 -> 0.076073402
B49: 46 | C49: ='1.RETURNS'!D50*100 -> -0.76831274 | D49: =C49^2 -> 0.59030447 | E49: =C48 -> -1.4851304 | F49: =D48 -> 2.2056123
B50: 47 | C50: ='1.RETURNS'!D51*100 -> -0.43656826 | D50: =C50^2 -> 0.19059185 | E50: =C49 -> -0.76831274 | F50: =D49 -> 0.59030447
B51: 48 | C51: ='1.RETURNS'!D52*100 -> 1.0511056 | D51: =C51^2 -> 1.1048229 | E51: =C50 -> -0.43656826 | F51: =D50 -> 0.19059185
... B63: 60 | C63: ='1.RETURNS'!D64*100 -> 1.0092627 | D63: =C63^2 -> 1.0186112 | E63: =C62 -> 0.35960395 | F63: =D62 -> 0.129315
B66: ACF TABLE — Autocorrelation at Lags 1 to 10
B67: Lag | C67: ACF (raw returns) | D67: ACF (squared returns) | E67: Is raw near zero? | F67: Is squared > 0?
B68: 1 | C68: =CORREL('1.RETURNS'!D6:D254,'1.RETURNS'!D5:D253) -> -0.16792779 | D68: {=CORREL(('1.RETURNS'!D6:D254)^2,('1.RETURNS'!D5:D253)^2)} -> 0.094382044 | E68: =IF(ABS(C68)<0.1,"YES — near zero","Not near zero") -> Not near zero | F68: =IF(D68>0.05,"YES — clustering!","Weak") -> YES — clustering! | G68: =C68^2 -> 0.028199742
B69: 2 | C69: =CORREL('1.RETURNS'!D7:D254,'1.RETURNS'!D5:D252) -> 0.13936336 | D69: {=CORREL(('1.RETURNS'!D7:D254)^2,('1.RETURNS'!D5:D252)^2)} -> 0.14222002 | E69: =IF(ABS(C69)<0.1,"YES — near zero","Not near zero") -> Not near zero | F69: =IF(D69>0.05,"YES — clustering!","Weak") -> YES — clustering!
B70: 3 | C70: =CORREL('1.RETURNS'!D8:D254,'1.RETURNS'!D5:D251) -> -0.10804433 | D70: {=CORREL(('1.RETURNS'!D8:D254)^2,('1.RETURNS'!D5:D251)^2)} -> 0.089525857 | E70: =IF(ABS(C70)<0.1,"YES — near zero","Not near zero") -> Not near zero | F70: =IF(D70>0.05,"YES — clustering!","Weak") -> YES — clustering!
B71: 4 | C71: =CORREL('1.RETURNS'!D9:D254,'1.RETURNS'!D5:D250) -> 0.072265681 | D71: {=CORREL(('1.RETURNS'!D9:D254)^2,('1.RETURNS'!D5:D250)^2)} -> 0.28510245 | E71: =IF(ABS(C71)<0.1,"YES — near zero","Not near zero") -> YES — near zero | F71: =IF(D71>0.05,"YES — clustering!","Weak") -> YES — clustering!
B72: 5 | C72: =CORREL('1.RETURNS'!D10:D254,'1.RETURNS'!D5:D249) -> -0.030267311 | D72: {=CORREL(('1.RETURNS'!D10:D254)^2,('1.RETURNS'!D5:D249)^2)} -> 0.066794846 | E72: =IF(ABS(C72)<0.1,"YES — near zero","Not near zero") -> YES — near zero | F72: =IF(D72>0.05,"YES — clustering!","Weak") -> YES — clustering!
B73: 6 | C73: =CORREL('1.RETURNS'!D11:D254,'1.RETURNS'!D5:D248) -> 0.12281281 | D73: {=CORREL(('1.RETURNS'!D11:D254)^2,('1.RETURNS'!D5:D248)^2)} -> -0.0059643576 | E73: =IF(ABS(C73)<0.1,"YES — near zero","Not near zero") -> Not near zero | F73: =IF(D73>0.05,"YES — clustering!","Weak") -> Weak
B74: 7 | C74: =CORREL('1.RETURNS'!D12:D254,'1.RETURNS'!D5:D247) -> -0.10100867 | D74: {=CORREL(('1.RETURNS'!D12:D254)^2,('1.RETURNS'!D5:D247)^2)} -> 0.02483916 | E74: =IF(ABS(C74)<0.1,"YES — near zero","Not near zero") -> Not near zero | F74: =IF(D74>0.05,"YES — clustering!","Weak") -> Weak
B75: 8 | C75: =CORREL('1.RETURNS'!D13:D254,'1.RETURNS'!D5:D246) -> 0.12604096 | D75: {=CORREL(('1.RETURNS'!D13:D254)^2,('1.RETURNS'!D5:D246)^2)} -> 0.060574636 | E75: =IF(ABS(C75)<0.1,"YES — near zero","Not near zero") -> Not near zero | F75: =IF(D75>0.05,"YES — clustering!","Weak") -> YES — clustering!
B76: 9 | C76: =CORREL('1.RETURNS'!D14:D254,'1.RETURNS'!D5:D245) -> -0.081800826 | D76: {=CORREL(('1.RETURNS'!D14:D254)^2,('1.RETURNS'!D5:D245)^2)} -> -0.0051825929 | E76: =IF(ABS(C76)<0.1,"YES — near zero","Not near zero") -> YES — near zero | F76: =IF(D76>0.05,"YES — clustering!","Weak") -> Weak
B77: 10 | C77: =CORREL('1.RETURNS'!D15:D254,'1.RETURNS'!D5:D244) -> 0.047901803 | D77: {=CORREL(('1.RETURNS'!D15:D254)^2,('1.RETURNS'!D5:D244)^2)} -> -0.038893001 | E77: =IF(ABS(C77)<0.1,"YES — near zero","Not near zero") -> YES — near zero | F77: =IF(D77>0.05,"YES — clustering!","Weak") -> Weak

Sheet 5.ARIMA
B1: φ (AR): | C1: 0.95 | D1: θ (MA): | E1: 0.7 | J1: φ̂ (from simulated return series): | K1: =CORREL('1.RETURNS'!D6:D254,'1.RETURNS'!D5:D253) -> -0.16792779 | M1: θ̂ (MA1, simulated data): | N1: =(1-SQRT(1-4*K1^2))/(2*K1) -> -0.17295084
B2: SECTION 5 — ARIMA: MODELING THE MEAN OF A TIME SERIES | J2: SIMULATED RETURN SERIES — AR(1) APPLIED [Illustrative, 2023 calendar] | M2: MA(1) & ARIMA(1,0,1) APPLIED TO SIMULATED RETURN SERIES
A3: ε (AR) | B3: Obs | C3: AR(1) Simulation | D3: MA(1) Simulation | E3: Random Walk | F3: 1st Diff (= shock) | G3: ε (MA) | H3: ARIMA(1,0,1) | J3: Actual Return (×100 = % daily) | K3: AR(1) Fitted: φ̂ × r(t−1) | L3: Residual/Error: r(t) − φ̂×r(t−1) | M3: MA(1) ε̂(t) [helper] | N3: MA(1) Fitted: θ̂×ε̂(t−1) | O3: ARIMA ε̂(t) [helper] | P3: ARIMA(1,0,1) Fitted: φ̂×r(t−1)+θ̂×ε̂(t−1)
A4: n/a | B4: =ROW()-3 -> 1 | C4: =_xlfn.NORM.INV(RAND(),0,1) -> -0.34384148 | D4: =G4 -> -0.20850132 | E4: =_xlfn.NORM.INV(RAND(),0,1) -> 1.2479159 | F4: n/a | G4: =_xlfn.NORM.INV(RAND(),0,1) -> -0.20850132 | H4: =G4 -> -0.20850132 | I4: ▌ ARIMA(p, d, q) — MODELING THE MEAN | J4: ='1.RETURNS'!D5*100 -> 0.58848723 | K4: n/a | L4: n/a | M4: =J4 -> 0.58848723 | N4: n/a | O4: =J4 -> 0.58848723 | P4: n/a
A5: =_xlfn.NORM.INV(RAND(),0,1) -> -1.2694067 | B5: =ROW()-3 -> 2 | C5: =$C$1*C4+A5 -> -1.5960561 | D5: =G5+$E$1*G4 -> -0.81309841 | E5: =E4+F5 -> 1.0909878 | F5: =_xlfn.NORM.INV(RAND(),0,1) -> -0.15692813 | G5: =_xlfn.NORM.INV(RAND(),0,1) -> -0.66714748 | H5: =$C$1*H4+G5+$E$1*G4 -> -1.0111747 | I5: ARIMA combines three tools into one model to capture structure in the conditional mean: | J5: ='1.RETURNS'!D6*100 -> -0.12113658 | K5: =$K$1*J4 -> -0.098823359 | L5: =J5-K5 -> -0.022313217 | M5: =J5-$N$1*M4 -> -0.019357214 | N5: =$N$1*M4 -> -0.10177936 | O5: =J5-$K$1*J4-$N$1*O4 -> 0.079466145 | P5: =$K$1*J4+$N$1*O4 -> -0.20060272
A6: =_xlfn.NORM.INV(RAND(),0,1) -> -1.0917576 | B6: =ROW()-3 -> 3 | C6: =$C$1*C5+A6 -> -2.6080109 | D6: =G6+$E$1*G5 -> 0.30876878 | E6: =E5+F6 -> 0.75367204 | F6: =_xlfn.NORM.INV(RAND(),0,1) -> -0.33731573 | G6: =_xlfn.NORM.INV(RAND(),0,1) -> 0.77577201 | H6: =$C$1*H5+G6+$E$1*G5 -> -0.65184716 | I6: AR = AutoRegressive · today's value depends on past VALUES of y | J6: ='1.RETURNS'!D7*100 -> 0.66707917 | K6: =$K$1*J5 -> 0.020342197 | L6: =J6-K6 -> 0.64673698 | M6: =J6-$N$1*M5 -> 0.66373133 | N6: =$N$1*M5 -> 0.0033478464 | O6: =J6-$K$1*J5-$N$1*O5 -> 0.66048071 | P6: =$K$1*J5+$N$1*O5 -> 0.0065984605 | Q6: =J6-'5.ARIMA'!P6 -> 0.66048071
A7: =_xlfn.NORM.INV(RAND(),0,1) -> -0.42388598 | B7: =ROW()-3 -> 4 | C7: =$C$1*C6+A7 -> -2.9014963 | D7: =G7+$E$1*G6 -> 0.61738419 | E7: =E6+F7 -> 0.33389596 | F7: =_xlfn.NORM.INV(RAND(),0,1) -> -0.41977609 | G7: =_xlfn.NORM.INV(RAND(),0,1) -> 0.074343782 | H7: =$C$1*H6+G7+$E$1*G6 -> -0.0018706073 | I7: I = Integrated · how many times the series is differenced first | J7: ='1.RETURNS'!D8*100 -> 1.6065487 | K7: =$K$1*J6 -> -0.11202113 | L7: =J7-K7 -> 1.7185698 | M7: =J7-$N$1*M6 -> 1.7213416 | N7: =$N$1*M6 -> -0.11479289 | O7: =J7-$K$1*J6-$N$1*O6 -> 1.8328005 | P7: =$K$1*J6+$N$1*O6 -> -0.22625183
A8: =_xlfn.NORM.INV(RAND(),0,1) -> 0.23633082 | B8: =ROW()-3 -> 5 | C8: =$C$1*C7+A8 -> -2.5200907 | D8: =G8+$E$1*G7 -> -0.57982611 | E8: =E7+F8 -> -0.36314519 | F8: =_xlfn.NORM.INV(RAND(),0,1) -> -0.69704115 | G8: =_xlfn.NORM.INV(RAND(),0,1) -> -0.63186676 | H8: =$C$1*H7+G8+$E$1*G7 -> -0.58160319 | I8: MA = Moving Average · today's value depends on past SHOCKS (ε) | J8: ='1.RETURNS'!D9*100 -> -0.24548761 | K8: =$K$1*J7 -> -0.26978416 | L8: =J8-K8 -> 0.024296549 | M8: =J8-$N$1*M7 -> 0.052219858 | N8: =$N$1*M7 -> -0.29770747 | O8: =J8-$K$1*J7-$N$1*O7 -> 0.34128094 | P8: =$K$1*J7+$N$1*O7 -> -0.58676855
A9: =_xlfn.NORM.INV(RAND(),0,1) -> 1.378673 | B9: =ROW()-3 -> 6 | C9: =$C$1*C8+A9 -> -1.0154132 | D9: =G9+$E$1*G8 -> -0.227681 | E9: =E8+F9 -> 0.82987368 | F9: =_xlfn.NORM.INV(RAND(),0,1) -> 1.1930189 | G9: =_xlfn.NORM.INV(RAND(),0,1) -> 0.21462573 | H9: =$C$1*H8+G9+$E$1*G8 -> -0.78020403 | I9: Notation: ARIMA(p, d, q) where p = # AR lags, d = # differences, q = # MA lags | J9: ='1.RETURNS'!D10*100 -> -0.20112502 | K9: =$K$1*J8 -> 0.041224192 | L9: =J9-K9 -> -0.24234921 | M9: =J9-$N$1*M8 -> -0.19209355 | N9: =$N$1*M8 -> -0.0090314685 | O9: =J9-$K$1*J8-$N$1*O8 -> -0.18332439 | P9: =$K$1*J8+$N$1*O8 -> -0.017800634
A10: =_xlfn.NORM.INV(RAND(),0,1) -> -1.716232 | B10: =ROW()-3 -> 7 | C10: =$C$1*C9+A10 -> -2.6808745 | D10: =G10+$E$1*G9 -> -0.42288065 | E10: =E9+F10 -> 1.0368187 | F10: =_xlfn.NORM.INV(RAND(),0,1) -> 0.20694501 | G10: =_xlfn.NORM.INV(RAND(),0,1) -> -0.57311866 | H10: =$C$1*H9+G10+$E$1*G9 -> -1.1640745 | J10: ='1.RETURNS'!D11*100 -> 1.5334303 | K10: =$K$1*J9 -> 0.03377448 | L10: =J10-K10 -> 1.4996558 | M10: =J10-$N$1*M9 -> 1.5002075 | N10: =$N$1*M9 -> 0.033222742 | O10: =J10-$K$1*J9-$N$1*O9 -> 1.4679497 | P10: =$K$1*J9+$N$1*O9 -> 0.065480587
A11: =_xlfn.NORM.INV(RAND(),0,1) -> -0.57312432 | B11: =ROW()-3 -> 8 | C11: =$C$1*C10+A11 -> -3.1199551 | D11: =G11+$E$1*G10 -> -1.3213294 | E11: =E10+F11 -> 1.4099151 | F11: =_xlfn.NORM.INV(RAND(),0,1) -> 0.37309645 | G11: =_xlfn.NORM.INV(RAND(),0,1) -> -0.9201463 | H11: =$C$1*H10+G11+$E$1*G10 -> -2.4272001 | I11: ▌ PART A — AR(p): AUTOREGRESSIVE MODEL [Column C] | J11: ='1.RETURNS'!D12*100 -> 0.88748844 | K11: =$K$1*J10 -> -0.25750555 | L11: =J11-K11 -> 1.144994 | M11: =J11-$N$1*M10 -> 1.1469506 | N11: =$N$1*M10 -> -0.25946215 | O11: =J11-$K$1*J10-$N$1*O10 -> 1.3988771 | P11: =$K$1*J10+$N$1*O10 -> -0.51138868
A12: =_xlfn.NORM.INV(RAND(),0,1) -> 0.27117501 | B12: =ROW()-3 -> 9 | C12: =$C$1*C11+A12 -> -2.6927823 | D12: =G12+$E$1*G11 -> -1.2866289 | E12: =E11+F12 -> 2.2251914 | F12: =_xlfn.NORM.INV(RAND(),0,1) -> 0.81527623 | G12: =_xlfn.NORM.INV(RAND(),0,1) -> -0.6425265 | H12: =$C$1*H11+G12+$E$1*G11 -> -3.592469 | I12: AR(p): today's value is a weighted sum of the last p values plus white noise ε(t): | J12: ='1.RETURNS'!D13*100 -> -0.48215906 | K12: =$K$1*J11 -> -0.14903397 | L12: =J12-K12 -> -0.33312509 | M12: =J12-$N$1*M11 -> -0.28379299 | N12: =$N$1*M11 -> -0.19836607 | O12: =J12-$K$1*J11-$N$1*O11 -> -0.091188117 | P12: =$K$1*J11+$N$1*O11 -> -0.39097095
A13: =_xlfn.NORM.INV(RAND(),0,1) -> 0.099459566 | B13: =ROW()-3 -> 10 | C13: =$C$1*C12+A13 -> -2.4586836 | D13: =G13+$E$1*G12 -> -2.0983316 | E13: =E12+F13 -> 0.83744536 | F13: =_xlfn.NORM.INV(RAND(),0,1) -> -1.387746 | G13: =_xlfn.NORM.INV(RAND(),0,1) -> -1.6485631 | H13: =$C$1*H12+G13+$E$1*G12 -> -5.5111772 | I13: y(t) = φ₁·y(t−1) + φ₂·y(t−2) + ··· + φₚ·y(t−p) + ε(t) ← general AR(p) | J13: ='1.RETURNS'!D14*100 -> 0.55124296 | K13: =$K$1*J12 -> 0.080967905 | L13: =J13-K13 -> 0.47027506 | M13: =J13-$N$1*M12 -> 0.50216073 | N13: =$N$1*M12 -> 0.049082237 | O13: =J13-$K$1*J12-$N$1*O12 -> 0.454504 | P13: =$K$1*J12+$N$1*O12 -> 0.096738966
A14: =_xlfn.NORM.INV(RAND(),0,1) -> -0.13334775 | B14: =ROW()-3 -> 11 | C14: =$C$1*C13+A14 -> -2.4690972 | D14: =G14+$E$1*G13 -> -0.19202373 | E14: =E13+F14 -> 1.1382691 | F14: =_xlfn.NORM.INV(RAND(),0,1) -> 0.30082375 | G14: =_xlfn.NORM.INV(RAND(),0,1) -> 0.9619704 | H14: =$C$1*H13+G14+$E$1*G13 -> -5.427642 | I14: AR(1) simulated in Column C [φ = 0.7, stored in C1 — change to experiment]: | J14: ='1.RETURNS'!D15*100 -> -0.42904899 | K14: =$K$1*J13 -> -0.092569011 | L14: =J14-K14 -> -0.33647998 | M14: =J14-$N$1*M13 -> -0.34219987 | N14: =$N$1*M13 -> -0.086849121 | O14: =J14-$K$1*J13-$N$1*O13 -> -0.25787313 | P14: =$K$1*J13+$N$1*O13 -> -0.17117586
A15: =_xlfn.NORM.INV(RAND(),0,1) -> -0.34291639 | B15: =ROW()-3 -> 12 | C15: =$C$1*C14+A15 -> -2.6885587 | D15: =G15+$E$1*G14 -> -0.15282932 | E15: =E14+F15 -> 1.4377766 | F15: =_xlfn.NORM.INV(RAND(),0,1) -> 0.29950749 | G15: =_xlfn.NORM.INV(RAND(),0,1) -> -0.8262086 | H15: =$C$1*H14+G15+$E$1*G14 -> -5.3090893 | I15: y(t) = φ · y(t−1) + ε(t) | J15: ='1.RETURNS'!D16*100 -> -0.42128306 | K15: =$K$1*J14 -> 0.072049248 | L15: =J15-K15 -> -0.49333231 | M15: =J15-$N$1*M14 -> -0.48046682 | N15: =$N$1*M14 -> 0.059183756 | O15: =J15-$K$1*J14-$N$1*O14 -> -0.53793168 | P15: =$K$1*J14+$N$1*O14 -> 0.11664862
A16: =_xlfn.NORM.INV(RAND(),0,1) -> -0.55069572 | B16: =ROW()-3 -> 13 | C16: =$C$1*C15+A16 -> -3.1048265 | D16: =G16+$E$1*G15 -> -0.66031733 | E16: =E15+F16 -> 0.5561792 | F16: =_xlfn.NORM.INV(RAND(),0,1) -> -0.88159741 | G16: =_xlfn.NORM.INV(RAND(),0,1) -> -0.081971312 | H16: =$C$1*H15+G16+$E$1*G15 -> -5.7039521 | I16: ↳ Excel cell: C5 = $C$1 × C4 + A5 [C1 = φ = 0.7, C4 = y(t−1), A5 = ε(t)] | J16: ='1.RETURNS'!D17*100 -> 0.25967418 | K16: =$K$1*J15 -> 0.070745132 | L16: =J16-K16 -> 0.18892904 | M16: =J16-$N$1*M15 -> 0.17657704 | N16: =$N$1*M15 -> 0.083097141 | O16: =J16-$K$1*J15-$N$1*O15 -> 0.095893307 | P16: =$K$1*J15+$N$1*O15 -> 0.16378087
A17: =_xlfn.NORM.INV(RAND(),0,1) -> -0.78137756 | B17: =ROW()-3 -> 14 | C17: =$C$1*C16+A17 -> -3.7309628 | D17: =G17+$E$1*G16 -> -0.04090451 | E17: =E16+F17 -> 0.44982235 | F17: =_xlfn.NORM.INV(RAND(),0,1) -> -0.10635684 | G17: =_xlfn.NORM.INV(RAND(),0,1) -> 0.016475408 | H17: =$C$1*H16+G17+$E$1*G16 -> -5.459659 | I17: Persistence: φ = 0.7 means 70% of last period's level carries into today's value. | J17: ='1.RETURNS'!D18*100 -> -1.9171552 | K17: =$K$1*J16 -> -0.04360651 | L17: =J17-K17 -> -1.8735487 | M17: =J17-$N$1*M16 -> -1.8866161 | N17: =$N$1*M16 -> -0.030539147 | O17: =J17-$K$1*J16-$N$1*O16 -> -1.8569639 | P17: =$K$1*J16+$N$1*O16 -> -0.060191338
A18: =_xlfn.NORM.INV(RAND(),0,1) -> 1.6142582 | B18: =ROW()-3 -> 15 | C18: =$C$1*C17+A18 -> -1.9301565 | D18: =G18+$E$1*G17 -> 0.21319264 | E18: =E17+F18 -> -0.2710434 | F18: =_xlfn.NORM.INV(RAND(),0,1) -> -0.72086575 | G18: =_xlfn.NORM.INV(RAND(),0,1) -> 0.20165986 | H18: =$C$1*H17+G18+$E$1*G17 -> -4.9734834 | I18: Stability: ||φ|| < 1 required for stationarity. At φ = 1 the process becomes a random walk. | J18: ='1.RETURNS'!D19*100 -> -2.0470412 | K18: =$K$1*J17 -> 0.32194363 | L18: =J18-K18 -> -2.3689848 | M18: =J18-$N$1*M17 -> -2.373333 | N18: =$N$1*M17 -> 0.32629184 | O18: =J18-$K$1*J17-$N$1*O17 -> -2.6901483 | P18: =$K$1*J17+$N$1*O17 -> 0.6431071
A19: =_xlfn.NORM.INV(RAND(),0,1) -> 1.2444162 | B19: =ROW()-3 -> 16 | C19: =$C$1*C18+A19 -> -0.58923247 | D19: =G19+$E$1*G18 -> 0.23847845 | E19: =E18+F19 -> 1.3712497 | F19: =_xlfn.NORM.INV(RAND(),0,1) -> 1.6422931 | G19: =_xlfn.NORM.INV(RAND(),0,1) -> 0.097316551 | H19: =$C$1*H18+G19+$E$1*G18 -> -4.4863308 | I19: Long-run variance: Var[y(t)] = σ²_ε / (1 − φ²) [grows as φ → 1] | J19: ='1.RETURNS'!D20*100 -> -0.64772079 | K19: =$K$1*J18 -> 0.3437551 | L19: =J19-K19 -> -0.99147589 | M19: =J19-$N$1*M18 -> -1.0581907 | N19: =$N$1*M18 -> 0.41046994 | O19: =J19-$K$1*J18-$N$1*O18 -> -1.4567393 | P19: =$K$1*J18+$N$1*O18 -> 0.80901851
A20: =_xlfn.NORM.INV(RAND(),0,1) -> 0.36738545 | B20: =ROW()-3 -> 17 | C20: =$C$1*C19+A20 -> -0.1923854 | D20: =G20+$E$1*G19 -> 0.51097909 | E20: =E19+F20 -> 1.6271123 | F20: =_xlfn.NORM.INV(RAND(),0,1) -> 0.25586258 | G20: =_xlfn.NORM.INV(RAND(),0,1) -> 0.44285751 | H20: =$C$1*H19+G20+$E$1*G19 -> -3.7510352 | J20: ='1.RETURNS'!D21*100 -> -0.97974154 | K20: =$K$1*J19 -> 0.10877032 | L20: =J20-K20 -> -1.0885119 | M20: =J20-$N$1*M19 -> -1.1627565 | N20: =$N$1*M19 -> 0.18301498 | O20: =J20-$K$1*J19-$N$1*O19 -> -1.3404562 | P20: =$K$1*J19+$N$1*O19 -> 0.36071461
A21: =_xlfn.NORM.INV(RAND(),0,1) -> -0.25991807 | B21: =ROW()-3 -> 18 | C21: =$C$1*C20+A21 -> -0.44268421 | D21: =G21+$E$1*G20 -> 0.72194793 | E21: =E20+F21 -> 1.8562381 | F21: =_xlfn.NORM.INV(RAND(),0,1) -> 0.22912582 | G21: =_xlfn.NORM.INV(RAND(),0,1) -> 0.41194767 | H21: =$C$1*H20+G21+$E$1*G20 -> -2.8415355 | I21: ▌ PART B — MA(q): MOVING AVERAGE MODEL [Column D] | J21: ='1.RETURNS'!D22*100 -> 0.36193333 | K21: =$K$1*J20 -> 0.16452583 | L21: =J21-K21 -> 0.1974075 | M21: =J21-$N$1*M20 -> 0.16083361 | N21: =$N$1*M20 -> 0.20109972 | O21: =J21-$K$1*J20-$N$1*O20 -> -0.034425521 | P21: =$K$1*J20+$N$1*O20 -> 0.39635885
A22: =_xlfn.NORM.INV(RAND(),0,1) -> -0.73406048 | B22: =ROW()-3 -> 19 | C22: =$C$1*C21+A22 -> -1.1546105 | D22: =G22+$E$1*G21 -> 0.53769054 | E22: =E21+F22 -> 2.4329261 | F22: =_xlfn.NORM.INV(RAND(),0,1) -> 0.57668799 | G22: =_xlfn.NORM.INV(RAND(),0,1) -> 0.24932717 | H22: =$C$1*H21+G22+$E$1*G21 -> -2.1617682 | I22: MA(q): today's value is a weighted sum of the current and last q−1 shocks: | J22: ='1.RETURNS'!D23*100 -> -0.87524506 | K22: =$K$1*J21 -> -0.060778663 | L22: =J22-K22 -> -0.8144664 | M22: =J22-$N$1*M21 -> -0.84742875 | N22: =$N$1*M21 -> -0.027816308 | O22: =J22-$K$1*J21-$N$1*O21 -> -0.82042032 | P22: =$K$1*J21+$N$1*O21 -> -0.05482474
A23: =_xlfn.NORM.INV(RAND(),0,1) -> 0.15752506 | B23: =ROW()-3 -> 20 | C23: =$C$1*C22+A23 -> -0.93935489 | D23: =G23+$E$1*G22 -> -0.26141869 | E23: =E22+F23 -> 2.8571091 | F23: =_xlfn.NORM.INV(RAND(),0,1) -> 0.42418298 | G23: =_xlfn.NORM.INV(RAND(),0,1) -> -0.43594771 | H23: =$C$1*H22+G23+$E$1*G22 -> -2.3150985 | I23: y(t) = ε(t) + θ₁·ε(t−1) + θ₂·ε(t−2) + ··· + θ_q·ε(t−q) ← general MA(q) | J23: ='1.RETURNS'!D24*100 -> -1.4251167 | K23: =$K$1*J22 -> 0.14697797 | L23: =J23-K23 -> -1.5720946 | M23: =J23-$N$1*M22 -> -1.5716802 | N23: =$N$1*M22 -> 0.14656352 | O23: =J23-$K$1*J22-$N$1*O22 -> -1.713987 | P23: =$K$1*J22+$N$1*O22 -> 0.28887035
A24: =_xlfn.NORM.INV(RAND(),0,1) -> 0.002043596 | B24: =ROW()-3 -> 21 | C24: =$C$1*C23+A24 -> -0.89034354 | D24: =G24+$E$1*G23 -> -0.19252911 | E24: =E23+F24 -> 2.6923863 | F24: =_xlfn.NORM.INV(RAND(),0,1) -> -0.16472278 | G24: =_xlfn.NORM.INV(RAND(),0,1) -> 0.11263429 | H24: =$C$1*H23+G24+$E$1*G23 -> -2.3918726 | I24: MA(1) simulated in Column D [θ = 0.6, stored in E1 — change to experiment]: | J24: ='1.RETURNS'!D25*100 -> 1.663348 | K24: =$K$1*J23 -> 0.23931669 | L24: =J24-K24 -> 1.4240313 | M24: =J24-$N$1*M23 -> 1.3915246 | N24: =$N$1*M23 -> 0.27182341 | O24: =J24-$K$1*J23-$N$1*O23 -> 1.1275958 | P24: =$K$1*J23+$N$1*O23 -> 0.53575218
A25: =_xlfn.NORM.INV(RAND(),0,1) -> 0.70367625 | B25: =ROW()-3 -> 22 | C25: =$C$1*C24+A25 -> -0.14215011 | D25: =G25+$E$1*G24 -> 0.10436858 | E25: =E24+F25 -> 1.4931956 | F25: =_xlfn.NORM.INV(RAND(),0,1) -> -1.1991907 | G25: =_xlfn.NORM.INV(RAND(),0,1) -> 0.025524582 | H25: =$C$1*H24+G25+$E$1*G24 -> -2.1679104 | I25: y(t) = ε(t) + θ · ε(t−1) | J25: ='1.RETURNS'!D26*100 -> -0.23279526 | K25: =$K$1*J24 -> -0.27932235 | L25: =J25-K25 -> 0.046527087 | M25: =J25-$N$1*M24 -> 0.0078700881 | N25: =$N$1*M24 -> -0.24066535 | O25: =J25-$K$1*J24-$N$1*O24 -> 0.24154574 | P25: =$K$1*J24+$N$1*O24 -> -0.474341
A26: =_xlfn.NORM.INV(RAND(),0,1) -> 0.097745077 | B26: =ROW()-3 -> 23 | C26: =$C$1*C25+A26 -> -0.037297532 | D26: =G26+$E$1*G25 -> 0.56228399 | E26: =E25+F26 -> 1.6501406 | F26: =_xlfn.NORM.INV(RAND(),0,1) -> 0.15694493 | G26: =_xlfn.NORM.INV(RAND(),0,1) -> 0.54441679 | H26: =$C$1*H25+G26+$E$1*G25 -> -1.4972309 | I26: ↳ Excel cell: D5 = G5 + $E$1 × G4 [G5 = ε(t), E1 = θ = 0.6, G4 = ε(t−1)] | J26: ='1.RETURNS'!D27*100 -> 0.093726236 | K26: =$K$1*J25 -> 0.039092794 | L26: =J26-K26 -> 0.054633442 | M26: =J26-$N$1*M25 -> 0.095087374 | N26: =$N$1*M25 -> -0.0013611384 | O26: =J26-$K$1*J25-$N$1*O25 -> 0.096408981 | P26: =$K$1*J25+$N$1*O25 -> -0.0026827448
A27: =_xlfn.NORM.INV(RAND(),0,1) -> 0.59531868 | B27: =ROW()-3 -> 24 | C27: =$C$1*C26+A27 -> 0.55988603 | D27: =G27+$E$1*G26 -> -0.88451142 | E27: =E26+F27 -> 1.8611612 | F27: =_xlfn.NORM.INV(RAND(),0,1) -> 0.21102062 | G27: =_xlfn.NORM.INV(RAND(),0,1) -> -1.2656032 | H27: =$C$1*H26+G27+$E$1*G26 -> -2.3068808 | I27: Intuition: today's value = current shock + a fraction of yesterday's shock. | J27: ='1.RETURNS'!D28*100 -> -1.3635752 | K27: =$K$1*J26 -> -0.015739239 | L27: =J27-K27 -> -1.3478359 | M27: =J27-$N$1*M26 -> -1.3471297 | N27: =$N$1*M26 -> -0.016445441 | O27: =J27-$K$1*J26-$N$1*O26 -> -1.3311619 | P27: =$K$1*J26+$N$1*O26 -> -0.032413254
A28: =_xlfn.NORM.INV(RAND(),0,1) -> -1.2092017 | B28: =ROW()-3 -> 25 | C28: =$C$1*C27+A28 -> -0.67731 | D28: =G28+$E$1*G27 -> 0.78078352 | E28: =E27+F28 -> 1.4742377 | F28: =_xlfn.NORM.INV(RAND(),0,1) -> -0.38692347 | G28: =_xlfn.NORM.INV(RAND(),0,1) -> 1.6667057 | H28: =$C$1*H27+G28+$E$1*G27 -> -1.4107532 | I28: Short memory: the MA effect vanishes completely after exactly q lags (finite impulse response). | J28: ='1.RETURNS'!D29*100 -> -0.55921391 | K28: =$K$1*J27 -> 0.22898216 | L28: =J28-K28 -> -0.78819607 | M28: =J28-$N$1*M27 -> -0.79220113 | N28: =$N$1*M27 -> 0.23298722 | O28: =J28-$K$1*J27-$N$1*O27 -> -1.0184216 | P28: =$K$1*J27+$N$1*O27 -> 0.45920773
A29: =_xlfn.NORM.INV(RAND(),0,1) -> -2.6232188 | B29: =ROW()-3 -> 26 | C29: =$C$1*C28+A29 -> -3.2666633 | D29: =G29+$E$1*G28 -> 1.2725625 | E29: =E28+F29 -> 2.5627955 | F29: =_xlfn.NORM.INV(RAND(),0,1) -> 1.0885577 | G29: =_xlfn.NORM.INV(RAND(),0,1) -> 0.10586846 | H29: =$C$1*H28+G29+$E$1*G28 -> -0.067653083 | I29: Always stationary: any value of θ works — no stability constraint required (unlike AR). | J29: ='1.RETURNS'!D30*100 -> 0.13854201 | K29: =$K$1*J28 -> 0.093907555 | L29: =J29-K29 -> 0.044634457 | M29: =J29-$N$1*M28 -> 0.0015301588 | N29: =$N$1*M28 -> 0.13701185 | O29: =J29-$K$1*J28-$N$1*O28 -> -0.13150242 | P29: =$K$1*J28+$N$1*O28 -> 0.27004444
A30: =_xlfn.NORM.INV(RAND(),0,1) -> 0.13872704 | B30: =ROW()-3 -> 27 | C30: =$C$1*C29+A30 -> -2.9646031 | D30: =G30+$E$1*G29 -> 0.018942366 | E30: =E29+F30 -> 2.8278337 | F30: =_xlfn.NORM.INV(RAND(),0,1) -> 0.26503828 | G30: =_xlfn.NORM.INV(RAND(),0,1) -> -0.055165559 | H30: =$C$1*H29+G30+$E$1*G29 -> -0.045328062 | I30: Long-run variance: Var[y(t)] = σ²_ε · (1 + θ²) | J30: ='1.RETURNS'!D31*100 -> -1.1016358 | K30: =$K$1*J29 -> -0.023265053 | L30: =J30-K30 -> -1.0783707 | M30: =J30-$N$1*M29 -> -1.1013711 | N30: =$N$1*M29 -> -0.00026464225 | O30: =J30-$K$1*J29-$N$1*O29 -> -1.1011142 | P30: =$K$1*J29+$N$1*O29 -> -0.00052159844
A31: =_xlfn.NORM.INV(RAND(),0,1) -> -0.7999257 | B31: =ROW()-3 -> 28 | C31: =$C$1*C30+A31 -> -3.6162986 | D31: =G31+$E$1*G30 -> -0.26344613 | E31: =E30+F31 -> 1.4010741 | F31: =_xlfn.NORM.INV(RAND(),0,1) -> -1.4267597 | G31: =_xlfn.NORM.INV(RAND(),0,1) -> -0.22483023 | H31: =$C$1*H30+G31+$E$1*G30 -> -0.30650779 | I31: ▌ PART C — I(d): INTEGRATION & DIFFERENCING [Columns E & F] | J31: ='1.RETURNS'!D32*100 -> 0.43343887 | K31: =$K$1*J30 -> 0.18499526 | L31: =J31-K31 -> 0.24844361 | M31: =J31-$N$1*M30 -> 0.2429558 | N31: =$N$1*M30 -> 0.19048307 | O31: =J31-$K$1*J30-$N$1*O30 -> 0.058004981 | P31: =$K$1*J30+$N$1*O30 -> 0.37543388
A32: =_xlfn.NORM.INV(RAND(),0,1) -> -0.0067286969 | B32: =ROW()-3 -> 29 | C32: =$C$1*C31+A32 -> -3.4422124 | D32: =G32+$E$1*G31 -> -1.0342662 | E32: =E31+F32 -> 0.56482578 | F32: =_xlfn.NORM.INV(RAND(),0,1) -> -0.83624829 | G32: =_xlfn.NORM.INV(RAND(),0,1) -> -0.87688507 | H32: =$C$1*H31+G32+$E$1*G31 -> -1.3254486 | I32: I(d): a series must be differenced d times to become stationary. Each difference removes one unit root. | J32: ='1.RETURNS'!D33*100 -> -0.59637653 | K32: =$K$1*J31 -> -0.07278643 | L32: =J32-K32 -> -0.52359011 | M32: =J32-$N$1*M31 -> -0.55435712 | N32: =$N$1*M31 -> -0.04201941 | O32: =J32-$K$1*J31-$N$1*O31 -> -0.51355809 | P32: =$K$1*J31+$N$1*O31 -> -0.08281844
... A46: =_xlfn.NORM.INV(RAND(),0,1) -> 0.25715839 | B46: =ROW()-3 -> 43 | C46: =$C$1*C45+A46 -> -2.375982 | D46: =G46+$E$1*G45 -> 0.43192214 | E46: =E45+F46 -> -3.286052 | F46: =_xlfn.NORM.INV(RAND(),0,1) -> 0.9450328 | G46: =_xlfn.NORM.INV(RAND(),0,1) -> 0.1110205 | H46: =$C$1*H45+G46+$E$1*G45 -> 2.7386932 | I46: Θ(L) = 1 + θ₁L + θ₂L² + ··· + θ_qL^q ← MA lag polynomial | J46: ='1.RETURNS'!D47*100 -> -0.084768128 | K46: =$K$1*J45 -> -0.035509545 | L46: =J46-K46 -> -0.049258583 | M46: =J46-$N$1*M45 -> -0.025999107 | N46: =$N$1*M45 -> -0.058769021 | O46: =J46-$K$1*J45-$N$1*O45 -> 0.031063071 | P46: =$K$1*J45+$N$1*O45 -> -0.1158312
A47: =_xlfn.NORM.INV(RAND(),0,1) -> -0.85133388 | B47: =ROW()-3 -> 44 | C47: =$C$1*C46+A47 -> -3.1085167 | D47: =G47+$E$1*G46 -> 0.73285886 | E47: =E46+F47 -> -4.2879492 | F47: =_xlfn.NORM.INV(RAND(),0,1) -> -1.0018972 | G47: =_xlfn.NORM.INV(RAND(),0,1) -> 0.65514451 | H47: =$C$1*H46+G47+$E$1*G46 -> 3.3346174 | J47: ='1.RETURNS'!D48*100 -> -0.27581407 | K47: =$K$1*J46 -> 0.014234924 | L47: =J47-K47 -> -0.290049 | M47: =J47-$N$1*M46 -> -0.28031064 | N47: =$N$1*M46 -> 0.0044965675 | O47: =J47-$K$1*J46-$N$1*O46 -> -0.28467661 | P47: =$K$1*J46+$N$1*O46 -> 0.00886254
A48: =_xlfn.NORM.INV(RAND(),0,1) -> -0.24273476 | B48: =ROW()-3 -> 45 | C48: =$C$1*C47+A48 -> -3.1958257 | D48: =G48+$E$1*G47 -> -0.14374406 | E48: =E47+F48 -> -4.1065957 | F48: =_xlfn.NORM.INV(RAND(),0,1) -> 0.18135346 | G48: =_xlfn.NORM.INV(RAND(),0,1) -> -0.60234522 | H48: =$C$1*H47+G48+$E$1*G47 -> 3.0241425 | I48: ▌ THE HONEST PUNCHLINE FOR FINANCE | J48: ='1.RETURNS'!D49*100 -> -1.4851304 | K48: =$K$1*J47 -> 0.046316847 | L48: =J48-K48 -> -1.5314473 | M48: =J48-$N$1*M47 -> -1.5336104 | N48: =$N$1*M47 -> 0.048479961 | O48: =J48-$K$1*J47-$N$1*O47 -> -1.5806823 | P48: =$K$1*J47+$N$1*O47 -> 0.095551906
A49: =_xlfn.NORM.INV(RAND(),0,1) -> 0.55654363 | B49: =ROW()-3 -> 46 | C49: =$C$1*C48+A49 -> -2.4794908 | D49: =G49+$E$1*G48 -> 0.66354337 | E49: =E48+F49 -> -3.3953701 | F49: =_xlfn.NORM.INV(RAND(),0,1) -> 0.71122564 | G49: =_xlfn.NORM.INV(RAND(),0,1) -> 1.085185 | H49: =$C$1*H48+G49+$E$1*G48 -> 3.5364787 | I49: Daily returns show small but statistically detectable autocorrelation in the mean (φ̂ = −0.168; R² ≈ 3%). | J49: ='1.RETURNS'!D50*100 -> -0.76831274 | K49: =$K$1*J48 -> 0.24939466 | L49: =J49-K49 -> -1.0177074 | M49: =J49-$N$1*M48 -> -1.0335519 | N49: =$N$1*M48 -> 0.26523921 | O49: =J49-$K$1*J48-$N$1*O48 -> -1.2910877 | P49: =$K$1*J48+$N$1*O48 -> 0.522775
A50: =_xlfn.NORM.INV(RAND(),0,1) -> -0.79905462 | B50: =ROW()-3 -> 47 | C50: =$C$1*C49+A50 -> -3.1545708 | D50: =G50+$E$1*G49 -> 0.43988467 | E50: =E49+F50 -> -3.4236921 | F50: =_xlfn.NORM.INV(RAND(),0,1) -> -0.028322039 | G50: =_xlfn.NORM.INV(RAND(),0,1) -> -0.31974485 | H50: =$C$1*H49+G50+$E$1*G49 -> 3.7995394 | I50: A fitted ARIMA finds small φ and θ — statistically nonzero, but the signal is swamped by noise in practice. | J50: ='1.RETURNS'!D51*100 -> -0.43656826 | K50: =$K$1*J49 -> 0.12902106 | L50: =J50-K50 -> -0.56558932 | M50: =J50-$N$1*M49 -> -0.61532194 | N50: =$N$1*M49 -> 0.17875368 | O50: =J50-$K$1*J49-$N$1*O49 -> -0.78888403 | P50: =$K$1*J49+$N$1*O49 -> 0.35231577
A51: =_xlfn.NORM.INV(RAND(),0,1) -> -0.20736457 | B51: =ROW()-3 -> 48 | C51: =$C$1*C50+A51 -> -3.2042069 | D51: =G51+$E$1*G50 -> 0.41764174 | E51: =E50+F51 -> -4.2920115 | F51: =_xlfn.NORM.INV(RAND(),0,1) -> -0.86831938 | G51: =_xlfn.NORM.INV(RAND(),0,1) -> 0.64146313 | H51: =$C$1*H50+G51+$E$1*G50 -> 4.0272042 | I51: The mean of daily returns is nearly unpredictable (consistent with efficient market logic, despite the small measured autocorrelation). | J51: ='1.RETURNS'!D52*100 -> 1.0511056 | K51: =$K$1*J50 -> 0.073311942 | L51: =J51-K51 -> 0.97779363 | M51: =J51-$N$1*M50 -> 0.94468512 | N51: =$N$1*M50 -> 0.10642045 | O51: =J51-$K$1*J50-$N$1*O50 -> 0.84135547 | P51: =$K$1*J50+$N$1*O50 -> 0.2097501
A52: =_xlfn.NORM.INV(RAND(),0,1) -> 0.052470131 | B52: =ROW()-3 -> 49 | C52: =$C$1*C51+A52 -> -2.9915264 | D52: =G52+$E$1*G51 -> 0.2108955 | E52: =E51+F52 -> -3.7902514 | F52: =_xlfn.NORM.INV(RAND(),0,1) -> 0.50176016 | G52: =_xlfn.NORM.INV(RAND(),0,1) -> -0.23812869 | H52: =$C$1*H51+G52+$E$1*G51 -> 4.0367395 | I52: Financial data's real persistence lives in the VARIANCE of returns, not in the mean. | J52: ='1.RETURNS'!D53*100 -> 0.38205554 | K52: =$K$1*J51 -> -0.17650983 | L52: =J52-K52 -> 0.55856537 | M52: =J52-$N$1*M51 -> 0.54543963 | N52: =$N$1*M51 -> -0.16338409 | O52: =J52-$K$1*J51-$N$1*O51 -> 0.70407851 | P52: =$K$1*J51+$N$1*O51 -> -0.32202297
A53: =_xlfn.NORM.INV(RAND(),0,1) -> -0.31854598 | B53: =ROW()-3 -> 50 | C53: =$C$1*C52+A53 -> -3.1604961 | D53: =G53+$E$1*G52 -> 0.10243309 | E53: =E52+F53 -> -2.6869445 | F53: =_xlfn.NORM.INV(RAND(),0,1) -> 1.1033068 | G53: =_xlfn.NORM.INV(RAND(),0,1) -> 0.26912317 | H53: =$C$1*H52+G53+$E$1*G52 -> 3.9373356 | I53: → GARCH (Section 6) takes over for variance. Columns J–L prove it: φ̂ = −0.17 on this simulated series — AR(1) explains only ~3% of return variance. | J53: ='1.RETURNS'!D54*100 -> -1.6681933 | K53: =$K$1*J52 -> -0.064157742 | L53: =J53-K53 -> -1.6040356 | M53: =J53-$N$1*M52 -> -1.5738591 | N53: =$N$1*M52 -> -0.094334243 | O53: =J53-$K$1*J52-$N$1*O52 -> -1.4822646 | P53: =$K$1*J52+$N$1*O52 -> -0.18592871
A54: =_xlfn.NORM.INV(RAND(),0,1) -> -1.0549328 | B54: =ROW()-3 -> 51 | C54: =$C$1*C53+A54 -> -4.057404 | D54: =G54+$E$1*G53 -> 1.0003089 | E54: =E53+F54 -> -4.4926598 | F54: =_xlfn.NORM.INV(RAND(),0,1) -> -1.8057152 | G54: =_xlfn.NORM.INV(RAND(),0,1) -> 0.81192272 | H54: =$C$1*H53+G54+$E$1*G53 -> 4.7407778 | I54: ▌ FINDINGS: AR, MA & ARIMA APPLIED TO SIMULATED SERIES (COLS J–P) | J54: ='1.RETURNS'!D55*100 -> 0.40394349 | K54: =$K$1*J53 -> 0.28013601 | L54: =J54-K54 -> 0.12380747 | M54: =J54-$N$1*M53 -> 0.13174323 | N54: =$N$1*M53 -> 0.27220025 | O54: =J54-$K$1*J53-$N$1*O53 -> -0.13255144 | P54: =$K$1*J53+$N$1*O53 -> 0.53649492
A55: =_xlfn.NORM.INV(RAND(),0,1) -> -0.071435869 | B55: =ROW()-3 -> 52 | C55: =$C$1*C54+A55 -> -3.9259697 | D55: =G55+$E$1*G54 -> 0.54822733 | E55: =E54+F55 -> -4.3077778 | F55: =_xlfn.NORM.INV(RAND(),0,1) -> 0.18488194 | G55: =_xlfn.NORM.INV(RAND(),0,1) -> -0.020118577 | H55: =$C$1*H54+G55+$E$1*G54 -> 5.0519662 | I55: Parameters estimated from all 251 simulated daily log-returns (illustrative 2023-calendar series): | J55: ='1.RETURNS'!D56*100 -> -0.34328482 | K55: =$K$1*J54 -> -0.067833336 | L55: =J55-K55 -> -0.27545148 | M55: =J55-$N$1*M54 -> -0.32049972 | N55: =$N$1*M54 -> -0.022785103 | O55: =J55-$K$1*J54-$N$1*O54 -> -0.29837637 | P55: =$K$1*J54+$N$1*O54 -> -0.044908453
A56: =_xlfn.NORM.INV(RAND(),0,1) -> 0.24728829 | B56: =ROW()-3 -> 53 | C56: =$C$1*C55+A56 -> -3.4823829 | D56: =G56+$E$1*G55 -> 1.2541992 | E56: =E55+F56 -> -4.0347973 | F56: =_xlfn.NORM.INV(RAND(),0,1) -> 0.27298056 | G56: =_xlfn.NORM.INV(RAND(),0,1) -> 1.2682822 | H56: =$C$1*H55+G56+$E$1*G55 -> 6.0535671 | I56: AR(1): φ̂ = −0.168 [Col K1] MA(1): θ̂ = −0.173 [Col N1] | J56: ='1.RETURNS'!D57*100 -> -0.63454124 | K56: =$K$1*J55 -> 0.05764706 | L56: =J56-K56 -> -0.6921883 | M56: =J56-$N$1*M55 -> -0.68997193 | N56: =$N$1*M55 -> 0.055430696 | O56: =J56-$K$1*J55-$N$1*O55 -> -0.74379274 | P56: =$K$1*J55+$N$1*O55 -> 0.1092515
A57: =_xlfn.NORM.INV(RAND(),0,1) -> -1.2354254 | B57: =ROW()-3 -> 54 | C57: =$C$1*C56+A57 -> -4.5436891 | D57: =G57+$E$1*G56 -> 1.9592811 | E57: =E56+F57 -> -3.8755826 | F57: =_xlfn.NORM.INV(RAND(),0,1) -> 0.15921469 | G57: =_xlfn.NORM.INV(RAND(),0,1) -> 1.0714835 | H57: =$C$1*H56+G57+$E$1*G56 -> 7.7101699 | I57: Both negative → in this series, an up-day slightly predicted the next day's return to be down (mild mean-reversion). | J57: ='1.RETURNS'!D58*100 -> 0.6744671 | K57: =$K$1*J56 -> 0.10655711 | L57: =J57-K57 -> 0.56791 | M57: =J57-$N$1*M56 -> 0.55513588 | N57: =$N$1*M56 -> 0.11933123 | O57: =J57-$K$1*J56-$N$1*O56 -> 0.43927042 | P57: =$K$1*J56+$N$1*O56 -> 0.23519669
A58: =_xlfn.NORM.INV(RAND(),0,1) -> 0.21783851 | B58: =ROW()-3 -> 55 | C58: =$C$1*C57+A58 -> -4.0986662 | D58: =G58+$E$1*G57 -> 1.2403252 | E58: =E57+F58 -> -3.716375 | F58: =_xlfn.NORM.INV(RAND(),0,1) -> 0.15920755 | G58: =_xlfn.NORM.INV(RAND(),0,1) -> 0.49028672 | H58: =$C$1*H57+G58+$E$1*G57 -> 8.5649865 | I58: If r(t−1) = +1.0%: AR predicts −0.17%, MA predicts −0.10% (1st step only), ARIMA predicts −0.27%. | J58: ='1.RETURNS'!D59*100 -> 1.0476356 | K58: =$K$1*J57 -> -0.11326177 | L58: =J58-K58 -> 1.1608974 | M58: =J58-$N$1*M57 -> 1.1436468 | N58: =$N$1*M57 -> -0.096011217 | O58: =J58-$K$1*J57-$N$1*O57 -> 1.2368696 | P58: =$K$1*J57+$N$1*O57 -> -0.18923396
A59: =_xlfn.NORM.INV(RAND(),0,1) -> -0.15166392 | B59: =ROW()-3 -> 56 | C59: =$C$1*C58+A59 -> -4.0453968 | D59: =G59+$E$1*G58 -> -0.68786737 | E59: =E58+F59 -> -4.1423827 | F59: =_xlfn.NORM.INV(RAND(),0,1) -> -0.42600763 | G59: =_xlfn.NORM.INV(RAND(),0,1) -> -1.0310681 | H59: =$C$1*H58+G59+$E$1*G58 -> 7.4488699 | I59: But daily volatility is ≈0.8% — the forecast signal is swamped by noise in every single period. | J59: ='1.RETURNS'!D60*100 -> 1.0563192 | K59: =$K$1*J58 -> -0.17592713 | L59: =J59-K59 -> 1.2322464 | M59: =J59-$N$1*M58 -> 1.2541139 | N59: =$N$1*M58 -> -0.19779469 | O59: =J59-$K$1*J58-$N$1*O58 -> 1.446164 | P59: =$K$1*J58+$N$1*O58 -> -0.38984477
... A63: =_xlfn.NORM.INV(RAND(),0,1) -> 2.3366526 | B63: =ROW()-3 -> 60 | C63: =$C$1*C62+A63 -> -0.34447617 | D63: =G63+$E$1*G62 -> 0.54427726 | E63: =E62+F63 -> -6.2583561 | F63: =_xlfn.NORM.INV(RAND(),0,1) -> 0.35912868 | G63: =_xlfn.NORM.INV(RAND(),0,1) -> 0.33898072 | H63: =$C$1*H62+G63+$E$1*G62 -> 8.434218 | I63: → Mean of returns: unpredictable by design (ARIMA gives up). Variance: highly persistent (GARCH takes over). | J63: ='1.RETURNS'!D64*100 -> 1.0092627 | K63: =$K$1*J62 -> -0.060387495 | L63: =J63-K63 -> 1.0696502 | M63: =J63-$N$1*M62 -> 1.0594611 | N63: =$N$1*M62 -> -0.050198456 | O63: =J63-$K$1*J62-$N$1*O62 -> 1.1082017 | P63: =$K$1*J62+$N$1*O62 -> -0.098938986

Sheet 6.GARCH MOTIVATION
G1: GARCH(1,1) Parameters — change to experiment: | H1: ω = | I1: 3e-06 | J1: α = | K1: 0.1 | L1: β = | M1: 0.85 | N1: VaR / ES Parameters: | O1: Conf₁ = | P1: 0.95 | Q1: Conf₂ = | R1: 0.99 | U1: ▌ BACKTEST RESULTS — KUPIEC PROPORTION OF FAILURES TEST
B2: SECTION 6 — GARCH MOTIVATION: VOLATILITY IS NOT CONSTANT | I2: PARAMETERS | N2: ▌ VALUE AT RISK & EXPECTED SHORTFALL [Normal-GARCH]
B3: Date | C3: Log-Return (%) | D3: Rolling 20d StdDev (%) | E3: Annualized Vol (%) | F3: Crisis Period? | G3: ε²(t) Squared Return | I3: σ²(t) GARCH Variance | J3: GARCH Daily σ (%) | K3: GARCH Ann. Vol (%) | N3: VaR 95% (Daily %) | O3: VaR 99% (Daily %) | P3: ES 95% (Daily %) | Q3: ES 99% (Daily %) | R3: Breach 95% | S3: Breach 99% | U3: METRIC | V3: 95% VaR | W3: 99% VaR | Z3: −VaR 95% | AA3: −VaR 99%
B4: ='1.RETURNS'!A5 -> 03-Jan-2023 | C4: ='1.RETURNS'!D5 -> 0.0058848723 | D4: — | E4: — | F4: =IF(E4="—","",IF(E4>=0.25,"■ HIGH VOLATILITY",IF(E4>=0.17,"▲ ELEVATED",""))) | G4: =C4^2 -> 3.4631723e-05 | H4: ▌ THE GOAL — CAN WE PREDICT TOMORROW’S VARIANCE? | I4: =$I$1/(1-$K$1-$M$1) -> 6e-05 | J4: =SQRT(I4)*100 -> 0.77459667 | K4: =J4*SQRT(252) -> 12.296341 | L4: =K4/100 -> 0.12296341 | N4: =-_xlfn.NORM.S.INV(1-$P$1)*J4 -> 1.2740981 | O4: =-_xlfn.NORM.S.INV(1-$R$1)*J4 -> 1.8019813 | P4: =_xlfn.NORM.S.DIST(_xlfn.NORM.S.INV(1-$P$1),FALSE)/(1-$P$1)*J4 -> 1.5977705 | Q4: =_xlfn.NORM.S.DIST(_xlfn.NORM.S.INV(1-$R$1),FALSE)/(1-$R$1)*J4 -> 2.0644661 | R4: =IF(C4*100<-N4,1,0) -> 0 | S4: =IF(C4*100<-O4,1,0) -> 0 | T4: ▌ WHAT IS GARCH-VaR? | U4: Total Observations (T) | V4: =COUNTA(C4:C253) -> 250 | W4: =V4 -> 250 | Z4: =-N4 -> -1.2740981 | AA4: =-O4 -> -1.8019813
B5: ='1.RETURNS'!A6 -> 04-Jan-2023 | C5: ='1.RETURNS'!D6 -> -0.0012113658 | D5: — | E5: — | F5: =IF(E5="—","",IF(E5>=0.25,"■ HIGH VOLATILITY",IF(E5>=0.17,"▲ ELEVATED",""))) | G5: =C5^2 -> 1.467407e-06 | H5: ARIMA asked: can we predict tomorrow’s MEAN return? Answer: NO (R² ≈ 3% — see Sheet 5). | I5: =$I$1+$K$1*G4+$M$1*I4 -> 5.7463172e-05 | J5: =SQRT(I5)*100 -> 0.75804467 | K5: =J5*SQRT(252) -> 12.033586 | L5: =K5/100 -> 0.12033586 | N5: =-_xlfn.NORM.S.INV(1-$P$1)*J5 -> 1.2468725 | O5: =-_xlfn.NORM.S.INV(1-$R$1)*J5 -> 1.7634756 | P5: =_xlfn.NORM.S.DIST(_xlfn.NORM.S.INV(1-$P$1),FALSE)/(1-$P$1)*J5 -> 1.5636285 | Q5: =_xlfn.NORM.S.DIST(_xlfn.NORM.S.INV(1-$R$1),FALSE)/(1-$R$1)*J5 -> 2.0203514 | R5: =IF(C5*100<-N5,1,0) -> 0 | S5: =IF(C5*100<-O5,1,0) -> 0 | T5: VaR(95%): on any given day, there is a 5% chance the loss | U5: Expected Breach Rate (p) | V5: =1-$P$1 -> 0.05 | W5: =1-$R$1 -> 0.01 | Z5: =-N5 -> -1.2468725 | AA5: =-O5 -> -1.7634756
B6: ='1.RETURNS'!A7 -> 05-Jan-2023 | C6: ='1.RETURNS'!D7 -> 0.0066707917 | D6: — | E6: — | F6: =IF(E6="—","",IF(E6>=0.25,"■ HIGH VOLATILITY",IF(E6>=0.17,"▲ ELEVATED",""))) | G6: =C6^2 -> 4.4499462e-05 | H6: GARCH asks: can we predict tomorrow’s VARIANCE? Answer: YES. | I6: =$I$1+$K$1*G5+$M$1*I5 -> 5.1990437e-05 | J6: =SQRT(I6)*100 -> 0.72104395 | K6: =J6*SQRT(252) -> 11.446218 | L6: =K6/100 -> 0.11446218 | N6: =-_xlfn.NORM.S.INV(1-$P$1)*J6 -> 1.1860117 | O6: =-_xlfn.NORM.S.INV(1-$R$1)*J6 -> 1.677399 | P6: =_xlfn.NORM.S.DIST(_xlfn.NORM.S.INV(1-$P$1),FALSE)/(1-$P$1)*J6 -> 1.4873066 | Q6: =_xlfn.NORM.S.DIST(_xlfn.NORM.S.INV(1-$R$1),FALSE)/(1-$R$1)*J6 -> 1.9217366 | R6: =IF(C6*100<-N6,1,0) -> 0 | S6: =IF(C6*100<-O6,1,0) -> 0 | T6: will exceed this value. Col N = 1.645 × σ_GARCH. | U6: Expected Breaches (T × p) | V6: =V4*V5 -> 12.5 | W6: =W4*W5 -> 2.5 | Z6: =-N6 -> -1.1860117 | AA6: =-O6 -> -1.677399
B7: ='1.RETURNS'!A8 -> 06-Jan-2023 | C7: ='1.RETURNS'!D8 -> 0.016065487 | D7: — | E7: — | F7: =IF(E7="—","",IF(E7>=0.25,"■ HIGH VOLATILITY",IF(E7>=0.17,"▲ ELEVATED",""))) | G7: =C7^2 -> 0.00025809986 | H7: This is what makes GARCH one of the most-used models in quantitative finance. | I7: =$I$1+$K$1*G6+$M$1*I6 -> 5.1641818e-05 | J7: =SQRT(I7)*100 -> 0.71862242 | K7: =J7*SQRT(252) -> 11.407777 | L7: =K7/100 -> 0.11407777 | N7: =-_xlfn.NORM.S.INV(1-$P$1)*J7 -> 1.1820287 | O7: =-_xlfn.NORM.S.INV(1-$R$1)*J7 -> 1.6717657 | P7: =_xlfn.NORM.S.DIST(_xlfn.NORM.S.INV(1-$P$1),FALSE)/(1-$P$1)*J7 -> 1.4823117 | Q7: =_xlfn.NORM.S.DIST(_xlfn.NORM.S.INV(1-$R$1),FALSE)/(1-$R$1)*J7 -> 1.9152827 | R7: =IF(C7*100<-N7,1,0) -> 0 | S7: =IF(C7*100<-O7,1,0) -> 0 | U7: Actual Breaches (k) | V7: =COUNTIF(R4:R253,1) -> 18 | W7: =COUNTIF(S4:S253,1) -> 5 | Z7: =-N7 -> -1.1820287 | AA7: =-O7 -> -1.6717657
B8: ='1.RETURNS'!A9 -> 09-Jan-2023 | C8: ='1.RETURNS'!D9 -> -0.0024548761 | D8: — | E8: — | F8: =IF(E8="—","",IF(E8>=0.25,"■ HIGH VOLATILITY",IF(E8>=0.17,"▲ ELEVATED",""))) | G8: =C8^2 -> 6.0264168e-06 | I8: =$I$1+$K$1*G7+$M$1*I7 -> 7.2705531e-05 | J8: =SQRT(I8)*100 -> 0.85267538 | K8: =J8*SQRT(252) -> 13.535802 | L8: =K8/100 -> 0.13535802 | N8: =-_xlfn.NORM.S.INV(1-$P$1)*J8 -> 1.4025262 | O8: =-_xlfn.NORM.S.INV(1-$R$1)*J8 -> 1.9836196 | P8: =_xlfn.NORM.S.DIST(_xlfn.NORM.S.INV(1-$P$1),FALSE)/(1-$P$1)*J8 -> 1.7588244 | Q8: =_xlfn.NORM.S.DIST(_xlfn.NORM.S.INV(1-$R$1),FALSE)/(1-$R$1)*J8 -> 2.2725626 | R8: =IF(C8*100<-N8,1,0) -> 0 | S8: =IF(C8*100<-O8,1,0) -> 0 | T8: VaR(99%): stricter threshold — 1% exceedance probability. | U8: Observed Breach Rate (p̂ = k/T) | V8: =V7/V4 -> 0.072 | W8: =W7/W4 -> 0.02 | Z8: =-N8 -> -1.4025262 | AA8: =-O8 -> -1.9836196
B9: ='1.RETURNS'!A10 -> 10-Jan-2023 | C9: ='1.RETURNS'!D10 -> -0.0020112502 | D9: — | E9: — | F9: =IF(E9="—","",IF(E9>=0.25,"■ HIGH VOLATILITY",IF(E9>=0.17,"▲ ELEVATED",""))) | G9: =C9^2 -> 4.0451275e-06 | H9: ▌ THE EVIDENCE — VOLATILITY IS NOT CONSTANT [Col E, rolling vol] | I9: =$I$1+$K$1*G8+$M$1*I8 -> 6.5402343e-05 | J9: =SQRT(I9)*100 -> 0.80871715 | K9: =J9*SQRT(252) -> 12.837987 | L9: =K9/100 -> 0.12837987 | N9: =-_xlfn.NORM.S.INV(1-$P$1)*J9 -> 1.3302213 | O9: =-_xlfn.NORM.S.INV(1-$R$1)*J9 -> 1.8813574 | P9: =_xlfn.NORM.S.DIST(_xlfn.NORM.S.INV(1-$P$1),FALSE)/(1-$P$1)*J9 -> 1.6681512 | Q9: =_xlfn.NORM.S.DIST(_xlfn.NORM.S.INV(1-$R$1),FALSE)/(1-$R$1)*J9 -> 2.1554045 | R9: =IF(C9*100<-N9,1,0) -> 0 | S9: =IF(C9*100<-O9,1,0) -> 0 | T9: Col O = 2.326 × σ_GARCH. | U9: Kupiec LR Statistic | V9: =IFERROR(2*(V7*LN(V8/V5)+(V4-V7)*LN((1-V8)/(1-V5))),"N/A") -> 2.2555153 | W9: =IFERROR(2*(W7*LN(W8/W5)+(W4-W7)*LN((1-W8)/(1-W5))),"N/A") -> 1.9568098 | Z9: =-N9 -> -1.3302213 | AA9: =-O9 -> -1.8813574
B10: ='1.RETURNS'!A11 -> 11-Jan-2023 | C10: ='1.RETURNS'!D11 -> 0.015334303 | D10: — | E10: — | F10: =IF(E10="—","",IF(E10>=0.25,"■ HIGH VOLATILITY",IF(E10>=0.17,"▲ ELEVATED",""))) | G10: =C10^2 -> 0.00023514084 | H10: Column E (rolling 20-day vol) ranges from ~10% to ~31% in this simulated series — a 3× swing. | I10: =$I$1+$K$1*G9+$M$1*I9 -> 5.8996504e-05 | J10: =SQRT(I10)*100 -> 0.76809182 | K10: =J10*SQRT(252) -> 12.19308 | L10: =K10/100 -> 0.1219308 | N10: =-_xlfn.NORM.S.INV(1-$P$1)*J10 -> 1.2633986 | O10: =-_xlfn.NORM.S.INV(1-$R$1)*J10 -> 1.7868488 | P10: =_xlfn.NORM.S.DIST(_xlfn.NORM.S.INV(1-$P$1),FALSE)/(1-$P$1)*J10 -> 1.5843528 | Q10: =_xlfn.NORM.S.DIST(_xlfn.NORM.S.INV(1-$R$1),FALSE)/(1-$R$1)*J10 -> 2.0471292 | R10: =IF(C10*100<-N10,1,0) -> 0 | S10: =IF(C10*100<-O10,1,0) -> 0 | U10: Critical Value (χ²₁, α=5%) | V10: 3.841 | W10: 3.841 | Z10: =-N10 -> -1.2633986 | AA10: =-O10 -> -1.7868488
B11: ='1.RETURNS'!A12 -> 12-Jan-2023 | C11: ='1.RETURNS'!D12 -> 0.0088748844 | D11: — | E11: — | F11: =IF(E11="—","",IF(E11>=0.25,"■ HIGH VOLATILITY",IF(E11>=0.17,"▲ ELEVATED",""))) | G11: =C11^2 -> 7.8763574e-05 | H11: A model that assumes constant σ is badly wrong for most of the year. | I11: =$I$1+$K$1*G10+$M$1*I10 -> 7.6661112e-05 | J11: =SQRT(I11)*100 -> 0.87556332 | K11: =J11*SQRT(252) -> 13.899137 | L11: =K11/100 -> 0.13899137 | N11: =-_xlfn.NORM.S.INV(1-$P$1)*J11 -> 1.4401735 | O11: =-_xlfn.NORM.S.INV(1-$R$1)*J11 -> 2.0368649 | P11: =_xlfn.NORM.S.DIST(_xlfn.NORM.S.INV(1-$P$1),FALSE)/(1-$P$1)*J11 -> 1.8060357 | Q11: =_xlfn.NORM.S.DIST(_xlfn.NORM.S.INV(1-$R$1),FALSE)/(1-$R$1)*J11 -> 2.3335638 | R11: =IF(C11*100<-N11,1,0) -> 0 | S11: =IF(C11*100<-O11,1,0) -> 0 | T11: Both use GARCH σ [Col J] not fixed historical vol. | U11: Kupiec Test Result | V11: =IF(ISNUMBER(V9),IF(V9<=V10,"✓ PASS","✗ FAIL"),"N/A") -> ✓ PASS | W11: =IF(ISNUMBER(W9),IF(W9<=W10,"✓ PASS","✗ FAIL"),"N/A") -> ✓ PASS | Z11: =-N11 -> -1.4401735 | AA11: =-O11 -> -2.0368649
B12: ='1.RETURNS'!A13 -> 13-Jan-2023 | C12: ='1.RETURNS'!D13 -> -0.0048215906 | D12: — | E12: — | F12: =IF(E12="—","",IF(E12>=0.25,"■ HIGH VOLATILITY",IF(E12>=0.17,"▲ ELEVATED",""))) | G12: =C12^2 -> 2.3247736e-05 | H12: Calm periods (early and mid-series): rolling vol ≈ 10–13% ← safe regime | I12: =$I$1+$K$1*G11+$M$1*I11 -> 7.6038303e-05 | J12: =SQRT(I12)*100 -> 0.87199944 | K12: =J12*SQRT(252) -> 13.842562 | L12: =K12/100 -> 0.13842562 | N12: =-_xlfn.NORM.S.INV(1-$P$1)*J12 -> 1.4343114 | O12: =-_xlfn.NORM.S.INV(1-$R$1)*J12 -> 2.0285741 | P12: =_xlfn.NORM.S.DIST(_xlfn.NORM.S.INV(1-$P$1),FALSE)/(1-$P$1)*J12 -> 1.7986844 | Q12: =_xlfn.NORM.S.DIST(_xlfn.NORM.S.INV(1-$R$1),FALSE)/(1-$R$1)*J12 -> 2.3240653 | R12: =IF(C12*100<-N12,1,0) -> 0 | S12: =IF(C12*100<-O12,1,0) -> 0 | T12: This makes VaR time-varying — higher in turbulent regimes, | Z12: =-N12 -> -1.4343114 | AA12: =-O12 -> -2.0285741
B13: ='1.RETURNS'!A14 -> 16-Jan-2023 | C13: ='1.RETURNS'!D14 -> 0.0055124296 | D13: — | E13: — | F13: =IF(E13="—","",IF(E13>=0.25,"■ HIGH VOLATILITY",IF(E13>=0.17,"▲ ELEVATED",""))) | G13: =C13^2 -> 3.0386881e-05 | H13: Turbulent periods (▲/■ in Col F): rolling vol ≈ 20–31% ← crisis regime | I13: =$I$1+$K$1*G12+$M$1*I12 -> 6.9957331e-05 | J13: =SQRT(I13)*100 -> 0.83640499 | K13: =J13*SQRT(252) -> 13.277518 | L13: =K13/100 -> 0.13277518 | N13: =-_xlfn.NORM.S.INV(1-$P$1)*J13 -> 1.3757638 | O13: =-_xlfn.NORM.S.INV(1-$R$1)*J13 -> 1.945769 | P13: =_xlfn.NORM.S.DIST(_xlfn.NORM.S.INV(1-$P$1),FALSE)/(1-$P$1)*J13 -> 1.7252633 | Q13: =_xlfn.NORM.S.DIST(_xlfn.NORM.S.INV(1-$R$1),FALSE)/(1-$R$1)*J13 -> 2.2291985 | R13: =IF(C13*100<-N13,1,0) -> 0 | S13: =IF(C13*100<-O13,1,0) -> 0 | T13: lower in calm ones. The 3× vol swing in Col E produces | U13: ▌ VaR / ES STATISTICS — SIMULATED SERIES | Z13: =-N13 -> -1.3757638 | AA13: =-O13 -> -1.945769
B14: ='1.RETURNS'!A15 -> 17-Jan-2023 | C14: ='1.RETURNS'!D15 -> -0.0042904899 | D14: — | E14: — | F14: =IF(E14="—","",IF(E14>=0.25,"■ HIGH VOLATILITY",IF(E14>=0.17,"▲ ELEVATED",""))) | G14: =C14^2 -> 1.8408304e-05 | I14: =$I$1+$K$1*G13+$M$1*I13 -> 6.550242e-05 | J14: =SQRT(I14)*100 -> 0.80933565 | K14: =J14*SQRT(252) -> 12.847805 | L14: =K14/100 -> 0.12847805 | N14: =-_xlfn.NORM.S.INV(1-$P$1)*J14 -> 1.3312387 | O14: =-_xlfn.NORM.S.INV(1-$R$1)*J14 -> 1.8827963 | P14: =_xlfn.NORM.S.DIST(_xlfn.NORM.S.INV(1-$P$1),FALSE)/(1-$P$1)*J14 -> 1.669427 | Q14: =_xlfn.NORM.S.DIST(_xlfn.NORM.S.INV(1-$R$1),FALSE)/(1-$R$1)*J14 -> 2.1570529 | R14: =IF(C14*100<-N14,1,0) -> 0 | S14: =IF(C14*100<-O14,1,0) -> 0 | T14: a 3× swing in VaR estimates across the year. | U14: METRIC | V14: VaR 95% (%) | W14: VaR 99% (%) | X14: ES 95% (%) | Y14: ES 99% (%) | Z14: =-N14 -> -1.3312387 | AA14: =-O14 -> -1.8827963
B15: ='1.RETURNS'!A16 -> 18-Jan-2023 | C15: ='1.RETURNS'!D16 -> -0.0042128306 | D15: — | E15: — | F15: =IF(E15="—","",IF(E15>=0.25,"■ HIGH VOLATILITY",IF(E15>=0.17,"▲ ELEVATED",""))) | G15: =C15^2 -> 1.7747942e-05 | H15: ▌ VOLATILITY CLUSTERING — THE CORE INSIGHT [Col G = ε²(t)] | I15: =$I$1+$K$1*G14+$M$1*I14 -> 6.0517887e-05 | J15: =SQRT(I15)*100 -> 0.77793243 | K15: =J15*SQRT(252) -> 12.349295 | L15: =K15/100 -> 0.12349295 | N15: =-_xlfn.NORM.S.INV(1-$P$1)*J15 -> 1.279585 | O15: =-_xlfn.NORM.S.INV(1-$R$1)*J15 -> 1.8097415 | P15: =_xlfn.NORM.S.DIST(_xlfn.NORM.S.INV(1-$P$1),FALSE)/(1-$P$1)*J15 -> 1.6046512 | Q15: =_xlfn.NORM.S.DIST(_xlfn.NORM.S.INV(1-$R$1),FALSE)/(1-$R$1)*J15 -> 2.0733566 | R15: =IF(C15*100<-N15,1,0) -> 0 | S15: =IF(C15*100<-O15,1,0) -> 0 | U15: Average (Typical Day) | V15: =AVERAGE(N4:N253) -> 1.5960233 | W15: =AVERAGE(O4:O253) -> 2.2572862 | X15: =AVERAGE(P4:P253) -> 2.0014776 | Y15: =AVERAGE(Q4:Q253) -> 2.5860927 | Z15: =-N15 -> -1.279585 | AA15: =-O15 -> -1.8097415
B16: ='1.RETURNS'!A17 -> 19-Jan-2023 | C16: ='1.RETURNS'!D17 -> 0.0025967418 | D16: — | E16: — | F16: =IF(E16="—","",IF(E16>=0.25,"■ HIGH VOLATILITY",IF(E16>=0.17,"▲ ELEVATED",""))) | G16: =C16^2 -> 6.7430678e-06 | H16: Large returns tend to be followed by large returns (of either sign). | I16: =$I$1+$K$1*G15+$M$1*I15 -> 5.6214998e-05 | J16: =SQRT(I16)*100 -> 0.74976662 | K16: =J16*SQRT(252) -> 11.902176 | L16: =K16/100 -> 0.11902176 | N16: =-_xlfn.NORM.S.INV(1-$P$1)*J16 -> 1.2332563 | O16: =-_xlfn.NORM.S.INV(1-$R$1)*J16 -> 1.744218 | P16: =_xlfn.NORM.S.DIST(_xlfn.NORM.S.INV(1-$P$1),FALSE)/(1-$P$1)*J16 -> 1.5465532 | Q16: =_xlfn.NORM.S.DIST(_xlfn.NORM.S.INV(1-$R$1),FALSE)/(1-$R$1)*J16 -> 1.9982887 | R16: =IF(C16*100<-N16,1,0) -> 0 | S16: =IF(C16*100<-O16,1,0) -> 0 | T16: ▌ EXPECTED SHORTFALL (ES / CVaR) | U16: Minimum (Calmest Day) | V16: =MIN(N4:N253) -> 1.1159712 | W16: =MIN(O4:O253) -> 1.5783393 | X16: =MIN(P4:P253) -> 1.3994729 | Y16: =MIN(Q4:Q253) -> 1.8082474 | Z16: =-N16 -> -1.2332563 | AA16: =-O16 -> -1.744218
B17: ='1.RETURNS'!A18 -> 20-Jan-2023 | C17: ='1.RETURNS'!D18 -> -0.019171552 | D17: — | E17: — | F17: =IF(E17="—","",IF(E17>=0.25,"■ HIGH VOLATILITY",IF(E17>=0.17,"▲ ELEVATED",""))) | G17: =C17^2 -> 0.00036754841 | H17: Small returns tend to be followed by small returns. | I17: =$I$1+$K$1*G16+$M$1*I16 -> 5.1457055e-05 | J17: =SQRT(I17)*100 -> 0.71733573 | K17: =J17*SQRT(252) -> 11.387352 | L17: =K17/100 -> 0.11387352 | N17: =-_xlfn.NORM.S.INV(1-$P$1)*J17 -> 1.1799123 | O17: =-_xlfn.NORM.S.INV(1-$R$1)*J17 -> 1.6687725 | P17: =_xlfn.NORM.S.DIST(_xlfn.NORM.S.INV(1-$P$1),FALSE)/(1-$P$1)*J17 -> 1.4796576 | Q17: =_xlfn.NORM.S.DIST(_xlfn.NORM.S.INV(1-$R$1),FALSE)/(1-$R$1)*J17 -> 1.9118534 | R17: =IF(C17*100<-N17,1,0) -> 1 | S17: =IF(C17*100<-O17,1,0) -> 1 | T17: ES = E[loss | loss > VaR] — the AVERAGE loss on breach days. | U17: Maximum (Most Stressed Day) | V17: =MAX(N4:N253) -> 3.3870917 | W17: =MAX(O4:O253) -> 4.7904284 | X17: =MAX(P4:P253) -> 4.2475496 | Y17: =MAX(Q4:Q253) -> 5.4882238 | Z17: =-N17 -> -1.1799123 | AA17: =-O17 -> -1.6687725
B18: ='1.RETURNS'!A19 -> 23-Jan-2023 | C18: ='1.RETURNS'!D19 -> -0.020470412 | D18: — | E18: — | F18: =IF(E18="—","",IF(E18>=0.25,"■ HIGH VOLATILITY",IF(E18>=0.17,"▲ ELEVATED",""))) | G18: =C18^2 -> 0.00041903776 | H18: Autocorrelation of ε²(t) [Col G] >> 0 ← the autocorrelation ARIMA ignored. | I18: =$I$1+$K$1*G17+$M$1*I17 -> 8.3493338e-05 | J18: =SQRT(I18)*100 -> 0.91374689 | K18: =J18*SQRT(252) -> 14.505282 | L18: =K18/100 -> 0.14505282 | N18: =-_xlfn.NORM.S.INV(1-$P$1)*J18 -> 1.5029799 | O18: =-_xlfn.NORM.S.INV(1-$R$1)*J18 -> 2.1256931 | P18: =_xlfn.NORM.S.DIST(_xlfn.NORM.S.INV(1-$P$1),FALSE)/(1-$P$1)*J18 -> 1.8847974 | Q18: =_xlfn.NORM.S.DIST(_xlfn.NORM.S.INV(1-$R$1),FALSE)/(1-$R$1)*J18 -> 2.4353312 | R18: =IF(C18*100<-N18,1,0) -> 1 | S18: =IF(C18*100<-O18,1,0) -> 0 | T18: ES > VaR always. Under normality: | U18: Stress / Calm Ratio | V18: =V17/V16 -> 3.0351068 | W18: =W17/W16 -> 3.0351068 | X18: =X17/X16 -> 3.0351068 | Y18: =Y17/Y16 -> 3.0351068 | Z18: =-N18 -> -1.5029799 | AA18: =-O18 -> -2.1256931
B19: ='1.RETURNS'!A20 -> 24-Jan-2023 | C19: ='1.RETURNS'!D20 -> -0.0064772079 | D19: — | E19: — | F19: =IF(E19="—","",IF(E19>=0.25,"■ HIGH VOLATILITY",IF(E19>=0.17,"▲ ELEVATED",""))) | G19: =C19^2 -> 4.1954222e-05 | H19: Look at Column G: squared returns cluster. Spikes appear together; calm periods too. | I19: =$I$1+$K$1*G18+$M$1*I18 -> 0.00011587311 | J19: =SQRT(I19)*100 -> 1.0764437 | K19: =J19*SQRT(252) -> 17.088015 | L19: =K19/100 -> 0.17088015 | N19: =-_xlfn.NORM.S.INV(1-$P$1)*J19 -> 1.7705924 | O19: =-_xlfn.NORM.S.INV(1-$R$1)*J19 -> 2.5041826 | P19: =_xlfn.NORM.S.DIST(_xlfn.NORM.S.INV(1-$P$1),FALSE)/(1-$P$1)*J19 -> 2.2203943 | Q19: =_xlfn.NORM.S.DIST(_xlfn.NORM.S.INV(1-$R$1),FALSE)/(1-$R$1)*J19 -> 2.8689532 | R19: =IF(C19*100<-N19,1,0) -> 0 | S19: =IF(C19*100<-O19,1,0) -> 0 | T19: ES₉₅ ≈ 2.06 × σ (Col P) ES₉₉ ≈ 2.67 × σ (Col Q) | U19: Latest Estimate (Last Day) | V19: =N253 -> 1.5944666 | W19: =O253 -> 2.2550845 | X19: =P253 -> 1.9995254 | Y19: =Q253 -> 2.5835703 | Z19: =-N19 -> -1.7705924 | AA19: =-O19 -> -2.5041826
B20: ='1.RETURNS'!A21 -> 25-Jan-2023 | C20: ='1.RETURNS'!D21 -> -0.0097974154 | D20: — | E20: — | F20: =IF(E20="—","",IF(E20>=0.25,"■ HIGH VOLATILITY",IF(E20>=0.17,"▲ ELEVATED",""))) | G20: =C20^2 -> 9.5989349e-05 | H20: This clustering is the entire motivation for GARCH. | I20: =$I$1+$K$1*G19+$M$1*I19 -> 0.00010568757 | J20: =SQRT(I20)*100 -> 1.0280446 | K20: =J20*SQRT(252) -> 16.319702 | L20: =K20/100 -> 0.16319702 | N20: =-_xlfn.NORM.S.INV(1-$P$1)*J20 -> 1.6909829 | O20: =-_xlfn.NORM.S.INV(1-$R$1)*J20 -> 2.3915894 | P20: =_xlfn.NORM.S.DIST(_xlfn.NORM.S.INV(1-$P$1),FALSE)/(1-$P$1)*J20 -> 2.1205607 | Q20: =_xlfn.NORM.S.DIST(_xlfn.NORM.S.INV(1-$R$1),FALSE)/(1-$R$1)*J20 -> 2.7399591 | R20: =IF(C20*100<-N20,1,0) -> 0 | S20: =IF(C20*100<-O20,1,0) -> 0 | U20: Avg Actual Loss on Breach Days | V20: =IFERROR(-AVERAGEIF(R4:R253,1,C4:C253)*100,"N/A") -> 2.1976915 | W20: =IFERROR(-AVERAGEIF(S4:S253,1,C4:C253)*100,"N/A") -> 2.938114 | X20: ← compare vs ES estimate above | Z20: =-N20 -> -1.6909829 | AA20: =-O20 -> -2.3915894
B21: ='1.RETURNS'!A22 -> 26-Jan-2023 | C21: ='1.RETURNS'!D22 -> 0.0036193333 | D21: — | E21: — | F21: =IF(E21="—","",IF(E21>=0.25,"■ HIGH VOLATILITY",IF(E21>=0.17,"▲ ELEVATED",""))) | G21: =C21^2 -> 1.3099573e-05 | I21: =$I$1+$K$1*G20+$M$1*I20 -> 0.00010243337 | J21: =SQRT(I21)*100 -> 1.0120937 | K21: =J21*SQRT(252) -> 16.06649 | L21: =K21/100 -> 0.1606649 | N21: =-_xlfn.NORM.S.INV(1-$P$1)*J21 -> 1.664746 | O21: =-_xlfn.NORM.S.INV(1-$R$1)*J21 -> 2.3544821 | P21: =_xlfn.NORM.S.DIST(_xlfn.NORM.S.INV(1-$P$1),FALSE)/(1-$P$1)*J21 -> 2.0876587 | Q21: =_xlfn.NORM.S.DIST(_xlfn.NORM.S.INV(1-$R$1),FALSE)/(1-$R$1)*J21 -> 2.6974466 | R21: =IF(C21*100<-N21,1,0) -> 0 | S21: =IF(C21*100<-O21,1,0) -> 0 | T21: ES tells you HOW BAD losses get in the tail, not just when | Z21: =-N21 -> -1.664746 | AA21: =-O21 -> -2.3544821
B22: ='1.RETURNS'!A23 -> 27-Jan-2023 | C22: ='1.RETURNS'!D23 -> -0.0087524506 | D22: — | E22: — | F22: =IF(E22="—","",IF(E22>=0.25,"■ HIGH VOLATILITY",IF(E22>=0.17,"▲ ELEVATED",""))) | G22: =C22^2 -> 7.6605392e-05 | H22: ▌ THE GARCH(1,1) MODEL [Columns I, J, K] | I22: =$I$1+$K$1*G21+$M$1*I21 -> 9.137832e-05 | J22: =SQRT(I22)*100 -> 0.95592008 | K22: =J22*SQRT(252) -> 15.174761 | L22: =K22/100 -> 0.15174761 | N22: =-_xlfn.NORM.S.INV(1-$P$1)*J22 -> 1.5723486 | O22: =-_xlfn.NORM.S.INV(1-$R$1)*J22 -> 2.2238027 | P22: =_xlfn.NORM.S.DIST(_xlfn.NORM.S.INV(1-$P$1),FALSE)/(1-$P$1)*J22 -> 1.9717886 | Q22: =_xlfn.NORM.S.DIST(_xlfn.NORM.S.INV(1-$R$1),FALSE)/(1-$R$1)*J22 -> 2.5477318 | R22: =IF(C22*100<-N22,1,0) -> 0 | S22: =IF(C22*100<-O22,1,0) -> 0 | T22: the threshold is crossed. Required for Basel III VaR reporting. | U22: ▌ INTERPRETATION | Z22: =-N22 -> -1.5723486 | AA22: =-O22 -> -2.2238027
B23: ='1.RETURNS'!A24 -> 30-Jan-2023 | C23: ='1.RETURNS'!D24 -> -0.014251167 | D23: =STDEV(C4:C23) -> 0.010054802 | E23: =D23*SQRT(252) -> 0.15961503 | F23: =IF(E23="—","",IF(E23>=0.25,"■ HIGH VOLATILITY",IF(E23>=0.17,"▲ ELEVATED",""))) | G23: =C23^2 -> 0.00020309575 | H23: Today’s variance depends on yesterday’s squared return AND yesterday’s variance: | I23: =$I$1+$K$1*G22+$M$1*I22 -> 8.8332111e-05 | J23: =SQRT(I23)*100 -> 0.93985164 | K23: =J23*SQRT(252) -> 14.919682 | L23: =K23/100 -> 0.14919682 | N23: =-_xlfn.NORM.S.INV(1-$P$1)*J23 -> 1.5459184 | O23: =-_xlfn.NORM.S.INV(1-$R$1)*J23 -> 2.1864219 | P23: =_xlfn.NORM.S.DIST(_xlfn.NORM.S.INV(1-$P$1),FALSE)/(1-$P$1)*J23 -> 1.938644 | Q23: =_xlfn.NORM.S.DIST(_xlfn.NORM.S.INV(1-$R$1),FALSE)/(1-$R$1)*J23 -> 2.504906 | R23: =IF(C23*100<-N23,1,0) -> 0 | S23: =IF(C23*100<-O23,1,0) -> 0 | U23: 95% model: 18 breaches vs 12.5 expected — slightly more than normal-dist predicts. | Z23: =-N23 -> -1.5459184 | AA23: =-O23 -> -2.1864219
B24: ='1.RETURNS'!A25 -> 31-Jan-2023 | C24: ='1.RETURNS'!D25 -> 0.01663348 | D24: =STDEV(C5:C24) -> 0.010743437 | E24: =D24*SQRT(252) -> 0.17054678 | F24: =IF(E24="—","",IF(E24>=0.25,"■ HIGH VOLATILITY",IF(E24>=0.17,"▲ ELEVATED",""))) -> ▲ ELEVATED | G24: =C24^2 -> 0.00027667266 | H24: σ²(t) = ω + α×ε²(t−1) + β×σ²(t−1) | I24: =$I$1+$K$1*G23+$M$1*I23 -> 9.8391869e-05 | J24: =SQRT(I24)*100 -> 0.99192676 | K24: =J24*SQRT(252) -> 15.746349 | L24: =K24/100 -> 0.15746349 | N24: =-_xlfn.NORM.S.INV(1-$P$1)*J24 -> 1.6315743 | O24: =-_xlfn.NORM.S.INV(1-$R$1)*J24 -> 2.3075667 | P24: =_xlfn.NORM.S.DIST(_xlfn.NORM.S.INV(1-$P$1),FALSE)/(1-$P$1)*J24 -> 2.04606 | Q24: =_xlfn.NORM.S.DIST(_xlfn.NORM.S.INV(1-$R$1),FALSE)/(1-$R$1)*J24 -> 2.6436973 | R24: =IF(C24*100<-N24,1,0) -> 0 | S24: =IF(C24*100<-O24,1,0) -> 0 | T24: ▌ BREACH INDICATORS (Cols R & S) | U24: Cause: Equity returns have fat tails. Normal GARCH underestimates extreme moves. | Z24: =-N24 -> -1.6315743 | AA24: =-O24 -> -2.3075667
B25: ='1.RETURNS'!A26 -> 01-Feb-2023 | C25: ='1.RETURNS'!D26 -> -0.0023279526 | D25: =STDEV(C6:C25) -> 0.010746779 | E25: =D25*SQRT(252) -> 0.17059983 | F25: =IF(E25="—","",IF(E25>=0.25,"■ HIGH VOLATILITY",IF(E25>=0.17,"▲ ELEVATED",""))) -> ▲ ELEVATED | G25: =C25^2 -> 5.4193635e-06 | H25: ω = long-run variance floor [I1 = 0.000003] | I25: =$I$1+$K$1*G24+$M$1*I24 -> 0.00011430036 | J25: =SQRT(I25)*100 -> 1.0691134 | K25: =J25*SQRT(252) -> 16.97165 | L25: =K25/100 -> 0.1697165 | N25: =-_xlfn.NORM.S.INV(1-$P$1)*J25 -> 1.7585351 | O25: =-_xlfn.NORM.S.INV(1-$R$1)*J25 -> 2.4871298 | P25: =_xlfn.NORM.S.DIST(_xlfn.NORM.S.INV(1-$P$1),FALSE)/(1-$P$1)*J25 -> 2.205274 | Q25: =_xlfn.NORM.S.DIST(_xlfn.NORM.S.INV(1-$R$1),FALSE)/(1-$R$1)*J25 -> 2.8494163 | R25: =IF(C25*100<-N25,1,0) -> 0 | S25: =IF(C25*100<-O25,1,0) -> 0 | T25: 1 = actual return < −VaR (i.e., loss exceeded the forecast). | U25: Both models PASS Kupiec — difference is not statistically significant at 5%. | Z25: =-N25 -> -1.7585351 | AA25: =-O25 -> -2.4871298
B26: ='1.RETURNS'!A27 -> 02-Feb-2023 | C26: ='1.RETURNS'!D27 -> 0.00093726236 | D26: =STDEV(C7:C26) -> 0.01060164 | E26: =D26*SQRT(252) -> 0.16829581 | F26: =IF(E26="—","",IF(E26>=0.25,"■ HIGH VOLATILITY",IF(E26>=0.17,"▲ ELEVATED",""))) | G26: =C26^2 -> 8.7846073e-07 | H26: α = news impact (ARCH term) [K1 = 0.10] ← how much ε²(t−1) matters | I26: =$I$1+$K$1*G25+$M$1*I25 -> 0.00010069724 | J26: =SQRT(I26)*100 -> 1.0034801 | K26: =J26*SQRT(252) -> 15.929753 | L26: =K26/100 -> 0.15929753 | N26: =-_xlfn.NORM.S.INV(1-$P$1)*J26 -> 1.6505779 | O26: =-_xlfn.NORM.S.INV(1-$R$1)*J26 -> 2.3344439 | P26: =_xlfn.NORM.S.DIST(_xlfn.NORM.S.INV(1-$P$1),FALSE)/(1-$P$1)*J26 -> 2.0698913 | Q26: =_xlfn.NORM.S.DIST(_xlfn.NORM.S.INV(1-$R$1),FALSE)/(1-$R$1)*J26 -> 2.6744895 | R26: =IF(C26*100<-N26,1,0) -> 0 | S26: =IF(C26*100<-O26,1,0) -> 0 | T26: Under a correct model: ~5% / ~1% breach rates expected. | U26: Real-world fix: use Student-t GARCH (heavier tails) to better capture tail risk. | Z26: =-N26 -> -1.6505779 | AA26: =-O26 -> -2.3344439
B27: ='1.RETURNS'!A28 -> 03-Feb-2023 | C27: ='1.RETURNS'!D28 -> -0.013635752 | D27: =STDEV(C8:C27) -> 0.010083104 | E27: =D27*SQRT(252) -> 0.16006431 | F27: =IF(E27="—","",IF(E27>=0.25,"■ HIGH VOLATILITY",IF(E27>=0.17,"▲ ELEVATED",""))) | G27: =C27^2 -> 0.00018593372 | H27: β = persistence (GARCH term) [M1 = 0.85] ← how much σ²(t−1) carries forward | I27: =$I$1+$K$1*G26+$M$1*I26 -> 8.8680499e-05 | J27: =SQRT(I27)*100 -> 0.94170324 | K27: =J27*SQRT(252) -> 14.949075 | L27: =K27/100 -> 0.14949075 | N27: =-_xlfn.NORM.S.INV(1-$P$1)*J27 -> 1.548964 | O27: =-_xlfn.NORM.S.INV(1-$R$1)*J27 -> 2.1907293 | P27: =_xlfn.NORM.S.DIST(_xlfn.NORM.S.INV(1-$P$1),FALSE)/(1-$P$1)*J27 -> 1.9424633 | Q27: =_xlfn.NORM.S.DIST(_xlfn.NORM.S.INV(1-$R$1),FALSE)/(1-$R$1)*J27 -> 2.5098409 | R27: =IF(C27*100<-N27,1,0) -> 0 | S27: =IF(C27*100<-O27,1,0) -> 0 | T27: 250 days × 5% = 12.5 expected breaches for 95% VaR. | Z27: =-N27 -> -1.548964 | AA27: =-O27 -> -2.1907293
B28: ='1.RETURNS'!A29 -> 06-Feb-2023 | C28: ='1.RETURNS'!D29 -> -0.0055921391 | D28: =STDEV(C9:C28) -> 0.01009925 | E28: =D28*SQRT(252) -> 0.16032062 | F28: =IF(E28="—","",IF(E28>=0.25,"■ HIGH VOLATILITY",IF(E28>=0.17,"▲ ELEVATED",""))) | G28: =C28^2 -> 3.127202e-05 | I28: =$I$1+$K$1*G27+$M$1*I27 -> 9.6971796e-05 | J28: =SQRT(I28)*100 -> 0.98474259 | K28: =J28*SQRT(252) -> 15.632304 | L28: =K28/100 -> 0.15632304 | N28: =-_xlfn.NORM.S.INV(1-$P$1)*J28 -> 1.6197574 | O28: =-_xlfn.NORM.S.INV(1-$R$1)*J28 -> 2.2908538 | P28: =_xlfn.NORM.S.DIST(_xlfn.NORM.S.INV(1-$P$1),FALSE)/(1-$P$1)*J28 -> 2.0312411 | Q28: =_xlfn.NORM.S.DIST(_xlfn.NORM.S.INV(1-$R$1),FALSE)/(1-$R$1)*J28 -> 2.6245499 | R28: =IF(C28*100<-N28,1,0) -> 0 | S28: =IF(C28*100<-O28,1,0) -> 0 | T28: The Kupiec test (right →) formally tests model calibration. | Z28: =-N28 -> -1.6197574 | AA28: =-O28 -> -2.2908538
B29: ='1.RETURNS'!A30 -> 07-Feb-2023 | C29: ='1.RETURNS'!D30 -> 0.0013854201 | D29: =STDEV(C10:C29) -> 0.010147237 | E29: =D29*SQRT(252) -> 0.1610824 | F29: =IF(E29="—","",IF(E29>=0.25,"■ HIGH VOLATILITY",IF(E29>=0.17,"▲ ELEVATED",""))) | G29: =C29^2 -> 1.9193889e-06 | H29: ▌ HOW COLUMN I IS COMPUTED [recursive, like MA residuals] | I29: =$I$1+$K$1*G28+$M$1*I28 -> 8.8553229e-05 | J29: =SQRT(I29)*100 -> 0.94102725 | K29: =J29*SQRT(252) -> 14.938344 | L29: =K29/100 -> 0.14938344 | N29: =-_xlfn.NORM.S.INV(1-$P$1)*J29 -> 1.5478521 | O29: =-_xlfn.NORM.S.INV(1-$R$1)*J29 -> 2.1891567 | P29: =_xlfn.NORM.S.DIST(_xlfn.NORM.S.INV(1-$P$1),FALSE)/(1-$P$1)*J29 -> 1.941069 | Q29: =_xlfn.NORM.S.DIST(_xlfn.NORM.S.INV(1-$R$1),FALSE)/(1-$R$1)*J29 -> 2.5080392 | R29: =IF(C29*100<-N29,1,0) -> 0 | S29: =IF(C29*100<-O29,1,0) -> 0 | Z29: =-N29 -> -1.5478521 | AA29: =-O29 -> -2.1891567
B30: ='1.RETURNS'!A31 -> 08-Feb-2023 | C30: ='1.RETURNS'!D31 -> -0.011016358 | D30: =STDEV(C11:C30) -> 0.0093263616 | E30: =D30*SQRT(252) -> 0.1480514 | F30: =IF(E30="—","",IF(E30>=0.25,"■ HIGH VOLATILITY",IF(E30>=0.17,"▲ ELEVATED",""))) | G30: =C30^2 -> 0.00012136014 | H30: Seed (Row 4, blue): long-run unconditional variance: | I30: =$I$1+$K$1*G29+$M$1*I29 -> 7.8462183e-05 | J30: =SQRT(I30)*100 -> 0.88578882 | K30: =J30*SQRT(252) -> 14.061462 | L30: =K30/100 -> 0.14061462 | N30: =-_xlfn.NORM.S.INV(1-$P$1)*J30 -> 1.456993 | O30: =-_xlfn.NORM.S.INV(1-$R$1)*J30 -> 2.0606529 | P30: =_xlfn.NORM.S.DIST(_xlfn.NORM.S.INV(1-$P$1),FALSE)/(1-$P$1)*J30 -> 1.8271279 | Q30: =_xlfn.NORM.S.DIST(_xlfn.NORM.S.INV(1-$R$1),FALSE)/(1-$R$1)*J30 -> 2.360817 | R30: =IF(C30*100<-N30,1,0) -> 0 | S30: =IF(C30*100<-O30,1,0) -> 0 | Z30: =-N30 -> -1.456993 | AA30: =-O30 -> -2.0606529
B31: ='1.RETURNS'!A32 -> 09-Feb-2023 | C31: ='1.RETURNS'!D32 -> 0.0043343887 | D31: =STDEV(C12:C31) -> 0.0090406121 | E31: =D31*SQRT(252) -> 0.14351527 | F31: =IF(E31="—","",IF(E31>=0.25,"■ HIGH VOLATILITY",IF(E31>=0.17,"▲ ELEVATED",""))) | G31: =C31^2 -> 1.8786925e-05 | H31: I4 = ω / (1−α−β) = 0.000003 / 0.05 = 0.00006 | I31: =$I$1+$K$1*G30+$M$1*I30 -> 8.182887e-05 | J31: =SQRT(I31)*100 -> 0.90459311 | K31: =J31*SQRT(252) -> 14.35997 | L31: =K31/100 -> 0.1435997 | N31: =-_xlfn.NORM.S.INV(1-$P$1)*J31 -> 1.4879233 | O31: =-_xlfn.NORM.S.INV(1-$R$1)*J31 -> 2.1043983 | P31: =_xlfn.NORM.S.DIST(_xlfn.NORM.S.INV(1-$P$1),FALSE)/(1-$P$1)*J31 -> 1.8659158 | Q31: =_xlfn.NORM.S.DIST(_xlfn.NORM.S.INV(1-$R$1),FALSE)/(1-$R$1)*J31 -> 2.4109344 | R31: =IF(C31*100<-N31,1,0) -> 0 | S31: =IF(C31*100<-O31,1,0) -> 0 | Z31: =-N31 -> -1.4879233 | AA31: =-O31 -> -2.1043983
B32: ='1.RETURNS'!A33 -> 10-Feb-2023 | C32: ='1.RETURNS'!D33 -> -0.0059637653 | D32: =STDEV(C13:C32) -> 0.0090464232 | E32: =D32*SQRT(252) -> 0.14360752 | F32: =IF(E32="—","",IF(E32>=0.25,"■ HIGH VOLATILITY",IF(E32>=0.17,"▲ ELEVATED",""))) | G32: =C32^2 -> 3.5566497e-05 | H32: Recursion (rows 5–253) — each σ²(t) uses the PRIOR row’s values: | I32: =$I$1+$K$1*G31+$M$1*I31 -> 7.4433232e-05 | J32: =SQRT(I32)*100 -> 0.86274696 | K32: =J32*SQRT(252) -> 13.695683 | L32: =K32/100 -> 0.13695683 | N32: =-_xlfn.NORM.S.INV(1-$P$1)*J32 -> 1.4190925 | O32: =-_xlfn.NORM.S.INV(1-$R$1)*J32 -> 2.0070496 | P32: =_xlfn.NORM.S.DIST(_xlfn.NORM.S.INV(1-$P$1),FALSE)/(1-$P$1)*J32 -> 1.7795992 | Q32: =_xlfn.NORM.S.DIST(_xlfn.NORM.S.INV(1-$R$1),FALSE)/(1-$R$1)*J32 -> 2.2994055 | R32: =IF(C32*100<-N32,1,0) -> 0 | S32: =IF(C32*100<-O32,1,0) -> 0 | Z32: =-N32 -> -1.4190925 | AA32: =-O32 -> -2.0070496
B33: ='1.RETURNS'!A34 -> 13-Feb-2023 | C33: ='1.RETURNS'!D34 -> -0.0027659885 | D33: =STDEV(C14:C33) -> 0.0087463394 | E33: =D33*SQRT(252) -> 0.13884383 | F33: =IF(E33="—","",IF(E33>=0.25,"■ HIGH VOLATILITY",IF(E33>=0.17,"▲ ELEVATED",""))) | G33: =C33^2 -> 7.6506926e-06 | H33: I5 = $I$1 + $K$1 × G4 + $M$1 × I4 | I33: =$I$1+$K$1*G32+$M$1*I32 -> 6.9824897e-05 | J33: =SQRT(I33)*100 -> 0.83561293 | K33: =J33*SQRT(252) -> 13.264944 | L33: =K33/100 -> 0.13264944 | N33: =-_xlfn.NORM.S.INV(1-$P$1)*J33 -> 1.374461 | O33: =-_xlfn.NORM.S.INV(1-$R$1)*J33 -> 1.9439264 | P33: =_xlfn.NORM.S.DIST(_xlfn.NORM.S.INV(1-$P$1),FALSE)/(1-$P$1)*J33 -> 1.7236295 | Q33: =_xlfn.NORM.S.DIST(_xlfn.NORM.S.INV(1-$R$1),FALSE)/(1-$R$1)*J33 -> 2.2270875 | R33: =IF(C33*100<-N33,1,0) -> 0 | S33: =IF(C33*100<-O33,1,0) -> 0 | Z33: =-N33 -> -1.374461 | AA33: =-O33 -> -1.9439264
B34: ='1.RETURNS'!A35 -> 14-Feb-2023 | C34: ='1.RETURNS'!D35 -> -0.005475057 | D34: =STDEV(C15:C34) -> 0.008745571 | E34: =D34*SQRT(252) -> 0.13883164 | F34: =IF(E34="—","",IF(E34>=0.25,"■ HIGH VOLATILITY",IF(E34>=0.17,"▲ ELEVATED",""))) | G34: =C34^2 -> 2.9976249e-05 | H34: J4 = SQRT(I4) × 100 ← daily vol as % | I34: =$I$1+$K$1*G33+$M$1*I33 -> 6.3116231e-05 | J34: =SQRT(I34)*100 -> 0.79445725 | K34: =J34*SQRT(252) -> 12.611618 | L34: =K34/100 -> 0.12611618 | N34: =-_xlfn.NORM.S.INV(1-$P$1)*J34 -> 1.3067659 | O34: =-_xlfn.NORM.S.INV(1-$R$1)*J34 -> 1.8481839 | P34: =_xlfn.NORM.S.DIST(_xlfn.NORM.S.INV(1-$P$1),FALSE)/(1-$P$1)*J34 -> 1.6387371 | Q34: =_xlfn.NORM.S.DIST(_xlfn.NORM.S.INV(1-$R$1),FALSE)/(1-$R$1)*J34 -> 2.1173987 | R34: =IF(C34*100<-N34,1,0) -> 0 | S34: =IF(C34*100<-O34,1,0) -> 0 | Z34: =-N34 -> -1.3067659 | AA34: =-O34 -> -1.8481839
B35: ='1.RETURNS'!A36 -> 15-Feb-2023 | C35: ='1.RETURNS'!D36 -> 0.018407344 | D35: =STDEV(C16:C35) -> 0.010197596 | E35: =D35*SQRT(252) -> 0.16188182 | F35: =IF(E35="—","",IF(E35>=0.25,"■ HIGH VOLATILITY",IF(E35>=0.17,"▲ ELEVATED",""))) | G35: =C35^2 -> 0.0003388303 | H35: K4 = J4 × SQRT(252) ← annualised vol as % | I35: =$I$1+$K$1*G34+$M$1*I34 -> 5.9646422e-05 | J35: =SQRT(I35)*100 -> 0.77231096 | K35: =J35*SQRT(252) -> 12.260056 | L35: =K35/100 -> 0.12260056 | N35: =-_xlfn.NORM.S.INV(1-$P$1)*J35 -> 1.2703385 | O35: =-_xlfn.NORM.S.INV(1-$R$1)*J35 -> 1.796664 | P35: =_xlfn.NORM.S.DIST(_xlfn.NORM.S.INV(1-$P$1),FALSE)/(1-$P$1)*J35 -> 1.5930557 | Q35: =_xlfn.NORM.S.DIST(_xlfn.NORM.S.INV(1-$R$1),FALSE)/(1-$R$1)*J35 -> 2.0583741 | R35: =IF(C35*100<-N35,1,0) -> 0 | S35: =IF(C35*100<-O35,1,0) -> 0 | Z35: =-N35 -> -1.2703385 | AA35: =-O35 -> -1.796664
B36: ='1.RETURNS'!A37 -> 16-Feb-2023 | C36: ='1.RETURNS'!D37 -> 8.7750088e-05 | D36: =STDEV(C17:C36) -> 0.010128808 | E36: =D36*SQRT(252) -> 0.16078985 | F36: =IF(E36="—","",IF(E36>=0.25,"■ HIGH VOLATILITY",IF(E36>=0.17,"▲ ELEVATED",""))) | G36: =C36^2 -> 7.7000779e-09 | I36: =$I$1+$K$1*G35+$M$1*I35 -> 8.7582488e-05 | J36: =SQRT(I36)*100 -> 0.93585516 | K36: =J36*SQRT(252) -> 14.85624 | L36: =K36/100 -> 0.1485624 | N36: =-_xlfn.NORM.S.INV(1-$P$1)*J36 -> 1.5393448 | O36: =-_xlfn.NORM.S.INV(1-$R$1)*J36 -> 2.1771247 | P36: =_xlfn.NORM.S.DIST(_xlfn.NORM.S.INV(1-$P$1),FALSE)/(1-$P$1)*J36 -> 1.9304004 | Q36: =_xlfn.NORM.S.DIST(_xlfn.NORM.S.INV(1-$R$1),FALSE)/(1-$R$1)*J36 -> 2.4942545 | R36: =IF(C36*100<-N36,1,0) -> 0 | S36: =IF(C36*100<-O36,1,0) -> 0 | Z36: =-N36 -> -1.5393448 | AA36: =-O36 -> -2.1771247
B37: ='1.RETURNS'!A38 -> 17-Feb-2023 | C37: ='1.RETURNS'!D38 -> -0.0093562806 | D37: =STDEV(C18:C37) -> 0.0095786111 | E37: =D37*SQRT(252) -> 0.15205574 | F37: =IF(E37="—","",IF(E37>=0.25,"■ HIGH VOLATILITY",IF(E37>=0.17,"▲ ELEVATED",""))) | G37: =C37^2 -> 8.7539986e-05 | H37: ▌ WHAT WE FIND [compare Col E rolling vs Col K GARCH] | I37: =$I$1+$K$1*G36+$M$1*I36 -> 7.7445885e-05 | J37: =SQRT(I37)*100 -> 0.88003344 | K37: =J37*SQRT(252) -> 13.970098 | L37: =K37/100 -> 0.13970098 | N37: =-_xlfn.NORM.S.INV(1-$P$1)*J37 -> 1.4475262 | O37: =-_xlfn.NORM.S.INV(1-$R$1)*J37 -> 2.0472639 | P37: =_xlfn.NORM.S.DIST(_xlfn.NORM.S.INV(1-$P$1),FALSE)/(1-$P$1)*J37 -> 1.8152562 | Q37: =_xlfn.NORM.S.DIST(_xlfn.NORM.S.INV(1-$R$1),FALSE)/(1-$R$1)*J37 -> 2.3454776 | R37: =IF(C37*100<-N37,1,0) -> 0 | S37: =IF(C37*100<-O37,1,0) -> 0 | Z37: =-N37 -> -1.4475262 | AA37: =-O37 -> -2.0472639
B38: ='1.RETURNS'!A39 -> 20-Feb-2023 | C38: ='1.RETURNS'!D39 -> 0.0090814585 | D38: =STDEV(C19:C38) -> 0.0090939196 | E38: =D38*SQRT(252) -> 0.1443615 | F38: =IF(E38="—","",IF(E38>=0.25,"■ HIGH VOLATILITY",IF(E38>=0.17,"▲ ELEVATED",""))) | G38: =C38^2 -> 8.2472889e-05 | H38: GARCH vol [Col K] tracks rolling vol [Col E] closely, but with key differences: | I38: =$I$1+$K$1*G37+$M$1*I37 -> 7.7583001e-05 | J38: =SQRT(I38)*100 -> 0.88081213 | K38: =J38*SQRT(252) -> 13.982459 | L38: =K38/100 -> 0.13982459 | N38: =-_xlfn.NORM.S.INV(1-$P$1)*J38 -> 1.448807 | O38: =-_xlfn.NORM.S.INV(1-$R$1)*J38 -> 2.0490754 | P38: =_xlfn.NORM.S.DIST(_xlfn.NORM.S.INV(1-$P$1),FALSE)/(1-$P$1)*J38 -> 1.8168625 | Q38: =_xlfn.NORM.S.DIST(_xlfn.NORM.S.INV(1-$R$1),FALSE)/(1-$R$1)*J38 -> 2.347553 | R38: =IF(C38*100<-N38,1,0) -> 0 | S38: =IF(C38*100<-O38,1,0) -> 0 | Z38: =-N38 -> -1.448807 | AA38: =-O38 -> -2.0490754
B39: ='1.RETURNS'!A40 -> 21-Feb-2023 | C39: ='1.RETURNS'!D40 -> -0.013189794 | D39: =STDEV(C20:C39) -> 0.0093852636 | E39: =D39*SQRT(252) -> 0.14898644 | F39: =IF(E39="—","",IF(E39>=0.25,"■ HIGH VOLATILITY",IF(E39>=0.17,"▲ ELEVATED",""))) | G39: =C39^2 -> 0.00017397068 | H39: 1. More responsive — a large shock hits σ²(t+1) immediately via α×ε²(t) | I39: =$I$1+$K$1*G38+$M$1*I38 -> 7.719284e-05 | J39: =SQRT(I39)*100 -> 0.87859456 | K39: =J39*SQRT(252) -> 13.947256 | L39: =K39/100 -> 0.13947256 | N39: =-_xlfn.NORM.S.INV(1-$P$1)*J39 -> 1.4451594 | O39: =-_xlfn.NORM.S.INV(1-$R$1)*J39 -> 2.0439166 | P39: =_xlfn.NORM.S.DIST(_xlfn.NORM.S.INV(1-$P$1),FALSE)/(1-$P$1)*J39 -> 1.8122882 | Q39: =_xlfn.NORM.S.DIST(_xlfn.NORM.S.INV(1-$R$1),FALSE)/(1-$R$1)*J39 -> 2.3416427 | R39: =IF(C39*100<-N39,1,0) -> 0 | S39: =IF(C39*100<-O39,1,0) -> 0 | Z39: =-N39 -> -1.4451594 | AA39: =-O39 -> -2.0439166
B40: ='1.RETURNS'!A41 -> 22-Feb-2023 | C40: ='1.RETURNS'!D41 -> 0.0025898212 | D40: =STDEV(C21:C40) -> 0.0092782594 | E40: =D40*SQRT(252) -> 0.1472878 | F40: =IF(E40="—","",IF(E40>=0.25,"■ HIGH VOLATILITY",IF(E40>=0.17,"▲ ELEVATED",""))) | G40: =C40^2 -> 6.7071739e-06 | H40: 2. Smoother — no hard window edge that drops old observations equally | I40: =$I$1+$K$1*G39+$M$1*I39 -> 8.6010981e-05 | J40: =SQRT(I40)*100 -> 0.92742106 | K40: =J40*SQRT(252) -> 14.722353 | L40: =K40/100 -> 0.14722353 | N40: =-_xlfn.NORM.S.INV(1-$P$1)*J40 -> 1.5254719 | O40: =-_xlfn.NORM.S.INV(1-$R$1)*J40 -> 2.157504 | P40: =_xlfn.NORM.S.DIST(_xlfn.NORM.S.INV(1-$P$1),FALSE)/(1-$P$1)*J40 -> 1.9130033 | Q40: =_xlfn.NORM.S.DIST(_xlfn.NORM.S.INV(1-$R$1),FALSE)/(1-$R$1)*J40 -> 2.4717758 | R40: =IF(C40*100<-N40,1,0) -> 0 | S40: =IF(C40*100<-O40,1,0) -> 0 | Z40: =-N40 -> -1.5254719 | AA40: =-O40 -> -2.157504
B41: ='1.RETURNS'!A42 -> 23-Feb-2023 | C41: ='1.RETURNS'!D42 -> -0.018806259 | D41: =STDEV(C22:C41) -> 0.0099260823 | E41: =D41*SQRT(252) -> 0.15757167 | F41: =IF(E41="—","",IF(E41>=0.25,"■ HIGH VOLATILITY",IF(E41>=0.17,"▲ ELEVATED",""))) | G41: =C41^2 -> 0.00035367537 | H41: 3. Forward-looking — gives an explicit forecast for tomorrow’s variance: | I41: =$I$1+$K$1*G40+$M$1*I40 -> 7.6780052e-05 | J41: =SQRT(I41)*100 -> 0.87624227 | K41: =J41*SQRT(252) -> 13.909915 | L41: =K41/100 -> 0.13909915 | N41: =-_xlfn.NORM.S.INV(1-$P$1)*J41 -> 1.4412903 | O41: =-_xlfn.NORM.S.INV(1-$R$1)*J41 -> 2.0384443 | P41: =_xlfn.NORM.S.DIST(_xlfn.NORM.S.INV(1-$P$1),FALSE)/(1-$P$1)*J41 -> 1.8074362 | Q41: =_xlfn.NORM.S.DIST(_xlfn.NORM.S.INV(1-$R$1),FALSE)/(1-$R$1)*J41 -> 2.3353734 | R41: =IF(C41*100<-N41,1,0) -> 1 | S41: =IF(C41*100<-O41,1,0) -> 0 | Z41: =-N41 -> -1.4412903 | AA41: =-O41 -> -2.0384443
B42: ='1.RETURNS'!A43 -> 24-Feb-2023 | C42: ='1.RETURNS'!D43 -> -0.015574917 | D42: =STDEV(C23:C42) -> 0.010250317 | E42: =D42*SQRT(252) -> 0.16271875 | F42: =IF(E42="—","",IF(E42>=0.25,"■ HIGH VOLATILITY",IF(E42>=0.17,"▲ ELEVATED",""))) | G42: =C42^2 -> 0.00024257805 | H42: σ²(t+1) = ω + α×ε²(t) + β×σ²(t) ← known at end of day t | I42: =$I$1+$K$1*G41+$M$1*I41 -> 0.00010363058 | J42: =SQRT(I42)*100 -> 1.0179911 | K42: =J42*SQRT(252) -> 16.160107 | L42: =K42/100 -> 0.16160107 | N42: =-_xlfn.NORM.S.INV(1-$P$1)*J42 -> 1.6744463 | O42: =-_xlfn.NORM.S.INV(1-$R$1)*J42 -> 2.3682014 | P42: =_xlfn.NORM.S.DIST(_xlfn.NORM.S.INV(1-$P$1),FALSE)/(1-$P$1)*J42 -> 2.0998232 | Q42: =_xlfn.NORM.S.DIST(_xlfn.NORM.S.INV(1-$R$1),FALSE)/(1-$R$1)*J42 -> 2.7131643 | R42: =IF(C42*100<-N42,1,0) -> 0 | S42: =IF(C42*100<-O42,1,0) -> 0 | Z42: =-N42 -> -1.6744463 | AA42: =-O42 -> -2.3682014
B43: ='1.RETURNS'!A44 -> 27-Feb-2023 | C43: ='1.RETURNS'!D44 -> 0.0024878126 | D43: =STDEV(C24:C43) -> 0.009982508 | E43: =D43*SQRT(252) -> 0.1584674 | F43: =IF(E43="—","",IF(E43>=0.25,"■ HIGH VOLATILITY",IF(E43>=0.17,"▲ ELEVATED",""))) | G43: =C43^2 -> 6.1892114e-06 | I43: =$I$1+$K$1*G42+$M$1*I42 -> 0.0001153438 | J43: =SQRT(I43)*100 -> 1.0739823 | K43: =J43*SQRT(252) -> 17.048941 | L43: =K43/100 -> 0.17048941 | N43: =-_xlfn.NORM.S.INV(1-$P$1)*J43 -> 1.7665437 | O43: =-_xlfn.NORM.S.INV(1-$R$1)*J43 -> 2.4984565 | P43: =_xlfn.NORM.S.DIST(_xlfn.NORM.S.INV(1-$P$1),FALSE)/(1-$P$1)*J43 -> 2.2153171 | Q43: =_xlfn.NORM.S.DIST(_xlfn.NORM.S.INV(1-$R$1),FALSE)/(1-$R$1)*J43 -> 2.8623929 | R43: =IF(C43*100<-N43,1,0) -> 0 | S43: =IF(C43*100<-O43,1,0) -> 0 | Z43: =-N43 -> -1.7665437 | AA43: =-O43 -> -2.4984565
B44: ='1.RETURNS'!A45 -> 28-Feb-2023 | C44: ='1.RETURNS'!D45 -> 0.0075532941 | D44: =STDEV(C25:C44) -> 0.0092515985 | E44: =D44*SQRT(252) -> 0.14686457 | F44: =IF(E44="—","",IF(E44>=0.25,"■ HIGH VOLATILITY",IF(E44>=0.17,"▲ ELEVATED",""))) | G44: =C44^2 -> 5.7052251e-05 | H44: ▌ THE KEY FINDING: α + β = 0.95 | I44: =$I$1+$K$1*G43+$M$1*I43 -> 0.00010166115 | J44: =SQRT(I44)*100 -> 1.0082715 | K44: =J44*SQRT(252) -> 16.005815 | L44: =K44/100 -> 0.16005815 | N44: =-_xlfn.NORM.S.INV(1-$P$1)*J44 -> 1.6584591 | O44: =-_xlfn.NORM.S.INV(1-$R$1)*J44 -> 2.3455904 | P44: =_xlfn.NORM.S.DIST(_xlfn.NORM.S.INV(1-$P$1),FALSE)/(1-$P$1)*J44 -> 2.0797746 | Q44: =_xlfn.NORM.S.DIST(_xlfn.NORM.S.INV(1-$R$1),FALSE)/(1-$R$1)*J44 -> 2.6872597 | R44: =IF(C44*100<-N44,1,0) -> 0 | S44: =IF(C44*100<-O44,1,0) -> 0 | Z44: =-N44 -> -1.6584591 | AA44: =-O44 -> -2.3455904
B45: ='1.RETURNS'!A46 -> 01-Mar-2023 | C45: ='1.RETURNS'!D46 -> 0.0021145723 | D45: =STDEV(C26:C45) -> 0.0093176851 | E45: =D45*SQRT(252) -> 0.14791367 | F45: =IF(E45="—","",IF(E45>=0.25,"■ HIGH VOLATILITY",IF(E45>=0.17,"▲ ELEVATED",""))) | G45: =C45^2 -> 4.4714162e-06 | H45: With α=0.10 and β=0.85: today’s variance regime carries 95% into tomorrow. | I45: =$I$1+$K$1*G44+$M$1*I44 -> 9.5117203e-05 | J45: =SQRT(I45)*100 -> 0.97528049 | K45: =J45*SQRT(252) -> 15.482098 | L45: =K45/100 -> 0.15482098 | N45: =-_xlfn.NORM.S.INV(1-$P$1)*J45 -> 1.6041936 | O45: =-_xlfn.NORM.S.INV(1-$R$1)*J45 -> 2.2688417 | P45: =_xlfn.NORM.S.DIST(_xlfn.NORM.S.INV(1-$P$1),FALSE)/(1-$P$1)*J45 -> 2.0117236 | Q45: =_xlfn.NORM.S.DIST(_xlfn.NORM.S.INV(1-$R$1),FALSE)/(1-$R$1)*J45 -> 2.5993314 | R45: =IF(C45*100<-N45,1,0) -> 0 | S45: =IF(C45*100<-O45,1,0) -> 0 | Z45: =-N45 -> -1.6041936 | AA45: =-O45 -> -2.2688417
B46: ='1.RETURNS'!A47 -> 02-Mar-2023 | C46: ='1.RETURNS'!D47 -> -0.00084768128 | D46: =STDEV(C27:C46) -> 0.0092903291 | E46: =D46*SQRT(252) -> 0.1474794 | F46: =IF(E46="—","",IF(E46>=0.25,"■ HIGH VOLATILITY",IF(E46>=0.17,"▲ ELEVATED",""))) | G46: =C46^2 -> 7.1856356e-07 | H46: If GARCH vol is 20% today → expect ~19.6% tomorrow (before new return arrives). | I46: =$I$1+$K$1*G45+$M$1*I45 -> 8.4296764e-05 | J46: =SQRT(I46)*100 -> 0.91813269 | K46: =J46*SQRT(252) -> 14.574905 | L46: =K46/100 -> 0.14574905 | N46: =-_xlfn.NORM.S.INV(1-$P$1)*J46 -> 1.5101939 | O46: =-_xlfn.NORM.S.INV(1-$R$1)*J46 -> 2.135896 | P46: =_xlfn.NORM.S.DIST(_xlfn.NORM.S.INV(1-$P$1),FALSE)/(1-$P$1)*J46 -> 1.8938441 | Q46: =_xlfn.NORM.S.DIST(_xlfn.NORM.S.INV(1-$R$1),FALSE)/(1-$R$1)*J46 -> 2.4470203 | R46: =IF(C46*100<-N46,1,0) -> 0 | S46: =IF(C46*100<-O46,1,0) -> 0 | Z46: =-N46 -> -1.5101939 | AA46: =-O46 -> -2.135896
B47: ='1.RETURNS'!A48 -> 03-Mar-2023 | C47: ='1.RETURNS'!D48 -> -0.0027581407 | D47: =STDEV(C28:C47) -> 0.0089283368 | E47: =D47*SQRT(252) -> 0.14173295 | F47: =IF(E47="—","",IF(E47>=0.25,"■ HIGH VOLATILITY",IF(E47>=0.17,"▲ ELEVATED",""))) | G47: =C47^2 -> 7.6073402e-06 | H47: Long-run vol ≈ SQRT(ω/(1−α−β)) × 100 × SQRT(252) ≈ 12% annual | I47: =$I$1+$K$1*G46+$M$1*I46 -> 7.4724106e-05 | J47: =SQRT(I47)*100 -> 0.86443106 | K47: =J47*SQRT(252) -> 13.722418 | L47: =K47/100 -> 0.13722418 | N47: =-_xlfn.NORM.S.INV(1-$P$1)*J47 -> 1.4218626 | O47: =-_xlfn.NORM.S.INV(1-$R$1)*J47 -> 2.0109674 | P47: =_xlfn.NORM.S.DIST(_xlfn.NORM.S.INV(1-$P$1),FALSE)/(1-$P$1)*J47 -> 1.783073 | Q47: =_xlfn.NORM.S.DIST(_xlfn.NORM.S.INV(1-$R$1),FALSE)/(1-$R$1)*J47 -> 2.303894 | R47: =IF(C47*100<-N47,1,0) -> 0 | S47: =IF(C47*100<-O47,1,0) -> 0 | Z47: =-N47 -> -1.4218626 | AA47: =-O47 -> -2.0109674
B48: ='1.RETURNS'!A49 -> 06-Mar-2023 | C48: ='1.RETURNS'!D49 -> -0.014851304 | D48: =STDEV(C29:C48) -> 0.0093456858 | E48: =D48*SQRT(252) -> 0.14835816 | F48: =IF(E48="—","",IF(E48>=0.25,"■ HIGH VOLATILITY",IF(E48>=0.17,"▲ ELEVATED",""))) | G48: =C48^2 -> 0.00022056123 | H48: Mean reversion speed: vol reverts toward 12% at rate (1−α−β) = 5% per day. | I48: =$I$1+$K$1*G47+$M$1*I47 -> 6.7276224e-05 | J48: =SQRT(I48)*100 -> 0.82022085 | K48: =J48*SQRT(252) -> 13.020602 | L48: =K48/100 -> 0.13020602 | N48: =-_xlfn.NORM.S.INV(1-$P$1)*J48 -> 1.3491432 | O48: =-_xlfn.NORM.S.INV(1-$R$1)*J48 -> 1.908119 | P48: =_xlfn.NORM.S.DIST(_xlfn.NORM.S.INV(1-$P$1),FALSE)/(1-$P$1)*J48 -> 1.6918801 | Q48: =_xlfn.NORM.S.DIST(_xlfn.NORM.S.INV(1-$R$1),FALSE)/(1-$R$1)*J48 -> 2.1860643 | R48: =IF(C48*100<-N48,1,0) -> 1 | S48: =IF(C48*100<-O48,1,0) -> 0 | Z48: =-N48 -> -1.3491432 | AA48: =-O48 -> -1.908119
B49: ='1.RETURNS'!A50 -> 07-Mar-2023 | C49: ='1.RETURNS'!D50 -> -0.0076831274 | D49: =STDEV(C30:C49) -> 0.0093606863 | E49: =D49*SQRT(252) -> 0.14859629 | F49: =IF(E49="—","",IF(E49>=0.25,"■ HIGH VOLATILITY",IF(E49>=0.17,"▲ ELEVATED",""))) | G49: =C49^2 -> 5.9030447e-05 | H49: Contrast with ARIMA: φ̂≈−0.17 (mean autocorr). Here: β=0.85 (variance autocorr). | I49: =$I$1+$K$1*G48+$M$1*I48 -> 8.2240914e-05 | J49: =SQRT(I49)*100 -> 0.90686776 | K49: =J49*SQRT(252) -> 14.396079 | L49: =K49/100 -> 0.14396079 | N49: =-_xlfn.NORM.S.INV(1-$P$1)*J49 -> 1.4916647 | O49: =-_xlfn.NORM.S.INV(1-$R$1)*J49 -> 2.1096899 | P49: =_xlfn.NORM.S.DIST(_xlfn.NORM.S.INV(1-$P$1),FALSE)/(1-$P$1)*J49 -> 1.8706077 | Q49: =_xlfn.NORM.S.DIST(_xlfn.NORM.S.INV(1-$R$1),FALSE)/(1-$R$1)*J49 -> 2.4169969 | R49: =IF(C49*100<-N49,1,0) -> 0 | S49: =IF(C49*100<-O49,1,0) -> 0 | Z49: =-N49 -> -1.4916647 | AA49: =-O49 -> -2.1096899
B50: ='1.RETURNS'!A51 -> 08-Mar-2023 | C50: ='1.RETURNS'!D51 -> -0.0043656826 | D50: =STDEV(C31:C50) -> 0.0091803669 | E50: =D50*SQRT(252) -> 0.14573381 | F50: =IF(E50="—","",IF(E50>=0.25,"■ HIGH VOLATILITY",IF(E50>=0.17,"▲ ELEVATED",""))) | G50: =C50^2 -> 1.9059185e-05 | H50: Variance is far MORE persistent and predictable than the mean. | I50: =$I$1+$K$1*G49+$M$1*I49 -> 7.8807822e-05 | J50: =SQRT(I50)*100 -> 0.8877377 | K50: =J50*SQRT(252) -> 14.092399 | L50: =K50/100 -> 0.14092399 | N50: =-_xlfn.NORM.S.INV(1-$P$1)*J50 -> 1.4601986 | O50: =-_xlfn.NORM.S.INV(1-$R$1)*J50 -> 2.0651867 | P50: =_xlfn.NORM.S.DIST(_xlfn.NORM.S.INV(1-$P$1),FALSE)/(1-$P$1)*J50 -> 1.8311479 | Q50: =_xlfn.NORM.S.DIST(_xlfn.NORM.S.INV(1-$R$1),FALSE)/(1-$R$1)*J50 -> 2.3660111 | R50: =IF(C50*100<-N50,1,0) -> 0 | S50: =IF(C50*100<-O50,1,0) -> 0 | Z50: =-N50 -> -1.4601986 | AA50: =-O50 -> -2.0651867
B51: ='1.RETURNS'!A52 -> 09-Mar-2023 | C51: ='1.RETURNS'!D52 -> 0.010511056 | D51: =STDEV(C32:C51) -> 0.0095284937 | E51: =D51*SQRT(252) -> 0.15126015 | F51: =IF(E51="—","",IF(E51>=0.25,"■ HIGH VOLATILITY",IF(E51>=0.17,"▲ ELEVATED",""))) | G51: =C51^2 -> 0.00011048229 | I51: =$I$1+$K$1*G50+$M$1*I50 -> 7.1892567e-05 | J51: =SQRT(I51)*100 -> 0.84789484 | K51: =J51*SQRT(252) -> 13.459913 | L51: =K51/100 -> 0.13459913 | N51: =-_xlfn.NORM.S.INV(1-$P$1)*J51 -> 1.3946629 | O51: =-_xlfn.NORM.S.INV(1-$R$1)*J51 -> 1.9724984 | P51: =_xlfn.NORM.S.DIST(_xlfn.NORM.S.INV(1-$P$1),FALSE)/(1-$P$1)*J51 -> 1.7489636 | Q51: =_xlfn.NORM.S.DIST(_xlfn.NORM.S.INV(1-$R$1),FALSE)/(1-$R$1)*J51 -> 2.2598214 | R51: =IF(C51*100<-N51,1,0) -> 0 | S51: =IF(C51*100<-O51,1,0) -> 0 | Z51: =-N51 -> -1.3946629 | AA51: =-O51 -> -1.9724984
B52: ='1.RETURNS'!A53 -> 10-Mar-2023 | C52: ='1.RETURNS'!D53 -> 0.0038205554 | D52: =STDEV(C33:C52) -> 0.0095890492 | E52: =D52*SQRT(252) -> 0.15222144 | F52: =IF(E52="—","",IF(E52>=0.25,"■ HIGH VOLATILITY",IF(E52>=0.17,"▲ ELEVATED",""))) | G52: =C52^2 -> 1.4596644e-05 | H52: ▌ THE HONEST PUNCHLINE | I52: =$I$1+$K$1*G51+$M$1*I51 -> 7.5156911e-05 | J52: =SQRT(I52)*100 -> 0.86693086 | K52: =J52*SQRT(252) -> 13.762101 | L52: =K52/100 -> 0.13762101 | N52: =-_xlfn.NORM.S.INV(1-$P$1)*J52 -> 1.4259744 | O52: =-_xlfn.NORM.S.INV(1-$R$1)*J52 -> 2.0167828 | P52: =_xlfn.NORM.S.DIST(_xlfn.NORM.S.INV(1-$P$1),FALSE)/(1-$P$1)*J52 -> 1.7882294 | Q52: =_xlfn.NORM.S.DIST(_xlfn.NORM.S.INV(1-$R$1),FALSE)/(1-$R$1)*J52 -> 2.3105564 | R52: =IF(C52*100<-N52,1,0) -> 0 | S52: =IF(C52*100<-O52,1,0) -> 0 | Z52: =-N52 -> -1.4259744 | AA52: =-O52 -> -2.0167828
B53: ='1.RETURNS'!A54 -> 13-Mar-2023 | C53: ='1.RETURNS'!D54 -> -0.016681933 | D53: =STDEV(C34:C53) -> 0.010140332 | E53: =D53*SQRT(252) -> 0.16097277 | F53: =IF(E53="—","",IF(E53>=0.25,"■ HIGH VOLATILITY",IF(E53>=0.17,"▲ ELEVATED",""))) | G53: =C53^2 -> 0.0002782869 | H53: ARIMA: mean ≈ unpredictable. Fitted values ≈ 0. R² ≈ 3%. | I53: =$I$1+$K$1*G52+$M$1*I52 -> 6.8343039e-05 | J53: =SQRT(I53)*100 -> 0.82669849 | K53: =J53*SQRT(252) -> 13.123432 | L53: =K53/100 -> 0.13123432 | N53: =-_xlfn.NORM.S.INV(1-$P$1)*J53 -> 1.359798 | O53: =-_xlfn.NORM.S.INV(1-$R$1)*J53 -> 1.9231883 | P53: =_xlfn.NORM.S.DIST(_xlfn.NORM.S.INV(1-$P$1),FALSE)/(1-$P$1)*J53 -> 1.7052416 | Q53: =_xlfn.NORM.S.DIST(_xlfn.NORM.S.INV(1-$R$1),FALSE)/(1-$R$1)*J53 -> 2.2033286 | R53: =IF(C53*100<-N53,1,0) -> 1 | S53: =IF(C53*100<-O53,1,0) -> 0 | Z53: =-N53 -> -1.359798 | AA53: =-O53 -> -1.9231883
B54: ='1.RETURNS'!A55 -> 14-Mar-2023 | C54: ='1.RETURNS'!D55 -> 0.0040394349 | D54: =STDEV(C35:C54) -> 0.010223505 | E54: =D54*SQRT(252) -> 0.16229311 | F54: =IF(E54="—","",IF(E54>=0.25,"■ HIGH VOLATILITY",IF(E54>=0.17,"▲ ELEVATED",""))) | G54: =C54^2 -> 1.6317034e-05 | H54: GARCH: variance IS predictable. Tomorrow’s vol ≈ today’s vol × 0.95. | I54: =$I$1+$K$1*G53+$M$1*I53 -> 8.8920272e-05 | J54: =SQRT(I54)*100 -> 0.94297546 | K54: =J54*SQRT(252) -> 14.969271 | L54: =K54/100 -> 0.14969271 | N54: =-_xlfn.NORM.S.INV(1-$P$1)*J54 -> 1.5510566 | O54: =-_xlfn.NORM.S.INV(1-$R$1)*J54 -> 2.193689 | P54: =_xlfn.NORM.S.DIST(_xlfn.NORM.S.INV(1-$P$1),FALSE)/(1-$P$1)*J54 -> 1.9450876 | Q54: =_xlfn.NORM.S.DIST(_xlfn.NORM.S.INV(1-$R$1),FALSE)/(1-$R$1)*J54 -> 2.5132316 | R54: =IF(C54*100<-N54,1,0) -> 0 | S54: =IF(C54*100<-O54,1,0) -> 0 | Z54: =-N54 -> -1.5510566 | AA54: =-O54 -> -2.193689
B55: ='1.RETURNS'!A56 -> 15-Mar-2023 | C55: ='1.RETURNS'!D56 -> -0.0034328482 | D55: =STDEV(C36:C55) -> 0.0090033648 | E55: =D55*SQRT(252) -> 0.14292399 | F55: =IF(E55="—","",IF(E55>=0.25,"■ HIGH VOLATILITY",IF(E55>=0.17,"▲ ELEVATED",""))) | G55: =C55^2 -> 1.1784447e-05 | H55: GARCH tells you HOW WIDE tomorrow’s return distribution will be, not its direction. | I55: =$I$1+$K$1*G54+$M$1*I54 -> 8.0213935e-05 | J55: =SQRT(I55)*100 -> 0.89562233 | K55: =J55*SQRT(252) -> 14.217564 | L55: =K55/100 -> 0.14217564 | N55: =-_xlfn.NORM.S.INV(1-$P$1)*J55 -> 1.4731676 | O55: =-_xlfn.NORM.S.INV(1-$R$1)*J55 -> 2.0835291 | P55: =_xlfn.NORM.S.DIST(_xlfn.NORM.S.INV(1-$P$1),FALSE)/(1-$P$1)*J55 -> 1.8474116 | Q55: =_xlfn.NORM.S.DIST(_xlfn.NORM.S.INV(1-$R$1),FALSE)/(1-$R$1)*J55 -> 2.3870254 | R55: =IF(C55*100<-N55,1,0) -> 0 | S55: =IF(C55*100<-O55,1,0) -> 0 | Z55: =-N55 -> -1.4731676 | AA55: =-O55 -> -2.0835291
B56: ='1.RETURNS'!A57 -> 16-Mar-2023 | C56: ='1.RETURNS'!D57 -> -0.0063454124 | D56: =STDEV(C37:C56) -> 0.0089922599 | E56: =D56*SQRT(252) -> 0.1427477 | F56: =IF(E56="—","",IF(E56>=0.25,"■ HIGH VOLATILITY",IF(E56>=0.17,"▲ ELEVATED",""))) | G56: =C56^2 -> 4.0264258e-05 | H56: That’s enough to price options, compute VaR, and size positions correctly. | I56: =$I$1+$K$1*G55+$M$1*I55 -> 7.2360289e-05 | J56: =SQRT(I56)*100 -> 0.85064851 | K56: =J56*SQRT(252) -> 13.503627 | L56: =K56/100 -> 0.13503627 | N56: =-_xlfn.NORM.S.INV(1-$P$1)*J56 -> 1.3991923 | O56: =-_xlfn.NORM.S.INV(1-$R$1)*J56 -> 1.9789044 | P56: =_xlfn.NORM.S.DIST(_xlfn.NORM.S.INV(1-$P$1),FALSE)/(1-$P$1)*J56 -> 1.7546436 | Q56: =_xlfn.NORM.S.DIST(_xlfn.NORM.S.INV(1-$R$1),FALSE)/(1-$R$1)*J56 -> 2.2671605 | R56: =IF(C56*100<-N56,1,0) -> 0 | S56: =IF(C56*100<-O56,1,0) -> 0 | Z56: =-N56 -> -1.3991923 | AA56: =-O56 -> -1.9789044
B57: ='1.RETURNS'!A58 -> 17-Mar-2023 | C57: ='1.RETURNS'!D58 -> 0.006744671 | D57: =STDEV(C38:C57) -> 0.0091673878 | E57: =D57*SQRT(252) -> 0.14552777 | F57: =IF(E57="—","",IF(E57>=0.25,"■ HIGH VOLATILITY",IF(E57>=0.17,"▲ ELEVATED",""))) | G57: =C57^2 -> 4.5490587e-05 | H57: → This is the bridge from mean-modelling (ARIMA) to variance-modelling (GARCH). | I57: =$I$1+$K$1*G56+$M$1*I56 -> 6.8532672e-05 | J57: =SQRT(I57)*100 -> 0.82784462 | K57: =J57*SQRT(252) -> 13.141626 | L57: =K57/100 -> 0.13141626 | N57: =-_xlfn.NORM.S.INV(1-$P$1)*J57 -> 1.3616832 | O57: =-_xlfn.NORM.S.INV(1-$R$1)*J57 -> 1.9258546 | P57: =_xlfn.NORM.S.DIST(_xlfn.NORM.S.INV(1-$P$1),FALSE)/(1-$P$1)*J57 -> 1.7076057 | Q57: =_xlfn.NORM.S.DIST(_xlfn.NORM.S.INV(1-$R$1),FALSE)/(1-$R$1)*J57 -> 2.2063833 | R57: =IF(C57*100<-N57,1,0) -> 0 | S57: =IF(C57*100<-O57,1,0) -> 0 | Z57: =-N57 -> -1.3616832 | AA57: =-O57 -> -1.9258546
B58: ='1.RETURNS'!A59 -> 20-Mar-2023 | C58: ='1.RETURNS'!D59 -> 0.010476356 | D58: =STDEV(C39:C58) -> 0.0092671397 | E58: =D58*SQRT(252) -> 0.14711128 | F58: =IF(E58="—","",IF(E58>=0.25,"■ HIGH VOLATILITY",IF(E58>=0.17,"▲ ELEVATED",""))) | G58: =C58^2 -> 0.00010975404 | I58: =$I$1+$K$1*G57+$M$1*I57 -> 6.580183e-05 | J58: =SQRT(I58)*100 -> 0.81118327 | K58: =J58*SQRT(252) -> 12.877135 | L58: =K58/100 -> 0.12877135 | N58: =-_xlfn.NORM.S.INV(1-$P$1)*J58 -> 1.3342777 | O58: =-_xlfn.NORM.S.INV(1-$R$1)*J58 -> 1.8870945 | P58: =_xlfn.NORM.S.DIST(_xlfn.NORM.S.INV(1-$P$1),FALSE)/(1-$P$1)*J58 -> 1.6732381 | Q58: =_xlfn.NORM.S.DIST(_xlfn.NORM.S.INV(1-$R$1),FALSE)/(1-$R$1)*J58 -> 2.1619772 | R58: =IF(C58*100<-N58,1,0) -> 0 | S58: =IF(C58*100<-O58,1,0) -> 0 | Z58: =-N58 -> -1.3342777 | AA58: =-O58 -> -1.8870945
B59: ='1.RETURNS'!A60 -> 21-Mar-2023 | C59: ='1.RETURNS'!D60 -> 0.010563192 | D59: =STDEV(C40:C59) -> 0.0093748204 | E59: =D59*SQRT(252) -> 0.14882066 | F59: =IF(E59="—","",IF(E59>=0.25,"■ HIGH VOLATILITY",IF(E59>=0.17,"▲ ELEVATED",""))) | G59: =C59^2 -> 0.00011158103 | I59: =$I$1+$K$1*G58+$M$1*I58 -> 6.9906959e-05 | J59: =SQRT(I59)*100 -> 0.83610382 | K59: =J59*SQRT(252) -> 13.272737 | L59: =K59/100 -> 0.13272737 | N59: =-_xlfn.NORM.S.INV(1-$P$1)*J59 -> 1.3752684 | O59: =-_xlfn.NORM.S.INV(1-$R$1)*J59 -> 1.9450683 | P59: =_xlfn.NORM.S.DIST(_xlfn.NORM.S.INV(1-$P$1),FALSE)/(1-$P$1)*J59 -> 1.7246421 | Q59: =_xlfn.NORM.S.DIST(_xlfn.NORM.S.INV(1-$R$1),FALSE)/(1-$R$1)*J59 -> 2.2283958 | R59: =IF(C59*100<-N59,1,0) -> 0 | S59: =IF(C59*100<-O59,1,0) -> 0 | Z59: =-N59 -> -1.3752684 | AA59: =-O59 -> -1.9450683
B60: ='1.RETURNS'!A61 -> 22-Mar-2023 | C60: ='1.RETURNS'!D61 -> -0.0086289841 | D60: =STDEV(C41:C60) -> 0.0094511476 | E60: =D60*SQRT(252) -> 0.15003232 | F60: =IF(E60="—","",IF(E60>=0.25,"■ HIGH VOLATILITY",IF(E60>=0.17,"▲ ELEVATED",""))) | G60: =C60^2 -> 7.4459366e-05 | I60: =$I$1+$K$1*G59+$M$1*I59 -> 7.3579019e-05 | J60: =SQRT(I60)*100 -> 0.85778213 | K60: =J60*SQRT(252) -> 13.616869 | L60: =K60/100 -> 0.13616869 | N60: =-_xlfn.NORM.S.INV(1-$P$1)*J60 -> 1.4109261 | O60: =-_xlfn.NORM.S.INV(1-$R$1)*J60 -> 1.9954996 | P60: =_xlfn.NORM.S.DIST(_xlfn.NORM.S.INV(1-$P$1),FALSE)/(1-$P$1)*J60 -> 1.7693582 | Q60: =_xlfn.NORM.S.DIST(_xlfn.NORM.S.INV(1-$R$1),FALSE)/(1-$R$1)*J60 -> 2.2861731 | R60: =IF(C60*100<-N60,1,0) -> 0 | S60: =IF(C60*100<-O60,1,0) -> 0 | Z60: =-N60 -> -1.4109261 | AA60: =-O60 -> -1.9954996
B61: ='1.RETURNS'!A62 -> 23-Mar-2023 | C61: ='1.RETURNS'!D62 -> -0.0028929543 | D61: =STDEV(C42:C61) -> 0.0086007806 | E61: =D61*SQRT(252) -> 0.13653316 | F61: =IF(E61="—","",IF(E61>=0.25,"■ HIGH VOLATILITY",IF(E61>=0.17,"▲ ELEVATED",""))) | G61: =C61^2 -> 8.3691843e-06 | I61: =$I$1+$K$1*G60+$M$1*I60 -> 7.2988103e-05 | J61: =SQRT(I61)*100 -> 0.85433075 | K61: =J61*SQRT(252) -> 13.56208 | L61: =K61/100 -> 0.1356208 | N61: =-_xlfn.NORM.S.INV(1-$P$1)*J61 -> 1.405249 | O61: =-_xlfn.NORM.S.INV(1-$R$1)*J61 -> 1.9874705 | P61: =_xlfn.NORM.S.DIST(_xlfn.NORM.S.INV(1-$P$1),FALSE)/(1-$P$1)*J61 -> 1.762239 | Q61: =_xlfn.NORM.S.DIST(_xlfn.NORM.S.INV(1-$R$1),FALSE)/(1-$R$1)*J61 -> 2.2769745 | R61: =IF(C61*100<-N61,1,0) -> 0 | S61: =IF(C61*100<-O61,1,0) -> 0 | Z61: =-N61 -> -1.405249 | AA61: =-O61 -> -1.9874705
B62: ='1.RETURNS'!A63 -> 24-Mar-2023 | C62: ='1.RETURNS'!D63 -> 0.0035960395 | D62: =STDEV(C43:C62) -> 0.0079698161 | E62: =D62*SQRT(252) -> 0.12651691 | F62: =IF(E62="—","",IF(E62>=0.25,"■ HIGH VOLATILITY",IF(E62>=0.17,"▲ ELEVATED",""))) | G62: =C62^2 -> 1.29315e-05 | I62: =$I$1+$K$1*G61+$M$1*I61 -> 6.5876806e-05 | J62: =SQRT(I62)*100 -> 0.81164528 | K62: =J62*SQRT(252) -> 12.884469 | L62: =K62/100 -> 0.12884469 | N62: =-_xlfn.NORM.S.INV(1-$P$1)*J62 -> 1.3350377 | O62: =-_xlfn.NORM.S.INV(1-$R$1)*J62 -> 1.8881693 | P62: =_xlfn.NORM.S.DIST(_xlfn.NORM.S.INV(1-$P$1),FALSE)/(1-$P$1)*J62 -> 1.6741911 | Q62: =_xlfn.NORM.S.DIST(_xlfn.NORM.S.INV(1-$R$1),FALSE)/(1-$R$1)*J62 -> 2.1632085 | R62: =IF(C62*100<-N62,1,0) -> 0 | S62: =IF(C62*100<-O62,1,0) -> 0 | Z62: =-N62 -> -1.3350377 | AA62: =-O62 -> -1.8881693
B63: ='1.RETURNS'!A64 -> 27-Mar-2023 | C63: ='1.RETURNS'!D64 -> 0.010092627 | D63: =STDEV(C44:C63) -> 0.0082864075 | E63: =D63*SQRT(252) -> 0.13154264 | F63: =IF(E63="—","",IF(E63>=0.25,"■ HIGH VOLATILITY",IF(E63>=0.17,"▲ ELEVATED",""))) | G63: =C63^2 -> 0.00010186112 | I63: =$I$1+$K$1*G62+$M$1*I62 -> 6.0288435e-05 | J63: =SQRT(I63)*100 -> 0.77645628 | K63: =J63*SQRT(252) -> 12.325861 | L63: =K63/100 -> 0.12325861 | N63: =-_xlfn.NORM.S.INV(1-$P$1)*J63 -> 1.2771569 | O63: =-_xlfn.NORM.S.INV(1-$R$1)*J63 -> 1.8063074 | P63: =_xlfn.NORM.S.DIST(_xlfn.NORM.S.INV(1-$P$1),FALSE)/(1-$P$1)*J63 -> 1.6016063 | Q63: =_xlfn.NORM.S.DIST(_xlfn.NORM.S.INV(1-$R$1),FALSE)/(1-$R$1)*J63 -> 2.0694223 | R63: =IF(C63*100<-N63,1,0) -> 0 | S63: =IF(C63*100<-O63,1,0) -> 0 | Z63: =-N63 -> -1.2771569 | AA63: =-O63 -> -1.8063074
B64: ='1.RETURNS'!A65 -> 28-Mar-2023 | C64: ='1.RETURNS'!D65 -> -0.0050517287 | D64: =STDEV(C45:C64) -> 0.008164236 | E64: =D64*SQRT(252) -> 0.12960323 | F64: =IF(E64="—","",IF(E64>=0.25,"■ HIGH VOLATILITY",IF(E64>=0.17,"▲ ELEVATED",""))) | G64: =C64^2 -> 2.5519963e-05 | I64: =$I$1+$K$1*G63+$M$1*I63 -> 6.4431281e-05 | J64: =SQRT(I64)*100 -> 0.80269098 | K64: =J64*SQRT(252) -> 12.742324 | L64: =K64/100 -> 0.12742324 | N64: =-_xlfn.NORM.S.INV(1-$P$1)*J64 -> 1.3203092 | O64: =-_xlfn.NORM.S.INV(1-$R$1)*J64 -> 1.8673385 | P64: =_xlfn.NORM.S.DIST(_xlfn.NORM.S.INV(1-$P$1),FALSE)/(1-$P$1)*J64 -> 1.655721 | Q64: =_xlfn.NORM.S.DIST(_xlfn.NORM.S.INV(1-$R$1),FALSE)/(1-$R$1)*J64 -> 2.1393434 | R64: =IF(C64*100<-N64,1,0) -> 0 | S64: =IF(C64*100<-O64,1,0) -> 0 | Z64: =-N64 -> -1.3203092 | AA64: =-O64 -> -1.8673385
B65: ='1.RETURNS'!A66 -> 29-Mar-2023 | C65: ='1.RETURNS'!D66 -> -0.0016564715 | D65: =STDEV(C46:C65) -> 0.0081422689 | E65: =D65*SQRT(252) -> 0.12925451 | F65: =IF(E65="—","",IF(E65>=0.25,"■ HIGH VOLATILITY",IF(E65>=0.17,"▲ ELEVATED",""))) | G65: =C65^2 -> 2.7438979e-06 | I65: =$I$1+$K$1*G64+$M$1*I64 -> 6.0318585e-05 | J65: =SQRT(I65)*100 -> 0.77665041 | K65: =J65*SQRT(252) -> 12.328943 | L65: =K65/100 -> 0.12328943 | N65: =-_xlfn.NORM.S.INV(1-$P$1)*J65 -> 1.2774762 | O65: =-_xlfn.NORM.S.INV(1-$R$1)*J65 -> 1.806759 | P65: =_xlfn.NORM.S.DIST(_xlfn.NORM.S.INV(1-$P$1),FALSE)/(1-$P$1)*J65 -> 1.6020067 | Q65: =_xlfn.NORM.S.DIST(_xlfn.NORM.S.INV(1-$R$1),FALSE)/(1-$R$1)*J65 -> 2.0699397 | R65: =IF(C65*100<-N65,1,0) -> 0 | S65: =IF(C65*100<-O65,1,0) -> 0 | Z65: =-N65 -> -1.2774762 | AA65: =-O65 -> -1.806759
B66: ='1.RETURNS'!A67 -> 30-Mar-2023 | C66: ='1.RETURNS'!D67 -> -0.010795267 | D66: =STDEV(C47:C66) -> 0.0084455967 | E66: =D66*SQRT(252) -> 0.13406969 | F66: =IF(E66="—","",IF(E66>=0.25,"■ HIGH VOLATILITY",IF(E66>=0.17,"▲ ELEVATED",""))) | G66: =C66^2 -> 0.00011653779 | I66: =$I$1+$K$1*G65+$M$1*I65 -> 5.4545187e-05 | J66: =SQRT(I66)*100 -> 0.73854714 | K66: =J66*SQRT(252) -> 11.724072 | L66: =K66/100 -> 0.11724072 | N66: =-_xlfn.NORM.S.INV(1-$P$1)*J66 -> 1.2148019 | O66: =-_xlfn.NORM.S.INV(1-$R$1)*J66 -> 1.7181176 | P66: =_xlfn.NORM.S.DIST(_xlfn.NORM.S.INV(1-$P$1),FALSE)/(1-$P$1)*J66 -> 1.5234106 | Q66: =_xlfn.NORM.S.DIST(_xlfn.NORM.S.INV(1-$R$1),FALSE)/(1-$R$1)*J66 -> 1.9683863 | R66: =IF(C66*100<-N66,1,0) -> 0 | S66: =IF(C66*100<-O66,1,0) -> 0 | Z66: =-N66 -> -1.2148019 | AA66: =-O66 -> -1.7181176
B67: ='1.RETURNS'!A68 -> 31-Mar-2023 | C67: ='1.RETURNS'!D68 -> -0.012445 | D67: =STDEV(C48:C67) -> 0.008805815 | E67: =D67*SQRT(252) -> 0.13978798 | F67: =IF(E67="—","",IF(E67>=0.25,"■ HIGH VOLATILITY",IF(E67>=0.17,"▲ ELEVATED",""))) | G67: =C67^2 -> 0.00015487801 | I67: =$I$1+$K$1*G66+$M$1*I66 -> 6.1017189e-05 | J67: =SQRT(I67)*100 -> 0.781135 | K67: =J67*SQRT(252) -> 12.400134 | L67: =K67/100 -> 0.12400134 | N67: =-_xlfn.NORM.S.INV(1-$P$1)*J67 -> 1.2848527 | O67: =-_xlfn.NORM.S.INV(1-$R$1)*J67 -> 1.8171917 | P67: =_xlfn.NORM.S.DIST(_xlfn.NORM.S.INV(1-$P$1),FALSE)/(1-$P$1)*J67 -> 1.6112572 | Q67: =_xlfn.NORM.S.DIST(_xlfn.NORM.S.INV(1-$R$1),FALSE)/(1-$R$1)*J67 -> 2.0818921 | R67: =IF(C67*100<-N67,1,0) -> 0 | S67: =IF(C67*100<-O67,1,0) -> 0 | Z67: =-N67 -> -1.2848527 | AA67: =-O67 -> -1.8171917
B68: ='1.RETURNS'!A69 -> 03-Apr-2023 | C68: ='1.RETURNS'!D69 -> 0.008974606 | D68: =STDEV(C49:C68) -> 0.0085478929 | E68: =D68*SQRT(252) -> 0.13569359 | F68: =IF(E68="—","",IF(E68>=0.25,"■ HIGH VOLATILITY",IF(E68>=0.17,"▲ ELEVATED",""))) | G68: =C68^2 -> 8.0543553e-05 | I68: =$I$1+$K$1*G67+$M$1*I67 -> 7.0352412e-05 | J68: =SQRT(I68)*100 -> 0.83876345 | K68: =J68*SQRT(252) -> 13.314957 | L68: =K68/100 -> 0.13314957 | N68: =-_xlfn.NORM.S.INV(1-$P$1)*J68 -> 1.3796431 | O68: =-_xlfn.NORM.S.INV(1-$R$1)*J68 -> 1.9512556 | P68: =_xlfn.NORM.S.DIST(_xlfn.NORM.S.INV(1-$P$1),FALSE)/(1-$P$1)*J68 -> 1.7301281 | Q68: =_xlfn.NORM.S.DIST(_xlfn.NORM.S.INV(1-$R$1),FALSE)/(1-$R$1)*J68 -> 2.2354843 | R68: =IF(C68*100<-N68,1,0) -> 0 | S68: =IF(C68*100<-O68,1,0) -> 0 | Z68: =-N68 -> -1.3796431 | AA68: =-O68 -> -1.9512556
B69: ='1.RETURNS'!A70 -> 04-Apr-2023 | C69: ='1.RETURNS'!D70 -> 0.014946502 | D69: =STDEV(C50:C69) -> 0.0090387532 | E69: =D69*SQRT(252) -> 0.14348576 | F69: =IF(E69="—","",IF(E69>=0.25,"■ HIGH VOLATILITY",IF(E69>=0.17,"▲ ELEVATED",""))) | G69: =C69^2 -> 0.00022339793 | I69: =$I$1+$K$1*G68+$M$1*I68 -> 7.0853905e-05 | J69: =SQRT(I69)*100 -> 0.84174762 | K69: =J69*SQRT(252) -> 13.362329 | L69: =K69/100 -> 0.13362329 | N69: =-_xlfn.NORM.S.INV(1-$P$1)*J69 -> 1.3845516 | O69: =-_xlfn.NORM.S.INV(1-$R$1)*J69 -> 1.9581978 | P69: =_xlfn.NORM.S.DIST(_xlfn.NORM.S.INV(1-$P$1),FALSE)/(1-$P$1)*J69 -> 1.7362836 | Q69: =_xlfn.NORM.S.DIST(_xlfn.NORM.S.INV(1-$R$1),FALSE)/(1-$R$1)*J69 -> 2.2434377 | R69: =IF(C69*100<-N69,1,0) -> 0 | S69: =IF(C69*100<-O69,1,0) -> 0 | Z69: =-N69 -> -1.3845516 | AA69: =-O69 -> -1.9581978
... B253: ='1.RETURNS'!A254 -> 18-Dec-2023 | C253: ='1.RETURNS'!D254 -> 0.0049861947 | D253: =STDEV(C234:C253) -> 0.010138671 | E253: =D253*SQRT(252) -> 0.16094642 | F253: =IF(E253="—","",IF(E253>=0.25,"■ HIGH VOLATILITY",IF(E253>=0.17,"▲ ELEVATED",""))) | G253: =C253^2 -> 2.4862138e-05 | I253: =$I$1+$K$1*G252+$M$1*I252 -> 9.396721e-05 | J253: =SQRT(I253)*100 -> 0.96936685 | K253: =J253*SQRT(252) -> 15.388222 | L253: =K253/100 -> 0.15388222 | N253: =-_xlfn.NORM.S.INV(1-$P$1)*J253 -> 1.5944666 | O253: =-_xlfn.NORM.S.INV(1-$R$1)*J253 -> 2.2550845 | P253: =_xlfn.NORM.S.DIST(_xlfn.NORM.S.INV(1-$P$1),FALSE)/(1-$P$1)*J253 -> 1.9995254 | Q253: =_xlfn.NORM.S.DIST(_xlfn.NORM.S.INV(1-$R$1),FALSE)/(1-$R$1)*J253 -> 2.5835703 | R253: =IF(C253*100<-N253,1,0) -> 0 | S253: =IF(C253*100<-O253,1,0) -> 0 | Z253: =-N253 -> -1.5944666 | AA253: =-O253 -> -2.2550845
